{"type": "FeatureCollection", "name": "export_asan.geojson", "features": [{"geometry": {"type": "Point", "coordinates": [27.3714525691298, 44.4042779853689]}, "type": "Feature", "properties": {"Nivel": 2, "Form\u0103": "Vale", "marker-color": "#e55b5b", "Tip": "asan", "Nume": "Valea lui Asan", "Varianta 1": {"Nume": "Valea lui Asan", "Limb\u0103": "Limba rom\u00e2n\u0103", "Hart\u0103": "PDT"}, "ID": 3310, "Jude\u021b": "Calarasi"}}, {"geometry": {"type": "Point", "coordinates": [23.4131900653214, 44.0155177020373]}, "type": "Feature", "properties": {"Nivel": 2, "Form\u0103": "\u00cen\u0103l\u021bime", "marker-color": "#e55b5b", "Tip": "asan", "Nume": "M\u0103gura Asan", "Varianta 1": {"Nume": "M\u0103gura Asan", "Limb\u0103": "Limba rom\u00e2n\u0103", "Hart\u0103": "PDT"}, "ID": 3344, "Jude\u021b": "Dolj"}}]}