{"type": "FeatureCollection", "name": "export_jide\u0219ti.geojson", "features": [{"geometry": {"type": "Point", "coordinates": [26.5780831396091, 46.9031352863592]}, "type": "Feature", "properties": {"Nivel": 5, "Form\u0103": "Localitate", "marker-color": "#e55b5b", "Tip": "jide\u0219ti", "Nume": "Jide\u0219ti", "Varianta 1": {"Nume": "Jide\u0219ti", "Limb\u0103": "Limba rom\u00e2n\u0103", "Hart\u0103": "Moldova (1892-1898)"}, "ID": 9624, "Jude\u021b": "Neamt"}}]}