{"type": "FeatureCollection", "name": "export_secuieu.geojson", "features": [{"geometry": {"type": "Point", "coordinates": [25.246250060026, 46.7172472506345]}, "type": "Feature", "properties": {"Nivel": 3, "Form\u0103": "Vale", "marker-color": "#e55b5b", "Tip": "secuieu", "Nume": "Secuieul", "Varianta 1": {"Nume": "Secuieul", "Limb\u0103": "Limba rom\u00e2n\u0103", "Hart\u0103": "Geomil 25000"}, "ID": 5397, "Jude\u021b": "Mures"}}]}