{"type": "FeatureCollection", "name": "export_ardelean.geojson", "features": [{"geometry": {"type": "Point", "coordinates": [26.0946390340724, 46.5415627745999]}, "type": "Feature", "properties": {"Nivel": 3, "Form\u0103": "Poian\u0103", "marker-color": "#e55b5b", "Tip": "ardelean", "Nume": "Poiana Ardeleanului", "Varianta 2": {"Nume": "Poiana Ardeleanului", "Limb\u0103": "Limba rom\u00e2n\u0103", "Hart\u0103": "PDT"}, "Varianta 1": {"Nume": "Poiana Ardeleanului", "Limb\u0103": "Limba rom\u00e2n\u0103", "Hart\u0103": "Geomil 25000"}, "ID": 4550, "Jude\u021b": "Bacau"}}, {"geometry": {"type": "Point", "coordinates": [26.8841016264903, 45.2745564707663]}, "type": "Feature", "properties": {"Nivel": 3, "Form\u0103": "Deal", "marker-color": "#e55b5b", "Tip": "ardelean", "Nume": "Dealul Ardeleanului", "Varianta 1": {"Nume": "Dealul Ardeleanului", "Limb\u0103": "Limba rom\u00e2n\u0103", "Hart\u0103": "Geomil 25000"}, "ID": 2087, "Jude\u021b": "Buzau"}}, {"geometry": {"type": "Point", "coordinates": [22.6677138841708, 45.35512561887]}, "type": "Feature", "properties": {"Nivel": 3, "Form\u0103": "\u00cen\u0103l\u021bime", "marker-color": "#e55b5b", "Tip": "ardelean", "Nume": "V\u00e2rfu Ardeleanului", "Varianta 1": {"Nume": "V\u00e2rfu Ardeleanului", "Limb\u0103": "Limba rom\u00e2n\u0103", "Hart\u0103": "Geomil 25000"}, "ID": 6099, "Jude\u021b": "Hunedoara"}}, {"geometry": {"type": "Point", "coordinates": [23.0961492375322, 47.5844073722337]}, "type": "Feature", "properties": {"Nivel": 3, "Form\u0103": "Deal", "marker-color": "#e55b5b", "Tip": "ardelean", "Nume": "Dealu Ardeleanului", "Varianta 1": {"Nume": "Dealu Ardeleanului", "Limb\u0103": "Limba rom\u00e2n\u0103", "Hart\u0103": "Imperiul Habsburgic (1887)"}, "ID": 10827, "Jude\u021b": "Maramures"}}, {"geometry": {"type": "Point", "coordinates": [23.4898121680122, 47.4889398243495]}, "type": "Feature", "properties": {"Nivel": 3, "Form\u0103": "Altele", "marker-color": "#e55b5b", "Tip": "ardelean", "Nume": "Moara Ardeleanului", "Varianta 1": {"Nume": "Moara Ardeleanului", "Limb\u0103": "Limba rom\u00e2n\u0103", "Hart\u0103": "Imperiul Habsburgic (1887)"}, "ID": 10561, "Jude\u021b": "Maramures"}}, {"geometry": {"type": "Point", "coordinates": [23.4060208789644, 47.7621291953181]}, "type": "Feature", "properties": {"Nivel": 3, "Form\u0103": "Vale", "marker-color": "#e55b5b", "Tip": "ardelean", "Nume": "Valea Ardeleanu", "Varianta 1": {"Nume": "Valea Ardeleanu", "Limb\u0103": "Limba rom\u00e2n\u0103", "Hart\u0103": "Geomil 25000"}, "ID": 12348, "Jude\u021b": "Maramures"}}, {"geometry": {"type": "Point", "coordinates": [26.1650597816616, 46.9595270304811]}, "type": "Feature", "properties": {"Nivel": 3, "Form\u0103": "Vale", "marker-color": "#e55b5b", "Tip": "ardelean", "Nume": "Ardeleanul", "Varianta 1": {"Nume": "Ardeleanul", "Limb\u0103": "Limba rom\u00e2n\u0103", "Hart\u0103": "Geomil 25000"}, "ID": 13265, "Jude\u021b": "Neamt"}}, {"geometry": {"type": "Point", "coordinates": [26.9608162543016, 46.9476959789993]}, "type": "Feature", "properties": {"Nivel": 3, "Form\u0103": "Altele", "marker-color": "#e55b5b", "Tip": "ardelean", "Nume": "F\u00e2nt\u00e2na Ardeleanului", "Varianta 1": {"Nume": "F\u00e2nt\u00e2na Ardeleanului", "Limb\u0103": "Limba rom\u00e2n\u0103", "Hart\u0103": "PDT"}, "ID": 3891, "Jude\u021b": "Neamt"}}, {"geometry": {"type": "Point", "coordinates": [26.9559093171244, 45.8196934322979]}, "type": "Feature", "properties": {"Nivel": 3, "Form\u0103": "\u00cen\u0103l\u021bime", "marker-color": "#e55b5b", "Tip": "ardelean", "Nume": "Plaiul Ardeleanului", "Varianta 1": {"Nume": "Plaiul Ardeleanului", "Limb\u0103": "Limba rom\u00e2n\u0103", "Hart\u0103": "Geomil 25000"}, "ID": 768, "Jude\u021b": "Vrancea"}}]}