{"type": "FeatureCollection", "name": "export_pecini\u0219ca.geojson", "features": [{"geometry": {"type": "Point", "coordinates": [22.4037581060376, 44.8595907199728]}, "type": "Feature", "properties": {"Nivel": 3, "Form\u0103": "Localitate", "marker-color": "#e55b5b", "Tip": "pecini\u0219ca", "Nume": "Pecini\u0219ca", "Varianta 1": {"Nume": "Pecini\u0219ca", "Limb\u0103": "Limba rom\u00e2n\u0103", "Hart\u0103": "Geomil 25000"}, "ID": 12649, "Jude\u021b": "Caras Severin"}}]}