{"type": "FeatureCollection", "name": "export_leb\u0103doi.geojson", "features": [{"geometry": {"type": "Point", "coordinates": [28.0030909846516, 44.8590924201353]}, "type": "Feature", "properties": {"Nivel": 3, "Form\u0103": "Lac", "marker-color": "#e55b5b", "Tip": "leb\u0103doi", "Nume": "Ezeru Leb\u0103doiu", "Varianta 1": {"Nume": "Ezeru Leb\u0103doiu", "Limb\u0103": "Limba rom\u00e2n\u0103", "Hart\u0103": "PDT"}, "ID": 3488, "Jude\u021b": "Braila"}}]}