{"type": "FeatureCollection", "name": "export_g\u0103man.geojson", "features": [{"geometry": {"type": "Point", "coordinates": [25.6958205345196, 44.6556100692869]}, "type": "Feature", "properties": {"Nivel": 3, "Form\u0103": "Localitate", "marker-color": "#e55b5b", "Tip": "g\u0103m\u0103ne\u0219ti", "Nume": "G\u0103m\u0103ne\u0219ti", "Varianta 1": {"Nume": "G\u0103m\u0103ne\u0219ti", "Limb\u0103": "Limba rom\u00e2n\u0103", "Hart\u0103": "ANCPI"}, "ID": 15841, "Jude\u021b": "Dambovita"}}, {"geometry": {"type": "Point", "coordinates": [23.2498794048913, 44.2030133233511]}, "type": "Feature", "properties": {"Nivel": 2, "Form\u0103": "Vale", "marker-color": "#5be55b", "Tip": "g\u0103man", "Nume": "Valea lui G\u0103man", "Varianta 1": {"Nume": "Valea lui G\u0103man", "Limb\u0103": "Limba rom\u00e2n\u0103", "Hart\u0103": "PDT"}, "ID": 8093, "Jude\u021b": "Dolj"}}, {"geometry": {"type": "Point", "coordinates": [23.425282665759, 45.1367820780666]}, "type": "Feature", "properties": {"Nivel": 3, "Form\u0103": "Localitate", "marker-color": "#5b5be5", "Tip": "g\u0103mani", "Nume": "G\u00e2m\u00e2ni", "Varianta 2": {"Nume": "G\u0103mani", "Limb\u0103": "Limba rom\u00e2n\u0103", "Hart\u0103": "ANCPI"}, "Varianta 1": {"Nume": "G\u00e2m\u00e2ni", "Limb\u0103": "Limba rom\u00e2n\u0103", "Hart\u0103": "Austriac\u0103"}, "ID": 14765, "Jude\u021b": "Gorj"}}, {"geometry": {"type": "Point", "coordinates": [24.9082417727113, 43.9657170187585]}, "type": "Feature", "properties": {"Nivel": 3, "Form\u0103": "\u00cen\u0103l\u021bime", "marker-color": "#e55b5b", "Tip": "g\u0103m\u0103ne\u0219ti", "Nume": "M\u0103gura G\u0103m\u0103ne\u0219tilor", "Varianta 1": {"Nume": "M\u0103gura G\u0103m\u0103ne\u0219tilor", "Limb\u0103": "Limba rom\u00e2n\u0103", "Hart\u0103": "PDT"}, "ID": 14959, "Jude\u021b": "Teleorman"}}]}