{"type": "FeatureCollection", "name": "export_g\u0103man.geojson", "features": [{"geometry": {"type": "Point", "coordinates": [23.2498794048913, 44.2030133233511]}, "type": "Feature", "properties": {"Nivel": 2, "Form\u0103": "Vale", "marker-color": "#e55b5b", "Tip": "g\u0103man", "Nume": "Valea lui G\u0103man", "Varianta 1": {"Nume": "Valea lui G\u0103man", "Limb\u0103": "Limba rom\u00e2n\u0103", "Hart\u0103": "PDT"}, "ID": 8093, "Jude\u021b": "Dolj"}}]}