{"type": "FeatureCollection", "name": "export_s\u0103v\u00e2rlui.geojson", "features": [{"geometry": {"type": "Point", "coordinates": [25.7850051313651, 43.7671800967955]}, "type": "Feature", "properties": {"Nivel": 2, "Form\u0103": "Ap\u0103-deal-c\u00e2mpie", "marker-color": "#e55b5b", "Tip": "s\u0103v\u00e2rlui", "Nume": "\u0218owerliu", "Varianta 1": {"Nume": "\u0218owerliu", "Limb\u0103": "Limba rom\u00e2n\u0103", "Hart\u0103": "Austriac\u0103"}, "ID": 14394, "Jude\u021b": "Giurgiu"}}]}