{"type": "FeatureCollection", "name": "export_b\u0103can.geojson", "features": [{"geometry": {"type": "Point", "coordinates": [22.2817952957048, 46.3663592014322]}, "type": "Feature", "properties": {"Nivel": 3, "Form\u0103": "Vale", "marker-color": "#e55b5b", "Tip": "b\u0103can", "Nume": "Izvorul B\u0103canului", "Varianta 1": {"Nume": "Izvorul B\u0103canului", "Limb\u0103": "Limba rom\u00e2n\u0103", "Hart\u0103": "PDT"}, "ID": 15260, "Jude\u021b": "Arad"}}, {"geometry": {"type": "Point", "coordinates": [26.1303049199152, 44.7874984478985]}, "type": "Feature", "properties": {"Nivel": 3, "Form\u0103": "Altele", "marker-color": "#e55b5b", "Tip": "b\u0103can", "Nume": "Ograda B\u0103canului", "Varianta 1": {"Nume": "Ograda B\u0103canului", "Limb\u0103": "Limba rom\u00e2n\u0103", "Hart\u0103": "PDT"}, "ID": 15258, "Jude\u021b": "Prahova"}}]}