{"type": "FeatureCollection", "name": "export_b\u0103can.geojson", "features": [{"geometry": {"type": "Point", "coordinates": [22.2817952957048, 46.3663592014322]}, "type": "Feature", "properties": {"Nivel": 3, "Form\u0103": "Vale", "marker-color": "#e55b5b", "Tip": "b\u0103can", "Nume": "Izvorul B\u0103canului", "Varianta 1": {"Nume": "Izvorul B\u0103canului", "Limb\u0103": "Limba rom\u00e2n\u0103", "Hart\u0103": "PDT"}, "ID": 15260, "Jude\u021b": "Arad"}}, {"geometry": {"type": "Point", "coordinates": [26.943319933176, 45.1042021514743]}, "type": "Feature", "properties": {"Nivel": 3, "Form\u0103": "Ap\u0103-deal-c\u00e2mpie", "marker-color": "#e55b5b", "Tip": "b\u0103can", "Nume": "Cotul B\u0103canului", "Varianta 2": {"Nume": "Cot. Bacan", "Limb\u0103": "Limba rom\u00e2n\u0103", "Hart\u0103": "PDT"}, "Varianta 1": {"Nume": "Cotul B\u0103canului", "Limb\u0103": "Limba rom\u00e2n\u0103", "Hart\u0103": "ANCPI"}, "ID": 15408, "Jude\u021b": "Buzau"}}, {"geometry": {"type": "Point", "coordinates": [25.8247233189109, 44.4129221456082]}, "type": "Feature", "properties": {"Nivel": 3, "Form\u0103": "Localitate", "marker-color": "#e55b5b", "Tip": "b\u0103can", "Nume": "B\u0103canul", "Varianta 1": {"Nume": "B\u0103canul", "Limb\u0103": "Limba rom\u00e2n\u0103", "Hart\u0103": "PDT"}, "ID": 15406, "Jude\u021b": "Giurgiu"}}, {"geometry": {"type": "Point", "coordinates": [26.6952613461949, 44.6626846134698]}, "type": "Feature", "properties": {"Nivel": 3, "Form\u0103": "Ap\u0103-deal-c\u00e2mpie", "marker-color": "#e55b5b", "Tip": "b\u0103can", "Nume": "Cotul la B\u0103can", "Varianta 1": {"Nume": "Cotul la B\u0103can", "Limb\u0103": "Limba rom\u00e2n\u0103", "Hart\u0103": "PDT"}, "ID": 15426, "Jude\u021b": "Ialomita"}}, {"geometry": {"type": "Point", "coordinates": [24.3279707781021, 44.8115979283261]}, "type": "Feature", "properties": {"Nivel": 3, "Form\u0103": "Altele", "marker-color": "#e55b5b", "Tip": "b\u0103can", "Nume": "B\u0103canul", "Varianta 1": {"Nume": "B\u0103canul", "Limb\u0103": "Limba rom\u00e2n\u0103", "Hart\u0103": "PDT"}, "ID": 15755, "Jude\u021b": "Olt"}}, {"geometry": {"type": "Point", "coordinates": [26.1303049199152, 44.7874984478985]}, "type": "Feature", "properties": {"Nivel": 3, "Form\u0103": "Altele", "marker-color": "#e55b5b", "Tip": "b\u0103can", "Nume": "Ograda B\u0103canului", "Varianta 1": {"Nume": "Ograda B\u0103canului", "Limb\u0103": "Limba rom\u00e2n\u0103", "Hart\u0103": "PDT"}, "ID": 15258, "Jude\u021b": "Prahova"}}]}