{"type": "FeatureCollection", "name": "export_giurgi\u021ba.geojson", "features": [{"geometry": {"type": "Point", "coordinates": [23.6289511227214, 44.0141671885294]}, "type": "Feature", "properties": {"Nivel": 3, "Form\u0103": "Localitate", "marker-color": "#e55b5b", "Tip": "giurgi\u021ba", "Nume": "Giurgi\u021ba", "Varianta 1": {"Nume": "Giurgi\u021ba", "Limb\u0103": "Limba rom\u00e2n\u0103", "Hart\u0103": "PDT"}, "ID": 15292, "Jude\u021b": "Dolj"}}]}