{"type": "FeatureCollection", "name": "export_purcea.geojson", "features": [{"geometry": {"type": "Point", "coordinates": [24.0567663242187, 44.815037942961]}, "type": "Feature", "properties": {"Nivel": 3, "Form\u0103": "Vale", "marker-color": "#e55b5b", "Tip": "purcea", "Nume": "Valea Purceaua", "Varianta 1": {"Nume": "Valea Purceaua", "Limb\u0103": "Limba rom\u00e2n\u0103", "Hart\u0103": "Geomil 25000"}, "ID": 11039, "Jude\u021b": "Valcea"}}]}