{"type": "FeatureCollection", "name": "export_comori\u0219te.geojson", "features": [{"geometry": {"type": "Point", "coordinates": [23.1902714176932, 47.2260607649536]}, "type": "Feature", "properties": {"Nivel": 3, "Form\u0103": "Altele", "marker-color": "#e55b5b", "Tip": "comori\u0219te", "Nume": "Comori\u0219tea", "Varianta 1": {"Nume": "Comori\u0219tea", "Limb\u0103": "Limba rom\u00e2n\u0103", "Hart\u0103": "PDT"}, "ID": 7562, "Jude\u021b": "Salaj"}}, {"geometry": {"type": "Point", "coordinates": [22.501147683184, 44.8708625124359]}, "type": "Feature", "properties": {"Nivel": 3, "Form\u0103": "\u00cen\u0103l\u021bime", "marker-color": "#e55b5b", "Tip": "comori\u0219te", "Nume": "Comori\u0219te", "Varianta 1": {"Nume": "Comori\u0219te", "Limb\u0103": "Limba rom\u00e2n\u0103", "Hart\u0103": "Geomil 25000"}, "ID": 9440, "Jude\u021b": "Mehedinti"}}, {"geometry": {"type": "Point", "coordinates": [22.5997737035905, 44.6498670265462]}, "type": "Feature", "properties": {"Nivel": 3, "Form\u0103": "Altele", "marker-color": "#e55b5b", "Tip": "comori\u0219te", "Nume": "Comori\u0219tea", "Varianta 1": {"Nume": "Comori\u0219tea", "Limb\u0103": "Limba rom\u00e2n\u0103", "Hart\u0103": "Geomil 25000"}, "ID": 11160, "Jude\u021b": "Mehedinti"}}, {"geometry": {"type": "Point", "coordinates": [22.5519000029972, 44.8450235532612]}, "type": "Feature", "properties": {"Nivel": 3, "Form\u0103": "Deal", "marker-color": "#e55b5b", "Tip": "comori\u0219te", "Nume": "Dealul Comori\u0219te", "Varianta 1": {"Nume": "Dealul Comori\u0219te", "Limb\u0103": "Limba rom\u00e2n\u0103", "Hart\u0103": "ANCPI"}, "ID": 12465, "Jude\u021b": "Mehedinti"}}, {"geometry": {"type": "Point", "coordinates": [22.922646979408, 46.9926050590026]}, "type": "Feature", "properties": {"Nivel": 3, "Form\u0103": "Deal", "marker-color": "#e55b5b", "Tip": "comori\u0219te", "Nume": "Comoristi B.", "Varianta 1": {"Nume": "Comoristi B.", "Limb\u0103": "Limba rom\u00e2n\u0103", "Hart\u0103": "Transilvania (1769-1773)"}, "ID": 13425, "Jude\u021b": "Salaj"}}]}