{"type": "FeatureCollection", "name": "export_b\u0103rc\u0103ne\u0219ti.geojson", "features": [{"geometry": {"type": "Point", "coordinates": [24.5456549224998, 44.3054824435728]}, "type": "Feature", "properties": {"Nivel": 3, "Form\u0103": "Localitate", "marker-color": "#e55b5b", "Tip": "b\u0103rc\u0103ne\u0219ti", "Nume": "B\u0103rc\u0103ne\u0219ti", "Varianta 1": {"Nume": "B\u0103rc\u0103ne\u0219ti", "Limb\u0103": "Limba rom\u00e2n\u0103", "Hart\u0103": "Geomil 25000"}, "ID": 2998, "Jude\u021b": "Olt"}}, {"geometry": {"type": "Point", "coordinates": [26.6506827481802, 44.6387358064137]}, "type": "Feature", "properties": {"Nivel": 3, "Form\u0103": "Localitate", "marker-color": "#e55b5b", "Tip": "b\u0103rc\u0103ne\u0219ti", "Nume": "B\u0103rc\u0103ne\u0219ti", "Varianta 1": {"Nume": "B\u0103rc\u0103ne\u0219ti", "Limb\u0103": "Limba rom\u00e2n\u0103", "Hart\u0103": "Geomil 25000"}, "ID": 3179, "Jude\u021b": "Ialomita"}}, {"geometry": {"type": "Point", "coordinates": [24.0304243719221, 44.805876357069]}, "type": "Feature", "properties": {"Nivel": 3, "Form\u0103": "Localitate", "marker-color": "#e55b5b", "Tip": "b\u0103rc\u0103ne\u0219ti", "Nume": "B\u0103rc\u0103ne\u0219ti", "Varianta 2": {"Nume": "B\u00e2rc\u00e2ne\u0219ti", "Limb\u0103": "Limba rom\u00e2n\u0103", "Hart\u0103": "Austriac\u0103"}, "Varianta 3": {"Nume": "B\u0103rc\u0103ne\u0219ti", "Limb\u0103": "Limba rom\u00e2n\u0103", "Hart\u0103": "PDT"}, "Varianta 1": {"Nume": "B\u0103rc\u0103ne\u0219ti", "Limb\u0103": "Limba rom\u00e2n\u0103", "Hart\u0103": "Geomil 25000"}, "ID": 5833, "Jude\u021b": "Valcea"}}, {"geometry": {"type": "Point", "coordinates": [22.774172481033, 44.8175780199224]}, "type": "Feature", "properties": {"Nivel": 3, "Form\u0103": "Localitate", "marker-color": "#e55b5b", "Tip": "b\u0103rc\u0103ne\u0219ti", "Nume": "B\u0103rc\u0103ne\u0219ti", "Varianta 1": {"Nume": "B\u0103rc\u0103ne\u0219ti", "Limb\u0103": "Limba rom\u00e2n\u0103", "Hart\u0103": "PDT"}, "ID": 8412, "Jude\u021b": "Mehedinti"}}, {"geometry": {"type": "Point", "coordinates": [26.0502972424822, 44.8813496572617]}, "type": "Feature", "properties": {"Nivel": 3, "Form\u0103": "Localitate", "marker-color": "#e55b5b", "Tip": "b\u0103rc\u0103ne\u0219ti", "Nume": "B\u0103rc\u0103ne\u0219ti", "Varianta 2": {"Nume": "B\u0103rc\u0103ne\u0219ti", "Limb\u0103": "Limba rom\u00e2n\u0103", "Hart\u0103": "PDT"}, "Varianta 1": {"Nume": "B\u0103rc\u0103ne\u0219ti", "Limb\u0103": "Limba rom\u00e2n\u0103", "Hart\u0103": "Geomil 25000"}, "ID": 8795, "Jude\u021b": "Prahova"}}, {"geometry": {"type": "Point", "coordinates": [26.5911898348785, 46.7158304667601]}, "type": "Feature", "properties": {"Nivel": 3, "Form\u0103": "Localitate", "marker-color": "#e55b5b", "Tip": "b\u0103rc\u0103ne\u0219ti", "Nume": "B\u0103rc\u0103ne\u0219ti", "Varianta 2": {"Nume": "B\u0103rc\u0103ne\u0219ti", "Limb\u0103": "Limba rom\u00e2n\u0103", "Hart\u0103": "Geomil 25000"}, "Varianta 1": {"Nume": "B\u0103rc\u0103ne\u0219ti", "Limb\u0103": "Limba rom\u00e2n\u0103", "Hart\u0103": "Moldova (1892-1898)"}, "ID": 9948, "Jude\u021b": "Neamt"}}]}