{"type": "FeatureCollection", "name": "export_s\u0103cuiasaca.geojson", "features": [{"geometry": {"type": "Point", "coordinates": [23.915709939032, 47.8184258717981]}, "type": "Feature", "properties": {"Nivel": 3, "Form\u0103": "Altele", "marker-color": "#e55b5b", "Tip": "s\u0103cuiasaca", "Nume": "S\u0103cuiasca", "Varianta 1": {"Nume": "S\u0103cuiasca", "Limb\u0103": "Limba rom\u00e2n\u0103", "Hart\u0103": "Geomil 25000"}, "ID": 7168, "Jude\u021b": "Maramures"}}, {"geometry": {"type": "Point", "coordinates": [24.3953265281137, 46.5037753441531]}, "type": "Feature", "properties": {"Nivel": 3, "Form\u0103": "Localitate", "marker-color": "#e55b5b", "Tip": "s\u0103cuiasaca", "Nume": "\u0218eu\u0219a s\u0103cuieasc\u0103", "Varianta 1": {"Nume": "\u0218eu\u0219a s\u0103cuieasc\u0103", "Limb\u0103": "Limba rom\u00e2n\u0103", "Hart\u0103": "Imperiul Habsburgic (1887)"}, "ID": 10658, "Jude\u021b": "Mures"}}]}