{"type": "FeatureCollection", "name": "export_zap\u0103d.geojson", "features": [{"geometry": {"type": "Point", "coordinates": [22.5994705056215, 44.8481206745614]}, "type": "Feature", "properties": {"Nivel": 3, "Form\u0103": "Deal", "marker-color": "#e55b5b", "Tip": "zap\u0103d", "Nume": "Dealu Zap\u0103d", "Varianta 1": {"Nume": "Dealu Zap\u0103d", "Limb\u0103": "Limba rom\u00e2n\u0103", "Hart\u0103": "Geomil 25000"}, "ID": 12466, "Jude\u021b": "Mehedinti"}}]}