{"type": "FeatureCollection", "name": "export_caba.geojson", "features": [{"geometry": {"type": "Point", "coordinates": [27.4396976211841, 46.2036980353038]}, "type": "Feature", "properties": {"Nivel": 3, "Form\u0103": "Localitate", "marker-color": "#5be5e5", "Tip": "c\u0103be\u0219ti", "Nume": "C\u0103be\u0219ti", "Varianta 1": {"Nume": "C\u0103be\u0219ti", "Limb\u0103": "Limba rom\u00e2n\u0103", "Hart\u0103": "PDT"}, "ID": 14659, "Jude\u021b": "Bacau"}}, {"geometry": {"type": "Point", "coordinates": [22.3713403550348, 46.7704276315338]}, "type": "Feature", "properties": {"Nivel": 3, "Form\u0103": "Localitate", "marker-color": "#5be5e5", "Tip": "c\u0103be\u0219ti", "Nume": "C\u0103be\u0219ti", "Varianta 2": {"Nume": "Kebe\u0219d", "Limb\u0103": "Limba rom\u00e2n\u0103", "Hart\u0103": "Ungar\u0103 1869"}, "Varianta 3": {"Nume": "Gebesd", "Limb\u0103": "Limba rom\u00e2n\u0103", "Hart\u0103": "Ungaria (1782\u20131785)"}, "Varianta 1": {"Nume": "C\u0103be\u0219ti", "Limb\u0103": "Limba rom\u00e2n\u0103", "Hart\u0103": "PDT"}, "ID": 14662, "Jude\u021b": "Bihor"}}, {"geometry": {"type": "Point", "coordinates": [22.7610325102434, 45.9809174076712]}, "type": "Feature", "properties": {"Nivel": 2, "Form\u0103": "Deal", "marker-color": "#e55b5b", "Tip": "caba", "Nume": "Dealul Caba", "Varianta 1": {"Nume": "Dealul Caba", "Limb\u0103": "Limba rom\u00e2n\u0103", "Hart\u0103": "ANCPI"}, "ID": 14738, "Jude\u021b": "Hunedoara"}}, {"geometry": {"type": "Point", "coordinates": [22.7617418407213, 45.9956212455038]}, "type": "Feature", "properties": {"Nivel": 3, "Form\u0103": "Localitate", "marker-color": "#5be5e5", "Tip": "c\u0103be\u0219ti", "Nume": "C\u0103be\u0219ti", "Varianta 2": {"Nume": "C\u0103be\u0219ti", "Limb\u0103": "Limba rom\u00e2n\u0103", "Hart\u0103": "PDT"}, "Varianta 3": {"Nume": "Cabe\u0219d", "Limb\u0103": "Limba rom\u00e2n\u0103", "Hart\u0103": "Transilvania (1869-1870)"}, "Varianta 1": {"Nume": "C\u0103be\u0219ti", "Limb\u0103": "Limba rom\u00e2n\u0103", "Hart\u0103": "ANCPI"}, "ID": 14661, "Varianta 4": {"Nume": "Kabest", "Limb\u0103": "Limba rom\u00e2n\u0103", "Hart\u0103": "Transilvania (1769-1773)"}, "Jude\u021b": "Hunedoara"}}, {"geometry": {"type": "Point", "coordinates": [27.5357878890703, 46.0718961295031]}, "type": "Feature", "properties": {"Nivel": 2, "Form\u0103": "Deal", "marker-color": "#e55b5b", "Tip": "caba", "Nume": "Dealul Caba", "Varianta 1": {"Nume": "Dealul Caba", "Limb\u0103": "Limba rom\u00e2n\u0103", "Hart\u0103": "PDT"}, "ID": 14833, "Jude\u021b": "Vaslui"}}, {"geometry": {"type": "Point", "coordinates": [26.924393389634, 45.7274172255961]}, "type": "Feature", "properties": {"Nivel": 2, "Form\u0103": "Poian\u0103", "marker-color": "#e55b5b", "Tip": "caba", "Nume": "Poiana E. Caba", "Varianta 1": {"Nume": "Poiana E. Caba", "Limb\u0103": "Limba rom\u00e2n\u0103", "Hart\u0103": "PDT"}, "ID": 14989, "Jude\u021b": "Vrancea"}}]}