{"type": "FeatureCollection", "name": "export_arici.geojson", "features": [{"geometry": {"type": "Point", "coordinates": [26.8314512508176, 44.9574562500151]}, "type": "Feature", "properties": {"Nivel": 2, "Form\u0103": "\u00cen\u0103l\u021bime", "marker-color": "#e55b5b", "Tip": "arici", "Nume": "Movila Ariciului", "Varianta 2": {"Nume": "Movila Ariciului", "Limb\u0103": "Limba rom\u00e2n\u0103", "Hart\u0103": "Geomil 25000"}, "Varianta 3": {"Nume": "\u043a\u0443\u0440\u0433. \u0410\u0440\u0438\u0447\u0443 (mov. Ariciu)", "Limb\u0103": "Limba rom\u00e2n\u0103", "Hart\u0103": "Sovietic\u0103"}, "Varianta 1": {"Nume": "Movila Ariciului", "Limb\u0103": "Limba rom\u00e2n\u0103", "Hart\u0103": "PDT"}, "ID": 63, "Jude\u021b": "Buzau"}}, {"geometry": {"type": "Point", "coordinates": [22.2222597706336, 45.2658204212246]}, "type": "Feature", "properties": {"Nivel": 2, "Form\u0103": "\u00cen\u0103l\u021bime", "marker-color": "#e55b5b", "Tip": "arici", "Nume": "T\u00e2lva Ariciului", "Varianta 1": {"Nume": "T\u00e2lva Ariciului", "Limb\u0103": "Limba rom\u00e2n\u0103", "Hart\u0103": "PDT"}, "ID": 12701, "Jude\u021b": "Caras Severin"}}, {"geometry": {"type": "Point", "coordinates": [27.1271541821557, 47.3946777968361]}, "type": "Feature", "properties": {"Nivel": 2, "Form\u0103": "Deal", "marker-color": "#e55b5b", "Tip": "arici", "Nume": "Dealul Aricilor", "Varianta 1": {"Nume": "Dealul Aricilor", "Limb\u0103": "Limba rom\u00e2n\u0103", "Hart\u0103": "Geomil 25000"}, "ID": 2438, "Jude\u021b": "Iasi"}}, {"geometry": {"type": "Point", "coordinates": [26.256764256005, 45.1202070362878]}, "type": "Feature", "properties": {"Nivel": 2, "Form\u0103": "Vale", "marker-color": "#e55b5b", "Tip": "arici", "Nume": "Valea Ariciului", "Varianta 1": {"Nume": "Valea Ariciului", "Limb\u0103": "Limba rom\u00e2n\u0103", "Hart\u0103": "PDT"}, "ID": 32, "Jude\u021b": "Prahova"}}, {"geometry": {"type": "Point", "coordinates": [24.0250087799759, 45.3883999312609]}, "type": "Feature", "properties": {"Nivel": 2, "Form\u0103": "\u00cen\u0103l\u021bime", "marker-color": "#e55b5b", "Tip": "arici", "Nume": "Gruiul. Ariciului", "Varianta 1": {"Nume": "Gruiul. Ariciului", "Limb\u0103": "Limba rom\u00e2n\u0103", "Hart\u0103": "Geomil 25000"}, "ID": 1174, "Jude\u021b": "Valcea"}}]}