{"type": "FeatureCollection", "name": "export_\u0219erp\u0103rie.geojson", "features": [{"geometry": {"type": "Point", "coordinates": [26.8408598376038, 48.071822621939]}, "type": "Feature", "properties": {"Nivel": 3, "Form\u0103": "Vale", "marker-color": "#e55b5b", "Tip": "\u0219erp\u0103rie", "Nume": "Valea \u0218erp\u0103riei", "Varianta 1": {"Nume": "Valea \u0218erp\u0103riei", "Limb\u0103": "Limba rom\u00e2n\u0103", "Hart\u0103": "Geomil 25000"}, "ID": 2397, "Jude\u021b": "Botosani"}}, {"geometry": {"type": "Point", "coordinates": [26.9066755860692, 47.9882459964697]}, "type": "Feature", "properties": {"Nivel": 3, "Form\u0103": "Deal", "marker-color": "#e55b5b", "Tip": "\u0219erp\u0103rie", "Nume": "Dealul \u0218erp\u0103riei", "Varianta 1": {"Nume": "Dealul \u0218erp\u0103riei", "Limb\u0103": "Limba rom\u00e2n\u0103", "Hart\u0103": "Geomil 25000"}, "ID": 2405, "Jude\u021b": "Botosani"}}, {"geometry": {"type": "Point", "coordinates": [27.213085951529, 44.2117747252118]}, "type": "Feature", "properties": {"Nivel": 3, "Form\u0103": "Ap\u0103-deal-c\u00e2mpie", "marker-color": "#e55b5b", "Tip": "\u0219erp\u0103rie", "Nume": "Jap\u0219a \u0218serp\u0103riile", "Varianta 1": {"Nume": "Jap\u0219a \u0218serp\u0103riile", "Limb\u0103": "Limba rom\u00e2n\u0103", "Hart\u0103": "PDT"}, "ID": 3289, "Jude\u021b": "Calarasi"}}, {"geometry": {"type": "Point", "coordinates": [27.2518783994982, 46.1261250809966]}, "type": "Feature", "properties": {"Nivel": 3, "Form\u0103": "Altele", "marker-color": "#e55b5b", "Tip": "\u0219erp\u0103rie", "Nume": "La \u0218erp\u0103rie", "Varianta 1": {"Nume": "La \u0218erp\u0103rie", "Limb\u0103": "Limba rom\u00e2n\u0103", "Hart\u0103": "PDT"}, "ID": 3933, "Jude\u021b": "Vrancea"}}, {"geometry": {"type": "Point", "coordinates": [26.3501965036007, 48.0375291638344]}, "type": "Feature", "properties": {"Nivel": 3, "Form\u0103": "Vale", "marker-color": "#e55b5b", "Tip": "\u0219erp\u0103rie", "Nume": "Valea \u0218erp\u0103riei", "Varianta 1": {"Nume": "Valea \u0218erp\u0103riei", "Limb\u0103": "Limba rom\u00e2n\u0103", "Hart\u0103": "Geomil 25000"}, "ID": 4896, "Jude\u021b": "Botosani"}}, {"geometry": {"type": "Point", "coordinates": [25.7867293199949, 47.2124530415955]}, "type": "Feature", "properties": {"Nivel": 3, "Form\u0103": "\u00cen\u0103l\u021bime", "marker-color": "#e55b5b", "Tip": "\u0219erp\u0103rie", "Nume": "V\u00e2rful \u0218erp\u0103riei", "Varianta 1": {"Nume": "V\u00e2rful \u0218erp\u0103riei", "Limb\u0103": "Limba rom\u00e2n\u0103", "Hart\u0103": "PDT"}, "ID": 6419, "Jude\u021b": "Neamt"}}, {"geometry": {"type": "Point", "coordinates": [25.2868267762574, 45.065238238926]}, "type": "Feature", "properties": {"Nivel": 3, "Form\u0103": "Vale", "marker-color": "#e55b5b", "Tip": "\u0219erp\u0103rie", "Nume": "Valea \u0218erp\u0103ria", "Varianta 1": {"Nume": "Valea \u0218erp\u0103ria", "Limb\u0103": "Limba rom\u00e2n\u0103", "Hart\u0103": "PDT"}, "ID": 8370, "Jude\u021b": "Dambovita"}}, {"geometry": {"type": "Point", "coordinates": [26.9404768488392, 47.8691792285743]}, "type": "Feature", "properties": {"Nivel": 3, "Form\u0103": "\u00cen\u0103l\u021bime", "marker-color": "#e55b5b", "Tip": "\u0219erp\u0103rie", "Nume": "\u0218erp\u0103rie", "Varianta 1": {"Nume": "\u0218erp\u0103rie", "Limb\u0103": "Limba rom\u00e2n\u0103", "Hart\u0103": "Geomil 25000"}, "ID": 11557, "Jude\u021b": "Botosani"}}, {"geometry": {"type": "Point", "coordinates": [26.0774356861438, 47.126074989555]}, "type": "Feature", "properties": {"Nivel": 3, "Form\u0103": "Altele", "marker-color": "#e55b5b", "Tip": "\u0219erp\u0103rie", "Nume": "\u0218erp\u0103ria", "Varianta 1": {"Nume": "\u0218erp\u0103ria", "Limb\u0103": "Limba rom\u00e2n\u0103", "Hart\u0103": "Geomil 25000"}, "ID": 13267, "Jude\u021b": "Neamt"}}, {"geometry": {"type": "Point", "coordinates": [24.4965423042378, 44.2654364955458]}, "type": "Feature", "properties": {"Nivel": 3, "Form\u0103": "Vale", "marker-color": "#e55b5b", "Tip": "\u0219erp\u0103rie", "Nume": "Valea \u0218erp\u0103riei", "Varianta 1": {"Nume": "Valea \u0218erp\u0103riei", "Limb\u0103": "Limba rom\u00e2n\u0103", "Hart\u0103": "Geomil 25000"}, "ID": 14203, "Jude\u021b": "Olt"}}]}