{"type": "FeatureCollection", "name": "export_g\u0103ujani.geojson", "features": [{"geometry": {"type": "Point", "coordinates": [24.9577378007604, 44.5430253521223]}, "type": "Feature", "properties": {"Nivel": 3, "Form\u0103": "Localitate", "marker-color": "#e55b5b", "Tip": "g\u0103ujani", "Nume": "G\u0103ujani", "Varianta 1": {"Nume": "G\u0103ujani", "Limb\u0103": "Limba rom\u00e2n\u0103", "Hart\u0103": "Geomil 25000"}, "ID": 15308, "Jude\u021b": "Arges"}}, {"geometry": {"type": "Point", "coordinates": [25.7090028901345, 43.7389173785021]}, "type": "Feature", "properties": {"Nivel": 3, "Form\u0103": "Localitate", "marker-color": "#e55b5b", "Tip": "g\u0103ujani", "Nume": "G\u0103ujani", "Varianta 1": {"Nume": "G\u0103ujani", "Limb\u0103": "Limba rom\u00e2n\u0103", "Hart\u0103": "ANCPI"}, "ID": 15307, "Jude\u021b": "Giurgiu"}}, {"geometry": {"type": "Point", "coordinates": [24.3754142776778, 45.4565624132095]}, "type": "Feature", "properties": {"Nivel": 3, "Form\u0103": "Localitate", "marker-color": "#e55b5b", "Tip": "g\u0103ujani", "Nume": "G\u0103ujani", "Varianta 1": {"Nume": "G\u0103ujani", "Limb\u0103": "Limba rom\u00e2n\u0103", "Hart\u0103": "ANCPI"}, "ID": 15309, "Jude\u021b": "Valcea"}}]}