{"type": "FeatureCollection", "name": "export_varalia.geojson", "features": [{"geometry": {"type": "Point", "coordinates": [23.6399746323675, 46.2234657604065]}, "type": "Feature", "properties": {"Nivel": 3, "Form\u0103": "Localitate", "marker-color": "#e55b5b", "Tip": "varalia", "Nume": "Diodv\u00e1ralija ", "Varianta 1": {"Nume": "Diodv\u00e1ralija ", "Limb\u0103": "Limba maghiar\u0103", "Hart\u0103": "Transilvania (1769-1773)"}, "ID": 14494, "Jude\u021b": "Alba"}}, {"geometry": {"type": "Point", "coordinates": [24.0427988767842, 47.1174167986918]}, "type": "Feature", "properties": {"Nivel": 3, "Form\u0103": "Localitate", "marker-color": "#e55b5b", "Tip": "varalia", "Nume": "B\u00e1lv\u00e1nyos V\u00e1rallja", "Varianta 1": {"Nume": "B\u00e1lv\u00e1nyos V\u00e1rallja", "Limb\u0103": "Limba maghiar\u0103", "Hart\u0103": "Transilvania (1769-1773)"}, "ID": 14486, "Jude\u021b": "Cluj"}}, {"geometry": {"type": "Point", "coordinates": [23.4473565441725, 47.3865615898802]}, "type": "Feature", "properties": {"Nivel": 3, "Form\u0103": "Localitate", "marker-color": "#e55b5b", "Tip": "varalia", "Nume": "V\u00e1rallya", "Varianta 1": {"Nume": "V\u00e1rallya", "Limb\u0103": "Limba maghiar\u0103", "Hart\u0103": "Ungar\u0103 1869"}, "ID": 13384, "Jude\u021b": "Maramures"}}]}