{"type": "FeatureCollection", "name": "export_varalia.geojson", "features": [{"geometry": {"type": "Point", "coordinates": [23.4473565441725, 47.3865615898802]}, "type": "Feature", "properties": {"Nivel": 3, "Form\u0103": "Localitate", "marker-color": "#e55b5b", "Tip": "varalia", "Nume": "V\u00e1rallya", "Varianta 1": {"Nume": "V\u00e1rallya", "Limb\u0103": "Limba maghiar\u0103", "Hart\u0103": "Ungar\u0103 1869"}, "ID": 13384, "Jude\u021b": "Maramures"}}]}