{"type": "FeatureCollection", "name": "export_beczinegy.geojson", "features": [{"geometry": {"type": "Point", "coordinates": [23.435079163193, 46.8905119080087]}, "type": "Feature", "properties": {"Nivel": 3, "Form\u0103": "Deal", "marker-color": "#e55b5b", "Tip": "beczinegy", "Nume": "Beczinegy B.", "Varianta 1": {"Nume": "Beczinegy B.", "Limb\u0103": "Limba rom\u00e2n\u0103", "Hart\u0103": "Transilvania (1869-1870)"}, "ID": 11894, "Jude\u021b": "Cluj"}}]}