{"type": "FeatureCollection", "name": "export_pecinegi.geojson", "features": [{"geometry": {"type": "Point", "coordinates": [25.1015955682861, 45.5566674994352]}, "type": "Feature", "properties": {"Nivel": 3, "Form\u0103": "\u00cen\u0103l\u021bime", "marker-color": "#5be55b", "Tip": "pecineag", "Nume": "Muntele Picineagu", "Varianta 1": {"Nume": "Muntele Picineagu", "Limb\u0103": "Limba rom\u00e2n\u0103", "Hart\u0103": "PDT"}, "ID": 5077, "Jude\u021b": "Arges"}}, {"geometry": {"type": "Point", "coordinates": [28.1471138948218, 45.0058471571915]}, "type": "Feature", "properties": {"Nivel": 3, "Form\u0103": "Localitate", "marker-color": "#e55b5b", "Tip": "pecineaga", "Nume": "Pecineaga", "Varianta 2": {"Nume": "Peceneaga", "Limb\u0103": "Limba rom\u00e2n\u0103", "Hart\u0103": "Geomil 25000"}, "Varianta 1": {"Nume": "Pecineaga", "Limb\u0103": "Limba rom\u00e2n\u0103", "Hart\u0103": "PDT"}, "ID": 6699, "Jude\u021b": "Tulcea"}}, {"geometry": {"type": "Point", "coordinates": [22.5959568352944, 45.4049515808841]}, "type": "Feature", "properties": {"Nivel": 3, "Form\u0103": "Vale", "marker-color": "#e55b5b", "Tip": "pecineaga", "Nume": "P\u00e2r\u00e2u Peceneaga", "Varianta 1": {"Nume": "P\u00e2r\u00e2u Peceneaga", "Limb\u0103": "Limba rom\u00e2n\u0103", "Hart\u0103": "Geomil 25000"}, "ID": 8666, "Jude\u021b": "Caras Severin"}}, {"geometry": {"type": "Point", "coordinates": [26.7509538813844, 45.504136514912]}, "type": "Feature", "properties": {"Nivel": 3, "Form\u0103": "Vale", "marker-color": "#e55b5b", "Tip": "pecineaga", "Nume": "P\u00e2r\u00e2ul Pecineaga", "Varianta 1": {"Nume": "P\u00e2r\u00e2ul Pecineaga", "Limb\u0103": "Limba rom\u00e2n\u0103", "Hart\u0103": "Geomil 25000"}, "ID": 12269, "Jude\u021b": "Buzau"}}, {"geometry": {"type": "Point", "coordinates": [22.4037581060376, 44.8595907199728]}, "type": "Feature", "properties": {"Nivel": 3, "Form\u0103": "Localitate", "marker-color": "#5b5be5", "Tip": "pecini\u0219ca", "Nume": "Pecini\u0219ca", "Varianta 1": {"Nume": "Pecini\u0219ca", "Limb\u0103": "Limba rom\u00e2n\u0103", "Hart\u0103": "Geomil 25000"}, "ID": 12649, "Jude\u021b": "Caras Severin"}}]}