{"type": "FeatureCollection", "name": "export_c\u00e2rloman.geojson", "features": [{"geometry": {"type": "Point", "coordinates": [26.3417846163111, 46.9513668317082]}, "type": "Feature", "properties": {"Nivel": 3, "Form\u0103": "\u00cen\u0103l\u021bime", "marker-color": "#e55b5b", "Tip": "c\u00e2rloman", "Nume": "Plaiul C\u00e2rlomanu", "Varianta 2": {"Nume": "Dealul C\u00e2rlomanului", "Limb\u0103": "Limba rom\u00e2n\u0103", "Hart\u0103": "ANCPI"}, "Varianta 1": {"Nume": "Plaiul C\u00e2rlomanu", "Limb\u0103": "Limba rom\u00e2n\u0103", "Hart\u0103": "PDT"}, "ID": 15650, "Jude\u021b": "Neamt"}}]}