{"type": "FeatureCollection", "name": "export_t\u0103t\u0103rani.geojson", "features": [{"geometry": {"type": "Point", "coordinates": [25.2758060909814, 44.9978733665829]}, "type": "Feature", "properties": {"Nivel": 3, "Form\u0103": "Localitate", "marker-color": "#e55b5b", "Tip": "t\u0103t\u0103rani", "Nume": "T\u0103t\u0103rani", "Varianta 1": {"Nume": "T\u0103t\u0103rani", "Limb\u0103": "Limba rom\u00e2n\u0103", "Hart\u0103": "Geomil 25000"}, "ID": 5995, "Jude\u021b": "Dambovita"}}, {"geometry": {"type": "Point", "coordinates": [26.033273206065, 44.8931903269125]}, "type": "Feature", "properties": {"Nivel": 3, "Form\u0103": "Localitate", "marker-color": "#e55b5b", "Tip": "t\u0103t\u0103rani", "Nume": "T\u0103t\u0103rani", "Varianta 2": {"Nume": "T\u0103t\u0103rani", "Limb\u0103": "Limba rom\u00e2n\u0103", "Hart\u0103": "PDT"}, "Varianta 1": {"Nume": "T\u0103t\u0103rani", "Limb\u0103": "Limba rom\u00e2n\u0103", "Hart\u0103": "Geomil 25000"}, "ID": 8796, "Jude\u021b": "Prahova"}}, {"geometry": {"type": "Point", "coordinates": [24.2506328342552, 44.9830507537862]}, "type": "Feature", "properties": {"Nivel": 3, "Form\u0103": "Localitate", "marker-color": "#e55b5b", "Tip": "t\u0103t\u0103rani", "Nume": "T\u0103t\u0103rani", "Varianta 1": {"Nume": "T\u0103t\u0103rani", "Limb\u0103": "Limba rom\u00e2n\u0103", "Hart\u0103": "PDT"}, "ID": 8431, "Jude\u021b": "Valcea"}}]}