{"type": "FeatureCollection", "name": "export_gr\u0103de\u021b.geojson", "features": [{"geometry": {"type": "Point", "coordinates": [22.6242156385467, 44.7539383806422]}, "type": "Feature", "properties": {"Nivel": 3, "Form\u0103": "Deal", "marker-color": "#e55b5b", "Tip": "gr\u0103de\u021b", "Nume": "D. Gredetz", "Varianta 1": {"Nume": "D. Gredetz", "Limb\u0103": "Limba rom\u00e2n\u0103", "Hart\u0103": "Austriac\u0103"}, "ID": 14268, "Jude\u021b": "Mehedinti"}}]}