{"type": "FeatureCollection", "name": "export_giurcari.geojson", "features": [{"geometry": {"type": "Point", "coordinates": [26.929122870688, 45.556402941927]}, "type": "Feature", "properties": {"Nivel": 3, "Form\u0103": "Localitate", "marker-color": "#e55b5b", "Tip": "giurcari", "Nume": "Giurcari", "Varianta 1": {"Nume": "Giurcari", "Limb\u0103": "Limba rom\u00e2n\u0103", "Hart\u0103": "PDT"}, "ID": 15972, "Jude\u021b": "Vrancea"}}]}