{"type": "FeatureCollection", "name": "export_sultan.geojson", "features": [{"geometry": {"type": "Point", "coordinates": [26.8559264199414, 44.2619131509459]}, "type": "Feature", "properties": {"Nivel": 3, "Form\u0103": "\u00cen\u0103l\u021bime", "marker-color": "#5be5e5", "Tip": "sultana", "Nume": "Movila la Sultana", "Varianta 1": {"Nume": "Movila la Sultana", "Limb\u0103": "Limba rom\u00e2n\u0103", "Hart\u0103": "Austriac\u0103"}, "ID": 8460, "Jude\u021b": "Calarasi"}}, {"geometry": {"type": "Point", "coordinates": [25.5854412635332, 45.1136022698513]}, "type": "Feature", "properties": {"Nivel": 2, "Form\u0103": "Localitate", "marker-color": "#e55b5b", "Tip": "sultan", "Nume": "Sultanu", "Varianta 1": {"Nume": "Sultanu", "Limb\u0103": "Limba rom\u00e2n\u0103", "Hart\u0103": "Geomil 25000"}, "ID": 7465, "Jude\u021b": "Dambovita"}}, {"geometry": {"type": "Point", "coordinates": [23.6354411811572, 44.4067135937634]}, "type": "Feature", "properties": {"Nivel": 3, "Form\u0103": "Deal", "marker-color": "#5be5e5", "Tip": "sultana", "Nume": "Dealul Sultanei", "Varianta 1": {"Nume": "Dealul Sultanei", "Limb\u0103": "Limba rom\u00e2n\u0103", "Hart\u0103": "Geomil 25000"}, "ID": 11371, "Jude\u021b": "Dolj"}}, {"geometry": {"type": "Point", "coordinates": [28.0136878407512, 45.5123289986258]}, "type": "Feature", "properties": {"Nivel": 2, "Form\u0103": "Vale", "marker-color": "#e55b5b", "Tip": "sultan", "Nume": "Valea Sultanul", "Varianta 1": {"Nume": "Valea Sultanul", "Limb\u0103": "Limba rom\u00e2n\u0103", "Hart\u0103": "Geomil 25000"}, "ID": 11285, "Jude\u021b": "Galati"}}, {"geometry": {"type": "Point", "coordinates": [25.6119888183907, 44.5212515760999]}, "type": "Feature", "properties": {"Nivel": 3, "Form\u0103": "Altele", "marker-color": "#5be5e5", "Tip": "sultana", "Nume": "La Sultana", "Varianta 1": {"Nume": "La Sultana", "Limb\u0103": "Limba rom\u00e2n\u0103", "Hart\u0103": "PDT"}, "ID": 12012, "Jude\u021b": "Giurgiu"}}, {"geometry": {"type": "Point", "coordinates": [25.9045152706371, 45.389718468633]}, "type": "Feature", "properties": {"Nivel": 2, "Form\u0103": "Altele", "marker-color": "#e55b5b", "Tip": "sultan", "Nume": "La Casa lui Sultan", "Varianta 1": {"Nume": "La Casa lui Sultan", "Limb\u0103": "Limba rom\u00e2n\u0103", "Hart\u0103": "Geomil 25000"}, "ID": 11450, "Jude\u021b": "Prahova"}}]}