{"type": "FeatureCollection", "name": "export_beiluc.geojson", "features": [{"geometry": {"type": "Point", "coordinates": [26.7888895764206, 44.4580947851333]}, "type": "Feature", "properties": {"Nivel": 3, "Form\u0103": "Localitate", "marker-color": "#e55b5b", "Tip": "beiluc", "Nume": "Beilukului", "Varianta 1": {"Nume": "Beilukului", "Limb\u0103": "Limba rom\u00e2n\u0103", "Hart\u0103": "Austriac\u0103"}, "ID": 14672, "Jude\u021b": "Calarasi"}}]}