{"type": "FeatureCollection", "name": "export_furdue\u0219ti.geojson", "features": [{"geometry": {"type": "Point", "coordinates": [23.0807508291548, 46.3361543230606]}, "type": "Feature", "properties": {"Nivel": 3, "Form\u0103": "Localitate", "marker-color": "#e55b5b", "Tip": "furdue\u0219ti", "Nume": "Furduie\u0219ti", "Varianta 1": {"Nume": "Furduie\u0219ti", "Limb\u0103": "Limba rom\u00e2n\u0103", "Hart\u0103": "Geomil 25000"}, "ID": 10666, "Jude\u021b": "Alba"}}, {"geometry": {"type": "Point", "coordinates": [22.989105830628, 46.3129649849665]}, "type": "Feature", "properties": {"Nivel": 3, "Form\u0103": "Localitate", "marker-color": "#e55b5b", "Tip": "furdue\u0219ti", "Nume": "Furduie\u0219ti", "Varianta 1": {"Nume": "Furduie\u0219ti", "Limb\u0103": "Limba rom\u00e2n\u0103", "Hart\u0103": "Geomil 25000"}, "ID": 12506, "Jude\u021b": "Alba"}}, {"geometry": {"type": "Point", "coordinates": [25.1048848211997, 44.722362825431]}, "type": "Feature", "properties": {"Nivel": 3, "Form\u0103": "Localitate", "marker-color": "#e55b5b", "Tip": "furdue\u0219ti", "Nume": "Furdue\u0219ti", "Varianta 1": {"Nume": "Furdue\u0219ti", "Limb\u0103": "Limba rom\u00e2n\u0103", "Hart\u0103": "Geomil 25000"}, "ID": 10119, "Jude\u021b": "Arges"}}, {"geometry": {"type": "Point", "coordinates": [23.1728524702341, 44.8904243186741]}, "type": "Feature", "properties": {"Nivel": 3, "Form\u0103": "Ap\u0103-deal-c\u00e2mpie", "marker-color": "#e55b5b", "Tip": "furdue\u0219ti", "Nume": "Lunca Furdue\u0219tilor", "Varianta 1": {"Nume": "Lunca Furdue\u0219tilor", "Limb\u0103": "Limba rom\u00e2n\u0103", "Hart\u0103": "Geomil 25000"}, "ID": 11005, "Jude\u021b": "Gorj"}}]}