{"type": "FeatureCollection", "name": "export_caraman.geojson", "features": [{"geometry": {"type": "Point", "coordinates": [26.4307854484462, 45.3842167585786]}, "type": "Feature", "properties": {"Nivel": 3, "Form\u0103": "Localitate", "marker-color": "#e55b5b", "Tip": "c\u0103r\u0103m\u0103ne\u0219ti", "Nume": "Muscelu C\u0103r\u0103m\u0103ne\u0219ti", "Varianta 1": {"Nume": "Muscelu C\u0103r\u0103m\u0103ne\u0219ti", "Limb\u0103": "Limba rom\u00e2n\u0103", "Hart\u0103": "Geomil 25000"}, "ID": 6117, "Jude\u021b": "Buzau"}}]}