{"type": "FeatureCollection", "name": "export_tocbe\u0219ti.geojson", "features": [{"geometry": {"type": "Point", "coordinates": [23.8182795556902, 46.8210232871084]}, "type": "Feature", "properties": {"Nivel": 2, "Form\u0103": "Vale", "marker-color": "#e55b5b", "Tip": "tocbe\u0219ti", "Nume": "P\u00e2r\u00e2u Tocbe\u0219ti", "Varianta 1": {"Nume": "P\u00e2r\u00e2u Tocbe\u0219ti", "Limb\u0103": "Limba rom\u00e2n\u0103", "Hart\u0103": "Geomil 25000"}, "ID": 5878, "Jude\u021b": "Cluj"}}]}