{"type": "FeatureCollection", "name": "export_furde\u0219ti.geojson", "features": [{"geometry": {"type": "Point", "coordinates": [22.7704688915057, 46.3225741660986]}, "type": "Feature", "properties": {"Nivel": 3, "Form\u0103": "Localitate", "marker-color": "#e55b5b", "Tip": "furde\u0219ti", "Nume": "Furdesci", "Varianta 1": {"Nume": "Furdesci", "Limb\u0103": "Limba rom\u00e2n\u0103", "Hart\u0103": "Imperiul Habsburgic (1887)"}, "ID": 14778, "Jude\u021b": "Hunedoara"}}]}