{"type": "FeatureCollection", "name": "export_lespezea.geojson", "features": [{"geometry": {"type": "Point", "coordinates": [22.9055663934835, 46.4746786037507]}, "type": "Feature", "properties": {"Nivel": 4, "Form\u0103": "Localitate", "marker-color": "#e55b5b", "Tip": "lespezea", "Nume": "Lespezea", "Varianta 1": {"Nume": "Lespezea", "Limb\u0103": "Limba rom\u00e2n\u0103", "Hart\u0103": "Geomil 25000"}, "ID": 13198, "Jude\u021b": "Alba"}}]}