{"type": "FeatureCollection", "name": "export_vi\u021bea.geojson", "features": [{"geometry": {"type": "Point", "coordinates": [24.6842956653567, 44.7287207733531]}, "type": "Feature", "properties": {"Nivel": 3, "Form\u0103": "Vale", "marker-color": "#e55b5b", "Tip": "vi\u021bea", "Nume": "Valea Vi\u021belei", "Varianta 1": {"Nume": "Valea Vi\u021belei", "Limb\u0103": "Limba rom\u00e2n\u0103", "Hart\u0103": "PDT"}, "ID": 4774, "Jude\u021b": "Olt"}}]}