{"type": "FeatureCollection", "name": "export_secui_(singular).geojson", "features": [{"geometry": {"type": "Point", "coordinates": [26.0656709167745, 45.4490668368169]}, "type": "Feature", "properties": {"Nivel": 3, "Form\u0103": "Vale", "marker-color": "#e55b5b", "Tip": "secui (singular)", "Nume": "Valea Secuiului", "Varianta 1": {"Nume": "Valea Secuiului", "Limb\u0103": "Limba rom\u00e2n\u0103", "Hart\u0103": "Geomil 25000"}, "ID": 1574, "Jude\u021b": "Buzau"}}, {"geometry": {"type": "Point", "coordinates": [26.2217202582315, 45.6301478041869]}, "type": "Feature", "properties": {"Nivel": 3, "Form\u0103": "Deal", "marker-color": "#e55b5b", "Tip": "secui (singular)", "Nume": "Dealul Secuiului", "Varianta 1": {"Nume": "Dealul Secuiului", "Limb\u0103": "Limba rom\u00e2n\u0103", "Hart\u0103": "Geomil 25000"}, "ID": 1584, "Jude\u021b": "Covasna"}}, {"geometry": {"type": "Point", "coordinates": [23.1424145647307, 45.6398557976561]}, "type": "Feature", "properties": {"Nivel": 3, "Form\u0103": "\u00cen\u0103l\u021bime", "marker-color": "#e55b5b", "Tip": "secui (singular)", "Nume": "V\u00e2rful Secuiului", "Varianta 1": {"Nume": "V\u00e2rful Secuiului", "Limb\u0103": "Limba rom\u00e2n\u0103", "Hart\u0103": "Geomil 25000"}, "ID": 1125, "Jude\u021b": "Hunedoara"}}, {"geometry": {"type": "Point", "coordinates": [24.7780914651413, 46.3915341527427]}, "type": "Feature", "properties": {"Nivel": 3, "Form\u0103": "Deal", "marker-color": "#e55b5b", "Tip": "secui (singular)", "Nume": "Dealul Secuiului", "Varianta 1": {"Nume": "Dealul Secuiului", "Limb\u0103": "Limba rom\u00e2n\u0103", "Hart\u0103": "Geomil 25000"}, "ID": 14224, "Jude\u021b": "Mures"}}, {"geometry": {"type": "Point", "coordinates": [25.9653947696069, 45.3239487215601]}, "type": "Feature", "properties": {"Nivel": 4, "Form\u0103": "Vale", "marker-color": "#5be55b", "Tip": "secuianc\u0103", "Nume": "P\u00e2r\u00e2ul Secuianca", "Varianta 1": {"Nume": "P\u00e2r\u00e2ul Secuianca", "Limb\u0103": "Limba rom\u00e2n\u0103", "Hart\u0103": "Geomil 25000"}, "ID": 3994, "Jude\u021b": "Prahova"}}, {"geometry": {"type": "Point", "coordinates": [25.8102608361108, 45.4230756427073]}, "type": "Feature", "properties": {"Nivel": 4, "Form\u0103": "Vale", "marker-color": "#5be55b", "Tip": "secuianc\u0103", "Nume": "Valea Secuianca", "Varianta 1": {"Nume": "Valea Secuianca", "Limb\u0103": "Limba rom\u00e2n\u0103", "Hart\u0103": "Geomil 25000"}, "ID": 804, "Jude\u021b": "Prahova"}}, {"geometry": {"type": "Point", "coordinates": [27.7985731546141, 46.6026604141719]}, "type": "Feature", "properties": {"Nivel": 4, "Form\u0103": "Deal", "marker-color": "#5b5be5", "Tip": "secuia", "Nume": "Dealul Secuia", "Varianta 1": {"Nume": "Dealul Secuia", "Limb\u0103": "Limba rom\u00e2n\u0103", "Hart\u0103": "Geomil 25000"}, "ID": 2197, "Jude\u021b": "Vaslui"}}]}