{"type": "FeatureCollection", "name": "export_timi\u0219oara.geojson", "features": [{"geometry": {"type": "Point", "coordinates": [22.3793198833761, 46.1216259964797]}, "type": "Feature", "properties": {"Nivel": 3, "Form\u0103": "Vale", "marker-color": "#e55b5b", "Tip": "timi\u0219oara", "Nume": "Timi\u0219oara", "Varianta 1": {"Nume": "Timi\u0219oara", "Limb\u0103": "Limba rom\u00e2n\u0103", "Hart\u0103": "ANCPI"}, "ID": 14737, "Jude\u021b": "Arad"}}]}