{"type": "FeatureCollection", "name": "export_stupi.geojson", "features": [{"geometry": {"type": "Point", "coordinates": [21.9836090402943, 46.2813686897764]}, "type": "Feature", "properties": {"Nivel": 3, "Form\u0103": "Altele", "marker-color": "#e55b5b", "Tip": "stupi", "Nume": "La Stupii Surdului", "Varianta 1": {"Nume": "La Stupii Surdului", "Limb\u0103": "Limba rom\u00e2n\u0103", "Hart\u0103": "Geomil 25000"}, "ID": 9408, "Jude\u021b": "Arad"}}, {"geometry": {"type": "Point", "coordinates": [27.2503542830506, 46.3176062004349]}, "type": "Feature", "properties": {"Nivel": 3, "Form\u0103": "Vale", "marker-color": "#e55b5b", "Tip": "stupi", "Nume": "Valea Stupilor", "Varianta 1": {"Nume": "Valea Stupilor", "Limb\u0103": "Limba rom\u00e2n\u0103", "Hart\u0103": "PDT"}, "ID": 7892, "Jude\u021b": "Bacau"}}, {"geometry": {"type": "Point", "coordinates": [24.1958462095152, 47.407503837491]}, "type": "Feature", "properties": {"Nivel": 3, "Form\u0103": "Vale", "marker-color": "#e55b5b", "Tip": "stupi", "Nume": "Valea Stupului", "Varianta 1": {"Nume": "Valea Stupului", "Limb\u0103": "Limba rom\u00e2n\u0103", "Hart\u0103": "Geomil 25000"}, "ID": 7091, "Jude\u021b": "Bistrita Nasaud"}}, {"geometry": {"type": "Point", "coordinates": [21.8277199369785, 45.1728542098166]}, "type": "Feature", "properties": {"Nivel": 3, "Form\u0103": "Deal", "marker-color": "#e55b5b", "Tip": "stupi", "Nume": "Dealu Stupilor", "Varianta 1": {"Nume": "Dealu Stupilor", "Limb\u0103": "Limba rom\u00e2n\u0103", "Hart\u0103": "Geomil 25000"}, "ID": 5716, "Jude\u021b": "Caras Severin"}}, {"geometry": {"type": "Point", "coordinates": [22.1517924608733, 45.4434581427575]}, "type": "Feature", "properties": {"Nivel": 3, "Form\u0103": "Poian\u0103", "marker-color": "#e55b5b", "Tip": "stupi", "Nume": "Poiana Stupilor", "Varianta 1": {"Nume": "Poiana Stupilor", "Limb\u0103": "Limba rom\u00e2n\u0103", "Hart\u0103": "Ungar\u0103 1869"}, "ID": 10300, "Jude\u021b": "Caras Severin"}}, {"geometry": {"type": "Point", "coordinates": [23.2810357554025, 44.4575506492165]}, "type": "Feature", "properties": {"Nivel": 3, "Form\u0103": "Deal", "marker-color": "#e55b5b", "Tip": "stupi", "Nume": "Piscul Stuparului", "Varianta 2": {"Nume": "Piscul Stuparului", "Limb\u0103": "Limba rom\u00e2n\u0103", "Hart\u0103": "PDT"}, "Varianta 1": {"Nume": "\u0443\u0440. \u0421\u0442\u0443\u043f\u0443\u043b\u0443\u0439 (Dealul Stupului)", "Limb\u0103": "Limba rom\u00e2n\u0103", "Hart\u0103": "Sovietic\u0103"}, "ID": 116, "Jude\u021b": "Dolj"}}, {"geometry": {"type": "Point", "coordinates": [26.4944331981836, 44.6698721463094]}, "type": "Feature", "properties": {"Nivel": 3, "Form\u0103": "\u00cen\u0103l\u021bime", "marker-color": "#e55b5b", "Tip": "stupi", "Nume": "Mo. Stupului", "Varianta 1": {"Nume": "Mo. Stupului", "Limb\u0103": "Limba rom\u00e2n\u0103", "Hart\u0103": "Austriac\u0103"}, "ID": 5750, "Jude\u021b": "Ialomita"}}, {"geometry": {"type": "Point", "coordinates": [24.1273585870544, 45.7326905441462]}, "type": "Feature", "properties": {"Nivel": 3, "Form\u0103": "Vale", "marker-color": "#e55b5b", "Tip": "stupi", "Nume": "Stupul", "Varianta 1": {"Nume": "Stupul", "Limb\u0103": "Limba rom\u00e2n\u0103", "Hart\u0103": "Geomil 25000"}, "ID": 8584, "Jude\u021b": "Sibiu"}}, {"geometry": {"type": "Point", "coordinates": [27.9661683262573, 46.6810663452174]}, "type": "Feature", "properties": {"Nivel": 3, "Form\u0103": "Localitate", "marker-color": "#e55b5b", "Tip": "stupi", "Nume": "Valea Stupilor", "Varianta 1": {"Nume": "Valea Stupilor", "Limb\u0103": "Limba rom\u00e2n\u0103", "Hart\u0103": "PDT"}, "ID": 8850, "Jude\u021b": "Vaslui"}}]}