{"type": "FeatureCollection", "name": "export_izb\u0103se\u0219ti.geojson", "features": [{"geometry": {"type": "Point", "coordinates": [24.4491083487019, 45.0409132721954]}, "type": "Feature", "properties": {"Nivel": 3, "Form\u0103": "Localitate", "marker-color": "#e55b5b", "Tip": "izb\u0103se\u0219ti", "Nume": "Izb\u0103se\u0219ti", "Varianta 2": {"Nume": "Isb\u00e2ze\u0219ti Moreni", "Limb\u0103": "Limba rom\u00e2n\u0103", "Hart\u0103": "Austriac\u0103"}, "Varianta 1": {"Nume": "Izb\u0103se\u0219ti", "Limb\u0103": "Limba rom\u00e2n\u0103", "Hart\u0103": "ANCPI"}, "ID": 14819, "Jude\u021b": "Valcea"}}]}