{"type": "FeatureCollection", "name": "export_zl\u0103tari.geojson", "features": [{"geometry": {"type": "Point", "coordinates": [23.7473161882515, 44.4563004928824]}, "type": "Feature", "properties": {"Nivel": 3, "Form\u0103": "Localitate", "marker-color": "#e55b5b", "Tip": "zl\u0103tari", "Nume": "Zl\u0103tari", "Varianta 1": {"Nume": "Zl\u0103tari", "Limb\u0103": "Limba rom\u00e2n\u0103", "Hart\u0103": "Geomil 25000"}, "ID": 5167, "Jude\u021b": "Dolj"}}, {"geometry": {"type": "Point", "coordinates": [27.1168775126633, 46.5041368545473]}, "type": "Feature", "properties": {"Nivel": 3, "Form\u0103": "Localitate", "marker-color": "#e55b5b", "Tip": "zl\u0103tari", "Nume": "Zl\u0103tari", "Varianta 1": {"Nume": "Zl\u0103tari", "Limb\u0103": "Limba rom\u00e2n\u0103", "Hart\u0103": "PDT"}, "ID": 9505, "Jude\u021b": "Bacau"}}, {"geometry": {"type": "Point", "coordinates": [27.2352420862033, 46.3618975560905]}, "type": "Feature", "properties": {"Nivel": 4, "Form\u0103": "Localitate", "marker-color": "#5be55b", "Tip": "zl\u0103t\u0103reas\u0103", "Nume": "Zl\u0103t\u0103reasa", "Varianta 1": {"Nume": "Zl\u0103t\u0103reasa", "Limb\u0103": "Limba rom\u00e2n\u0103", "Hart\u0103": "Moldova (1892-1898)"}, "ID": 9521, "Jude\u021b": "Bacau"}}, {"geometry": {"type": "Point", "coordinates": [24.2540994174149, 44.631990960469]}, "type": "Feature", "properties": {"Nivel": 4, "Form\u0103": "Localitate", "marker-color": "#5b5be5", "Tip": "zl\u0103t\u0103rei", "Nume": "Zl\u0103t\u0103rei", "Varianta 1": {"Nume": "Zl\u0103t\u0103rei", "Limb\u0103": "Limba rom\u00e2n\u0103", "Hart\u0103": "Geomil 25000"}, "ID": 11040, "Jude\u021b": "Valcea"}}]}