{"type": "FeatureCollection", "name": "export_\u021big\u0103ne\u0219ti.geojson", "features": [{"geometry": {"type": "Point", "coordinates": [22.2590506776592, 45.4346055247839]}, "type": "Feature", "properties": {"Nivel": 3, "Form\u0103": "Vale", "marker-color": "#e55b5b", "Tip": "\u021big\u0103ne\u0219ti", "Nume": "Valea \u021aig\u0103ne\u0219ti", "Varianta 1": {"Nume": "Valea \u021aig\u0103ne\u0219ti", "Limb\u0103": "Limba rom\u00e2n\u0103", "Hart\u0103": "Geomil 25000"}, "ID": 859, "Jude\u021b": "Caras Severin"}}, {"geometry": {"type": "Point", "coordinates": [26.326681963737, 45.2952171071875]}, "type": "Feature", "properties": {"Nivel": 3, "Form\u0103": "Localitate", "marker-color": "#e55b5b", "Tip": "\u021big\u0103ne\u0219ti", "Nume": "Zigane\u0219ti", "Varianta 1": {"Nume": "Zigane\u0219ti", "Limb\u0103": "Limba rom\u00e2n\u0103", "Hart\u0103": "Austriac\u0103"}, "ID": 5758, "Jude\u021b": "Buzau"}}, {"geometry": {"type": "Point", "coordinates": [25.3793196884378, 43.9001651878461]}, "type": "Feature", "properties": {"Nivel": 3, "Form\u0103": "Localitate", "marker-color": "#e55b5b", "Tip": "\u021big\u0103ne\u0219ti", "Nume": "\u021aig\u0103ne\u0219ti", "Varianta 2": {"Nume": "Tzigane\u0219ti", "Limb\u0103": "Limba rom\u00e2n\u0103", "Hart\u0103": "Austriac\u0103"}, "Varianta 1": {"Nume": "\u021aig\u0103ne\u0219ti", "Limb\u0103": "Limba rom\u00e2n\u0103", "Hart\u0103": "Geomil 25000"}, "ID": 5783, "Jude\u021b": "Teleorman"}}, {"geometry": {"type": "Point", "coordinates": [23.4599968327121, 47.9722986646795]}, "type": "Feature", "properties": {"Nivel": 3, "Form\u0103": "\u00cen\u0103l\u021bime", "marker-color": "#e55b5b", "Tip": "\u021big\u0103ne\u0219ti", "Nume": "V\u00e2rful \u021aig\u0103ne\u0219ti", "Varianta 1": {"Nume": "V\u00e2rful \u021aig\u0103ne\u0219ti", "Limb\u0103": "Limba rom\u00e2n\u0103", "Hart\u0103": "PDT"}, "ID": 7226, "Jude\u021b": "Satu Mare"}}, {"geometry": {"type": "Point", "coordinates": [27.2604289653543, 46.3963857419191]}, "type": "Feature", "properties": {"Nivel": 3, "Form\u0103": "Localitate", "marker-color": "#e55b5b", "Tip": "\u021big\u0103ne\u0219ti", "Nume": "\u021aig\u0103ne\u0219ti", "Varianta 1": {"Nume": "\u021aig\u0103ne\u0219ti", "Limb\u0103": "Limba rom\u00e2n\u0103", "Hart\u0103": "Geomil 25000"}, "ID": 7848, "Jude\u021b": "Bacau"}}, {"geometry": {"type": "Point", "coordinates": [27.2085204881218, 46.3512238967963]}, "type": "Feature", "properties": {"Nivel": 3, "Form\u0103": "Deal", "marker-color": "#e55b5b", "Tip": "\u021big\u0103ne\u0219ti", "Nume": "Dealul \u021aig\u0103ne\u0219ti", "Varianta 1": {"Nume": "Dealul \u021aig\u0103ne\u0219ti", "Limb\u0103": "Limba rom\u00e2n\u0103", "Hart\u0103": "PDT"}, "ID": 7889, "Jude\u021b": "Bacau"}}, {"geometry": {"type": "Point", "coordinates": [26.1241897484, 44.726219978]}, "type": "Feature", "properties": {"Nivel": 3, "Form\u0103": "P\u0103dure", "marker-color": "#e55b5b", "Tip": "\u021big\u0103ne\u0219ti", "Nume": "P\u0103durea \u021aig\u0103ne\u0219ti", "Varianta 1": {"Nume": "P\u0103durea \u021aig\u0103ne\u0219ti", "Limb\u0103": "Limba rom\u00e2n\u0103", "Hart\u0103": "PDT"}, "ID": 8803, "Jude\u021b": "Ilfov"}}, {"geometry": {"type": "Point", "coordinates": [25.0883891428705, 44.8502377790965]}, "type": "Feature", "properties": {"Nivel": 3, "Form\u0103": "Localitate", "marker-color": "#e55b5b", "Tip": "\u021big\u0103ne\u0219ti", "Nume": "\u021aig\u0103ne\u0219ti", "Varianta 1": {"Nume": "\u021aig\u0103ne\u0219ti", "Limb\u0103": "Limba rom\u00e2n\u0103", "Hart\u0103": "PDT"}, "ID": 10157, "Jude\u021b": "Arges"}}, {"geometry": {"type": "Point", "coordinates": [23.3661378136258, 47.6167430556998]}, "type": "Feature", "properties": {"Nivel": 3, "Form\u0103": "Altele", "marker-color": "#e55b5b", "Tip": "\u021big\u0103ne\u0219ti", "Nume": "Ciganesti", "Varianta 1": {"Nume": "Ciganesti", "Limb\u0103": "Limba rom\u00e2n\u0103", "Hart\u0103": "Imperiul Habsburgic (1887)"}, "ID": 10546, "Jude\u021b": "Maramures"}}, {"geometry": {"type": "Point", "coordinates": [25.800716947677, 44.6604537596879]}, "type": "Feature", "properties": {"Nivel": 3, "Form\u0103": "Localitate", "marker-color": "#e55b5b", "Tip": "\u021big\u0103ne\u0219ti", "Nume": "\u021aig\u0103ne\u0219ti", "Varianta 1": {"Nume": "\u021aig\u0103ne\u0219ti", "Limb\u0103": "Limba rom\u00e2n\u0103", "Hart\u0103": "PDT"}, "ID": 11056, "Jude\u021b": "Dambovita"}}, {"geometry": {"type": "Point", "coordinates": [25.6653876828656, 44.0751853106469]}, "type": "Feature", "properties": {"Nivel": 3, "Form\u0103": "Altele", "marker-color": "#e55b5b", "Tip": "\u021big\u0103ne\u0219ti", "Nume": "Podu Cziganestilor", "Varianta 1": {"Nume": "Podu Cziganestilor", "Limb\u0103": "Limba rom\u00e2n\u0103", "Hart\u0103": "Oltenia-Muntenia (1790)"}, "ID": 12016, "Jude\u021b": "Giurgiu"}}]}