{"type": "FeatureCollection", "name": "export_ciurariu.geojson", "features": [{"geometry": {"type": "Point", "coordinates": [23.5528300947775, 47.5930591731344]}, "type": "Feature", "properties": {"Nivel": 3, "Form\u0103": "Altele", "marker-color": "#e55b5b", "Tip": "ciurariu", "Nume": "Sazu Ciurariului", "Varianta 1": {"Nume": "Sazu Ciurariului", "Limb\u0103": "Limba rom\u00e2n\u0103", "Hart\u0103": "PDT"}, "ID": 15762, "Jude\u021b": "Maramures"}}]}