{"type": "FeatureCollection", "name": "export_s\u0103scioara.geojson", "features": [{"geometry": {"type": "Point", "coordinates": [23.8686539689358, 44.7978783856526]}, "type": "Feature", "properties": {"Nivel": 4, "Form\u0103": "Localitate", "marker-color": "#e55b5b", "Tip": "s\u0103scioara", "Nume": "S\u0103\u0219cioara", "Varianta 2": {"Nume": "Sascioara", "Limb\u0103": "Limba rom\u00e2n\u0103", "Hart\u0103": "PDT"}, "Varianta 3": {"Nume": "S\u00e2\u0219cioara", "Limb\u0103": "Limba rom\u00e2n\u0103", "Hart\u0103": "Austriac\u0103"}, "Varianta 1": {"Nume": "S\u0103\u0219cioara", "Limb\u0103": "Limba rom\u00e2n\u0103", "Hart\u0103": "Geomil 25000"}, "ID": 9386, "Jude\u021b": "Valcea"}}]}