{"type": "FeatureCollection", "name": "export_tonguz.geojson", "features": [{"geometry": {"type": "Point", "coordinates": [27.3615520184263, 46.9217246501642]}, "type": "Feature", "properties": {"Nivel": 3, "Form\u0103": "Localitate", "marker-color": "#e55b5b", "Tip": "tungujei", "Nume": "Tungujei", "Varianta 1": {"Nume": "Tungujei", "Limb\u0103": "Limba rom\u00e2n\u0103", "Hart\u0103": "PDT"}, "ID": 14641, "Jude\u021b": "Iasi"}}]}