{"type": "FeatureCollection", "name": "export_\u021big\u0103neasa.geojson", "features": [{"geometry": {"type": "Point", "coordinates": [27.6232485536041, 47.3010115612912]}, "type": "Feature", "properties": {"Nivel": 3, "Form\u0103": "Altele", "marker-color": "#e55b5b", "Tip": "\u021big\u0103neasa", "Nume": "\u00cen \u021aig\u0103neasa", "Varianta 1": {"Nume": "\u00cen \u021aig\u0103neasa", "Limb\u0103": "Limba rom\u00e2n\u0103", "Hart\u0103": "Moldova (1892-1898)"}, "ID": 12387, "Jude\u021b": "Iasi"}}]}