{"type": "FeatureCollection", "name": "export_c\u0103rbunari\u0219te.geojson", "features": [{"geometry": {"type": "Point", "coordinates": [24.6221280506569, 46.944551330406]}, "type": "Feature", "properties": {"Nivel": 3, "Form\u0103": "\u00cen\u0103l\u021bime", "marker-color": "#e55b5b", "Tip": "c\u0103rbunari\u0219te", "Nume": "Groapa C\u00e2rbunari\u0219tii", "Varianta 1": {"Nume": "Groapa C\u00e2rbunari\u0219tii", "Limb\u0103": "Limba rom\u00e2n\u0103", "Hart\u0103": "PDT"}, "ID": 9899, "Jude\u021b": "Bistrita Nasaud"}}, {"geometry": {"type": "Point", "coordinates": [23.5485455324736, 47.4646738992066]}, "type": "Feature", "properties": {"Nivel": 3, "Form\u0103": "Vale", "marker-color": "#e55b5b", "Tip": "c\u0103rbunari\u0219te", "Nume": "Valea C\u0103rbun\u0103ri\u0219tei", "Varianta 1": {"Nume": "Valea C\u0103rbun\u0103ri\u0219tei", "Limb\u0103": "Limba rom\u00e2n\u0103", "Hart\u0103": "PDT"}, "ID": 13914, "Jude\u021b": "Maramures"}}]}