{"type": "FeatureCollection", "name": "export_olteanc\u0103.geojson", "features": [{"geometry": {"type": "Point", "coordinates": [24.9928178415394, 44.9680677594204]}, "type": "Feature", "properties": {"Nivel": 3, "Form\u0103": "Deal", "marker-color": "#e55b5b", "Tip": "olteanc\u0103", "Nume": "Dealu Olteanca", "Varianta 1": {"Nume": "Dealu Olteanca", "Limb\u0103": "Limba rom\u00e2n\u0103", "Hart\u0103": "Geomil 25000"}, "ID": 6012, "Jude\u021b": "Arges"}}, {"geometry": {"type": "Point", "coordinates": [26.9021389942, 46.0961386169]}, "type": "Feature", "properties": {"Nivel": 3, "Form\u0103": "Vale", "marker-color": "#e55b5b", "Tip": "olteanc\u0103", "Nume": "Olteanca", "Varianta 1": {"Nume": "Olteanca", "Limb\u0103": "Limba rom\u00e2n\u0103", "Hart\u0103": "Geomil 25000"}, "ID": 5290, "Jude\u021b": "Bacau"}}, {"geometry": {"type": "Point", "coordinates": [22.5084035084777, 45.3091791195608]}, "type": "Feature", "properties": {"Nivel": 3, "Form\u0103": "Vale", "marker-color": "#e55b5b", "Tip": "olteanc\u0103", "Nume": "P\u00e2r\u00e2u Olteana", "Varianta 1": {"Nume": "P\u00e2r\u00e2u Olteana", "Limb\u0103": "Limba rom\u00e2n\u0103", "Hart\u0103": "Geomil 25000"}, "ID": 854, "Jude\u021b": "Caras Severin"}}, {"geometry": {"type": "Point", "coordinates": [22.9596148666371, 44.4337603249204]}, "type": "Feature", "properties": {"Nivel": 3, "Form\u0103": "Localitate", "marker-color": "#e55b5b", "Tip": "olteanc\u0103", "Nume": "Olteanca", "Varianta 2": {"Nume": "Olteanca", "Limb\u0103": "Limba rom\u00e2n\u0103", "Hart\u0103": "Geomil 25000"}, "Varianta 1": {"Nume": "Olteanca", "Limb\u0103": "Limba rom\u00e2n\u0103", "Hart\u0103": "PDT"}, "ID": 3663, "Jude\u021b": "Mehedinti"}}, {"geometry": {"type": "Point", "coordinates": [22.9736563338179, 44.4470676913355]}, "type": "Feature", "properties": {"Nivel": 3, "Form\u0103": "\u00cen\u0103l\u021bime", "marker-color": "#e55b5b", "Tip": "olteanc\u0103", "Nume": "Olteanca", "Varianta 1": {"Nume": "Olteanca", "Limb\u0103": "Limba rom\u00e2n\u0103", "Hart\u0103": "Geomil 25000"}, "ID": 5197, "Jude\u021b": "Mehedinti"}}, {"geometry": {"type": "Point", "coordinates": [23.1513029152513, 44.3485372721876]}, "type": "Feature", "properties": {"Nivel": 3, "Form\u0103": "Vale", "marker-color": "#e55b5b", "Tip": "olteanc\u0103", "Nume": "Valea Olteanca", "Varianta 2": {"Nume": "Valea Oltenci", "Limb\u0103": "Limba rom\u00e2n\u0103", "Hart\u0103": "Austriac\u0103"}, "Varianta 1": {"Nume": "Valea Olteanca", "Limb\u0103": "Limba rom\u00e2n\u0103", "Hart\u0103": "Geomil 25000"}, "ID": 6165, "Jude\u021b": "Mehedinti"}}, {"geometry": {"type": "Point", "coordinates": [24.7948499509453, 43.8298279408594]}, "type": "Feature", "properties": {"Nivel": 3, "Form\u0103": "Localitate", "marker-color": "#e55b5b", "Tip": "olteanc\u0103", "Nume": "Olteanca", "Varianta 1": {"Nume": "Olteanca", "Limb\u0103": "Limba rom\u00e2n\u0103", "Hart\u0103": "Geomil 25000"}, "ID": 8011, "Jude\u021b": "Teleorman"}}, {"geometry": {"type": "Point", "coordinates": [24.1068948274739, 44.8113938958935]}, "type": "Feature", "properties": {"Nivel": 3, "Form\u0103": "Localitate", "marker-color": "#e55b5b", "Tip": "olteanc\u0103", "Nume": "Olteanca", "Varianta 1": {"Nume": "Olteanca", "Limb\u0103": "Limba rom\u00e2n\u0103", "Hart\u0103": "Geomil 25000"}, "ID": 5202, "Jude\u021b": "Valcea"}}, {"geometry": {"type": "Point", "coordinates": [24.0978574389153, 44.8613233567912]}, "type": "Feature", "properties": {"Nivel": 3, "Form\u0103": "Localitate", "marker-color": "#e55b5b", "Tip": "olteanc\u0103", "Nume": "Olteanca", "Varianta 1": {"Nume": "Olteanca", "Limb\u0103": "Limba rom\u00e2n\u0103", "Hart\u0103": "Geomil 25000"}, "ID": 5206, "Jude\u021b": "Valcea"}}, {"geometry": {"type": "Point", "coordinates": [24.0985969489869, 44.8985601816149]}, "type": "Feature", "properties": {"Nivel": 3, "Form\u0103": "Vale", "marker-color": "#e55b5b", "Tip": "olteanc\u0103", "Nume": "Valea Olteanca", "Varianta 1": {"Nume": "Valea Olteanca", "Limb\u0103": "Limba rom\u00e2n\u0103", "Hart\u0103": "Geomil 25000"}, "ID": 349, "Jude\u021b": "Valcea"}}]}