{"type": "FeatureCollection", "name": "export_t\u0103t\u0103rasca.geojson", "features": [{"geometry": {"type": "Point", "coordinates": [22.4372786055856, 46.5480577680268]}, "type": "Feature", "properties": {"Nivel": 3, "Form\u0103": "Lac", "marker-color": "#e55b5b", "Tip": "t\u0103t\u0103rasca", "Nume": "T\u0103t\u0103rasca", "Varianta 1": {"Nume": "T\u0103t\u0103rasca", "Limb\u0103": "Limba rom\u00e2n\u0103", "Hart\u0103": "PDT"}, "ID": 12044, "Jude\u021b": "Bihor"}}]}