{"type": "FeatureCollection", "name": "export_t\u0103t\u0103rasca.geojson", "features": [{"geometry": {"type": "Point", "coordinates": [22.4372786055856, 46.5480577680268]}, "type": "Feature", "properties": {"Nivel": 3, "Form\u0103": "Lac", "marker-color": "#e55b5b", "Tip": "t\u0103t\u0103rasca", "Nume": "T\u0103t\u0103rasca", "Varianta 1": {"Nume": "T\u0103t\u0103rasca", "Limb\u0103": "Limba rom\u00e2n\u0103", "Hart\u0103": "PDT"}, "ID": 12044, "Jude\u021b": "Bihor"}}, {"geometry": {"type": "Point", "coordinates": [21.4923846808618, 44.8024846461192]}, "type": "Feature", "properties": {"Nivel": 3, "Form\u0103": "\u00cen\u0103l\u021bime", "marker-color": "#e55b5b", "Tip": "t\u0103t\u0103rasca", "Nume": "Tatarska Reka", "Varianta 1": {"Nume": "Tatarska Reka", "Limb\u0103": "Limba rom\u00e2n\u0103", "Hart\u0103": "Imperiul Habsburgic (1887)"}, "ID": 15878, "Jude\u021b": "Caras Severin"}}]}