{"type": "FeatureCollection", "name": "export_epa.geojson", "features": [{"geometry": {"type": "Point", "coordinates": [25.0969205509959, 44.33735317943]}, "type": "Feature", "properties": {"Nivel": 3, "Form\u0103": "Lac", "marker-color": "#e55b5b", "Tip": "epa", "Nume": "La Lacul Epei", "Varianta 1": {"Nume": "La Lacul Epei", "Limb\u0103": "Limba rom\u00e2n\u0103", "Hart\u0103": "PDT"}, "ID": 14821, "Jude\u021b": "Teleorman"}}]}