{"type": "FeatureCollection", "name": "export_caragica.geojson", "features": [{"geometry": {"type": "Point", "coordinates": [27.5808841527521, 44.9426969988113]}, "type": "Feature", "properties": {"Nivel": 3, "Form\u0103": "Localitate", "marker-color": "#e55b5b", "Tip": "caragica", "Nume": "Caragica", "Varianta 1": {"Nume": "Caragica", "Limb\u0103": "Limba rom\u00e2n\u0103", "Hart\u0103": "PDT"}, "ID": 9268, "Jude\u021b": "Braila"}}]}