{"type": "FeatureCollection", "name": "export_pi\u021bigoi.geojson", "features": [{"geometry": {"type": "Point", "coordinates": [26.4627776076803, 46.5897461989478]}, "type": "Feature", "properties": {"Nivel": 2, "Form\u0103": "\u00cen\u0103l\u021bime", "marker-color": "#e55b5b", "Tip": "pi\u021bigoi", "Nume": "Muntele Pi\u021bigoiului", "Varianta 1": {"Nume": "Muntele Pi\u021bigoiului", "Limb\u0103": "Limba rom\u00e2n\u0103", "Hart\u0103": "Geomil 25000"}, "ID": 4602, "Jude\u021b": "Bacau"}}, {"geometry": {"type": "Point", "coordinates": [26.5218015811141, 45.1584793227862]}, "type": "Feature", "properties": {"Nivel": 2, "Form\u0103": "Altele", "marker-color": "#e55b5b", "Tip": "pi\u021bigoi", "Nume": "La Pi\u021bigoi", "Varianta 1": {"Nume": "La Pi\u021bigoi", "Limb\u0103": "Limba rom\u00e2n\u0103", "Hart\u0103": "Geomil 25000"}, "ID": 6029, "Jude\u021b": "Buzau"}}, {"geometry": {"type": "Point", "coordinates": [24.7795116440158, 43.8040721197217]}, "type": "Feature", "properties": {"Nivel": 2, "Form\u0103": "P\u0103dure", "marker-color": "#e55b5b", "Tip": "pi\u021bigoi", "Nume": "P\u0103durea Pi\u021bigoiu", "Varianta 1": {"Nume": "P\u0103durea Pi\u021bigoiu", "Limb\u0103": "Limba rom\u00e2n\u0103", "Hart\u0103": "Geomil 25000"}, "ID": 8010, "Jude\u021b": "Teleorman"}}, {"geometry": {"type": "Point", "coordinates": [22.3550186696399, 44.7761262200649]}, "type": "Feature", "properties": {"Nivel": 2, "Form\u0103": "Altele", "marker-color": "#e55b5b", "Tip": "pi\u021bigoi", "Nume": "Furca Pi\u021bigoiului", "Varianta 1": {"Nume": "Furca Pi\u021bigoiului", "Limb\u0103": "Limba rom\u00e2n\u0103", "Hart\u0103": "PDT"}, "ID": 8695, "Jude\u021b": "Mehedinti"}}, {"geometry": {"type": "Point", "coordinates": [27.0365798332278, 45.8012791396604]}, "type": "Feature", "properties": {"Nivel": 2, "Form\u0103": "Deal", "marker-color": "#e55b5b", "Tip": "pi\u021bigoi", "Nume": "Dealul Pi\u021bigoiu", "Varianta 1": {"Nume": "Dealul Pi\u021bigoiu", "Limb\u0103": "Limba rom\u00e2n\u0103", "Hart\u0103": "Moldova (1892-1898)"}, "ID": 9532, "Jude\u021b": "Vrancea"}}, {"geometry": {"type": "Point", "coordinates": [26.3822288227001, 45.2587886245265]}, "type": "Feature", "properties": {"Nivel": 2, "Form\u0103": "Deal", "marker-color": "#e55b5b", "Tip": "pi\u021bigoi", "Nume": "Dealul Pi\u021bigoiului", "Varianta 1": {"Nume": "Dealul Pi\u021bigoiului", "Limb\u0103": "Limba rom\u00e2n\u0103", "Hart\u0103": "Geomil 25000"}, "ID": 9650, "Jude\u021b": "Buzau"}}, {"geometry": {"type": "Point", "coordinates": [22.2620454858761, 47.1015910519057]}, "type": "Feature", "properties": {"Nivel": 2, "Form\u0103": "\u00cen\u0103l\u021bime", "marker-color": "#e55b5b", "Tip": "pi\u021bigoi", "Nume": "Culmea Pi\u021bigoi", "Varianta 1": {"Nume": "Culmea Pi\u021bigoi", "Limb\u0103": "Limba rom\u00e2n\u0103", "Hart\u0103": "PDT"}, "ID": 10378, "Jude\u021b": "Bihor"}}, {"geometry": {"type": "Point", "coordinates": [26.0714999889739, 45.2241150251557]}, "type": "Feature", "properties": {"Nivel": 2, "Form\u0103": "Vale", "marker-color": "#e55b5b", "Tip": "pi\u021bigoi", "Nume": "Valea Pi\u021bigoiului", "Varianta 1": {"Nume": "Valea Pi\u021bigoiului", "Limb\u0103": "Limba rom\u00e2n\u0103", "Hart\u0103": "Geomil 25000"}, "ID": 12879, "Jude\u021b": "Prahova"}}, {"geometry": {"type": "Point", "coordinates": [26.599998717045, 45.4690410852817]}, "type": "Feature", "properties": {"Nivel": 2, "Form\u0103": "\u00cen\u0103l\u021bime", "marker-color": "#e55b5b", "Tip": "pi\u021bigoi", "Nume": "V\u00e2rful Pi\u021bigoiului", "Varianta 1": {"Nume": "V\u00e2rful Pi\u021bigoiului", "Limb\u0103": "Limba rom\u00e2n\u0103", "Hart\u0103": "Geomil 25000"}, "ID": 12987, "Jude\u021b": "Buzau"}}, {"geometry": {"type": "Point", "coordinates": [26.0027647718221, 46.8593119629056]}, "type": "Feature", "properties": {"Nivel": 2, "Form\u0103": "Vale", "marker-color": "#e55b5b", "Tip": "pi\u021bigoi", "Nume": "P\u00e2r\u00e2ul Pi\u021bigoiul", "Varianta 1": {"Nume": "P\u00e2r\u00e2ul Pi\u021bigoiul", "Limb\u0103": "Limba rom\u00e2n\u0103", "Hart\u0103": "PDT"}, "ID": 13655, "Jude\u021b": "Neamt"}}]}