{"type": "FeatureCollection", "name": "export_porumbei.geojson", "features": [{"geometry": {"type": "Point", "coordinates": [24.9668763765953, 45.3552270429835]}, "type": "Feature", "properties": {"Nivel": 2, "Form\u0103": "Poian\u0103", "marker-color": "#e55b5b", "Tip": "porumbei", "Nume": "Poiana Porumbi\u021bei", "Varianta 1": {"Nume": "Poiana Porumbi\u021bei", "Limb\u0103": "Limba rom\u00e2n\u0103", "Hart\u0103": "Geomil 25000"}, "ID": 12274, "Jude\u021b": "Arges"}}, {"geometry": {"type": "Point", "coordinates": [22.118440129139, 45.3636945141241]}, "type": "Feature", "properties": {"Nivel": 2, "Form\u0103": "Deal", "marker-color": "#e55b5b", "Tip": "porumbei", "Nume": "Dealul Porumbelului", "Varianta 1": {"Nume": "Dealul Porumbelului", "Limb\u0103": "Limba rom\u00e2n\u0103", "Hart\u0103": "Geomil 25000"}, "ID": 4326, "Jude\u021b": "Caras Severin"}}, {"geometry": {"type": "Point", "coordinates": [25.8593205018793, 45.9757523601807]}, "type": "Feature", "properties": {"Nivel": 2, "Form\u0103": "Deal", "marker-color": "#e55b5b", "Tip": "porumbei", "Nume": "Dealul Porumbeilor", "Varianta 1": {"Nume": "Dealul Porumbeilor", "Limb\u0103": "Limba rom\u00e2n\u0103", "Hart\u0103": "Geomil 25000"}, "ID": 2746, "Jude\u021b": "Covasna"}}, {"geometry": {"type": "Point", "coordinates": [25.4249343474151, 45.186501502161]}, "type": "Feature", "properties": {"Nivel": 2, "Form\u0103": "Altele", "marker-color": "#e55b5b", "Tip": "porumbei", "Nume": "La Porumbei", "Varianta 1": {"Nume": "La Porumbei", "Limb\u0103": "Limba rom\u00e2n\u0103", "Hart\u0103": "Geomil 25000"}, "ID": 1498, "Jude\u021b": "Dambovita"}}, {"geometry": {"type": "Point", "coordinates": [22.7724306571853, 45.3840451139989]}, "type": "Feature", "properties": {"Nivel": 2, "Form\u0103": "Deal", "marker-color": "#e55b5b", "Tip": "porumbei", "Nume": "Dealu Cioaca Porumbelului", "Varianta 1": {"Nume": "Dealu Cioaca Porumbelului", "Limb\u0103": "Limba rom\u00e2n\u0103", "Hart\u0103": "Geomil 25000"}, "ID": 14196, "Jude\u021b": "Hunedoara"}}, {"geometry": {"type": "Point", "coordinates": [23.2546105707863, 45.5760748039052]}, "type": "Feature", "properties": {"Nivel": 2, "Form\u0103": "Vale", "marker-color": "#e55b5b", "Tip": "porumbei", "Nume": "Valea Porumbelului", "Varianta 1": {"Nume": "Valea Porumbelului", "Limb\u0103": "Limba rom\u00e2n\u0103", "Hart\u0103": "Geomil 25000"}, "ID": 9833, "Jude\u021b": "Hunedoara"}}, {"geometry": {"type": "Point", "coordinates": [24.8967967224889, 46.4959158044413]}, "type": "Feature", "properties": {"Nivel": 2, "Form\u0103": "Deal", "marker-color": "#e55b5b", "Tip": "porumbei", "Nume": "Dealul Porumbelului", "Varianta 1": {"Nume": "Dealul Porumbelului", "Limb\u0103": "Limba rom\u00e2n\u0103", "Hart\u0103": "Geomil 25000"}, "ID": 11483, "Jude\u021b": "Mures"}}, {"geometry": {"type": "Point", "coordinates": [24.1206658299632, 45.8242509199577]}, "type": "Feature", "properties": {"Nivel": 2, "Form\u0103": "Altele", "marker-color": "#e55b5b", "Tip": "porumbei", "Nume": "F\u00e2nt\u00e2na Porumbelului", "Varianta 1": {"Nume": "F\u00e2nt\u00e2na Porumbelului", "Limb\u0103": "Limba rom\u00e2n\u0103", "Hart\u0103": "PDT"}, "ID": 8592, "Jude\u021b": "Sibiu"}}]}