{"type": "FeatureCollection", "name": "export_c\u00e2rlogani.geojson", "features": [{"geometry": {"type": "Point", "coordinates": [24.1449443604216, 44.5255152072522]}, "type": "Feature", "properties": {"Nivel": 3, "Form\u0103": "Localitate", "marker-color": "#e55b5b", "Tip": "c\u00e2rlogani", "Nume": "C\u00e2rlogani", "Varianta 2": {"Nume": "K\u00eerlogani", "Limb\u0103": "Limba rom\u00e2n\u0103", "Hart\u0103": "Austriac\u0103"}, "Varianta 1": {"Nume": "C\u00e2rlogani", "Limb\u0103": "Limba rom\u00e2n\u0103", "Hart\u0103": "PDT"}, "ID": 14843, "Jude\u021b": "Olt"}}]}