{"type": "FeatureCollection", "name": "export_arqa.geojson", "features": [{"geometry": {"type": "Point", "coordinates": [26.6503998848614, 46.2859620041645]}, "type": "Feature", "properties": {"Nivel": 3, "Form\u0103": "\u00cen\u0103l\u021bime", "marker-color": "#e55b5b", "Tip": "arcaciu", "Nume": "V\u00e2rful Arcaciului", "Varianta 1": {"Nume": "V\u00e2rful Arcaciului", "Limb\u0103": "Limba rom\u00e2n\u0103", "Hart\u0103": "Mun\u021bii no\u0219tri"}, "ID": 15237, "Jude\u021b": "Bacau"}}, {"geometry": {"type": "Point", "coordinates": [24.2280635739535, 44.4665748025966]}, "type": "Feature", "properties": {"Nivel": 3, "Form\u0103": "Localitate", "marker-color": "#5be5e5", "Tip": "arce\u0219ti", "Nume": "Arce\u0219ti", "Varianta 2": {"Nume": "Arce\u0219ti", "Limb\u0103": "Limba rom\u00e2n\u0103", "Hart\u0103": "PDT"}, "Varianta 1": {"Nume": "Arce\u0219ti", "Limb\u0103": "Limba rom\u00e2n\u0103", "Hart\u0103": "ANCPI"}, "ID": 14840, "Jude\u021b": "Olt"}}, {"geometry": {"type": "Point", "coordinates": [27.2982274632192, 45.5213155693145]}, "type": "Feature", "properties": {"Nivel": 3, "Form\u0103": "Altele", "marker-color": "#e55b5b", "Tip": "arcaciu", "Nume": "Arcaciu", "Varianta 1": {"Nume": "Arcaciu", "Limb\u0103": "Limba rom\u00e2n\u0103", "Hart\u0103": "ANCPI"}, "ID": 15347, "Jude\u021b": "Vrancea"}}]}