{"type": "FeatureCollection", "name": "export_chi\u0219cani.geojson", "features": [{"geometry": {"type": "Point", "coordinates": [27.9357217137089, 45.1830692221521]}, "type": "Feature", "properties": {"Nivel": 3, "Form\u0103": "Localitate", "marker-color": "#e55b5b", "Tip": "chi\u0219cani", "Nume": "Chi\u0219canii", "Varianta 1": {"Nume": "Chi\u0219canii", "Limb\u0103": "Limba rom\u00e2n\u0103", "Hart\u0103": "PDT"}, "ID": 14825, "Jude\u021b": "Braila"}}]}