{"type": "FeatureCollection", "name": "export_m\u0103g\u0103rea\u021b\u0103.geojson", "features": [{"geometry": {"type": "Point", "coordinates": [23.9925876824195, 44.237682621138]}, "type": "Feature", "properties": {"Nivel": 3, "Form\u0103": "Vale", "marker-color": "#e55b5b", "Tip": "m\u0103g\u0103rea\u021b\u0103", "Nume": "Valea M\u0103g\u0103re\u021bei", "Varianta 1": {"Nume": "Valea M\u0103g\u0103re\u021bei", "Limb\u0103": "Limba rom\u00e2n\u0103", "Hart\u0103": "Geomil 25000"}, "ID": 3014, "Jude\u021b": "Dolj"}}, {"geometry": {"type": "Point", "coordinates": [25.7545128719185, 44.466406551602]}, "type": "Feature", "properties": {"Nivel": 3, "Form\u0103": "Altele", "marker-color": "#e55b5b", "Tip": "m\u0103g\u0103rea\u021b\u0103", "Nume": "La M\u0103g\u0103rea\u021b\u0103", "Varianta 1": {"Nume": "La M\u0103g\u0103rea\u021b\u0103", "Limb\u0103": "Limba rom\u00e2n\u0103", "Hart\u0103": "PDT"}, "ID": 4234, "Jude\u021b": "Giurgiu"}}, {"geometry": {"type": "Point", "coordinates": [28.2102396914731, 45.120414065026]}, "type": "Feature", "properties": {"Nivel": 3, "Form\u0103": "Vale", "marker-color": "#e55b5b", "Tip": "m\u0103g\u0103rea\u021b\u0103", "Nume": "Valea M\u0103g\u0103re\u021bei", "Varianta 2": {"Nume": "Valea M\u0103g\u0103re\u021bii", "Limb\u0103": "Limba rom\u00e2n\u0103", "Hart\u0103": "Geomil 25000"}, "Varianta 1": {"Nume": "Valea M\u0103g\u0103re\u021bei", "Limb\u0103": "Limba rom\u00e2n\u0103", "Hart\u0103": "PDT"}, "ID": 7686, "Jude\u021b": "Tulcea"}}]}