{"type": "FeatureCollection", "name": "export_schei.geojson", "features": [{"geometry": {"type": "Point", "coordinates": [24.5309159735697, 45.1063700481511]}, "type": "Feature", "properties": {"Nivel": 2, "Form\u0103": "Localitate", "marker-color": "#e55b5b", "Tip": "schei", "Nume": "Scheiul", "Varianta 1": {"Nume": "Scheiul", "Limb\u0103": "Limba rom\u00e2n\u0103", "Hart\u0103": "British Maps (1944)"}, "ID": 12579, "Jude\u021b": "Arges"}}, {"geometry": {"type": "Point", "coordinates": [25.6520636648428, 45.5988382007004]}, "type": "Feature", "properties": {"Nivel": 2, "Form\u0103": "Altele", "marker-color": "#e55b5b", "Tip": "schei", "Nume": "Piua din Schei", "Varianta 1": {"Nume": "Piua din Schei", "Limb\u0103": "Limba rom\u00e2n\u0103", "Hart\u0103": "PDT"}, "ID": 6843, "Jude\u021b": "Brasov"}}, {"geometry": {"type": "Point", "coordinates": [25.2811665234578, 45.0682771072189]}, "type": "Feature", "properties": {"Nivel": 2, "Form\u0103": "Vale", "marker-color": "#e55b5b", "Tip": "schei", "Nume": "Valea Schei", "Varianta 1": {"Nume": "Valea Schei", "Limb\u0103": "Limba rom\u00e2n\u0103", "Hart\u0103": "PDT"}, "ID": 8371, "Jude\u021b": "Dambovita"}}, {"geometry": {"type": "Point", "coordinates": [23.6390789024313, 44.8295238216568]}, "type": "Feature", "properties": {"Nivel": 2, "Form\u0103": "Vale", "marker-color": "#e55b5b", "Tip": "schei", "Nume": "Valea Scheiul", "Varianta 1": {"Nume": "Valea Scheiul", "Limb\u0103": "Limba rom\u00e2n\u0103", "Hart\u0103": "PDT"}, "ID": 13949, "Jude\u021b": "Gorj"}}, {"geometry": {"type": "Point", "coordinates": [22.5989653205462, 45.3049031091479]}, "type": "Feature", "properties": {"Nivel": 2, "Form\u0103": "\u00cen\u0103l\u021bime", "marker-color": "#e55b5b", "Tip": "schei", "Nume": "\u0218aua Scheiului", "Varianta 1": {"Nume": "\u0218aua Scheiului", "Limb\u0103": "Limba rom\u00e2n\u0103", "Hart\u0103": "Geomil 25000"}, "ID": 10330, "Jude\u021b": "Hunedoara"}}, {"geometry": {"type": "Point", "coordinates": [22.7396676901132, 45.5790276608726]}, "type": "Feature", "properties": {"Nivel": 2, "Form\u0103": "Localitate", "marker-color": "#e55b5b", "Tip": "schei", "Nume": "Schei", "Varianta 2": {"Nume": "Skei", "Limb\u0103": "Limba rom\u00e2n\u0103", "Hart\u0103": "Transilvania (1869-1870)"}, "Varianta 1": {"Nume": "Schei", "Limb\u0103": "Limba rom\u00e2n\u0103", "Hart\u0103": "Imperiul Habsburgic (1887)"}, "ID": 10801, "Jude\u021b": "Hunedoara"}}]}