{"type": "FeatureCollection", "name": "export_gioroc.geojson", "features": [{"geometry": {"type": "Point", "coordinates": [23.260674708824, 44.4735134499762]}, "type": "Feature", "properties": {"Nivel": 3, "Form\u0103": "Vale", "marker-color": "#e55bd1", "Tip": "giorcotin", "Nume": "Valea Giorcotinului", "Varianta 1": {"Nume": "Valea Giorcotinului", "Limb\u0103": "Limba rom\u00e2n\u0103", "Hart\u0103": "ANCPI"}, "ID": 14538, "Jude\u021b": "Dolj"}}, {"geometry": {"type": "Point", "coordinates": [23.9532891571448, 44.1203195297416]}, "type": "Feature", "properties": {"Nivel": 2, "Form\u0103": "Localitate", "marker-color": "#e5d15b", "Tip": "gioroc", "Nume": "Giorocul Mare", "Varianta 2": {"Nume": "Zorok mare", "Limb\u0103": "Limba rom\u00e2n\u0103", "Hart\u0103": "Austriac\u0103"}, "Varianta 3": {"Nume": "Csorog", "Limb\u0103": "Limba rom\u00e2n\u0103", "Hart\u0103": "Oltenia-Muntenia (1790)"}, "Varianta 1": {"Nume": "Giorocul Mare", "Limb\u0103": "Limba rom\u00e2n\u0103", "Hart\u0103": "PDT"}, "ID": 14412, "Jude\u021b": "Dolj"}}, {"geometry": {"type": "Point", "coordinates": [23.7214814039337, 44.4557278017009]}, "type": "Feature", "properties": {"Nivel": 3, "Form\u0103": "Vale", "marker-color": "#83e55b", "Tip": "gioroceanu", "Nume": "Valea Gioroceanu", "Varianta 1": {"Nume": "Valea Gioroceanu", "Limb\u0103": "Limba rom\u00e2n\u0103", "Hart\u0103": "ANCPI"}, "ID": 14763, "Jude\u021b": "Dolj"}}, {"geometry": {"type": "Point", "coordinates": [23.9664035827934, 43.9801766346627]}, "type": "Feature", "properties": {"Nivel": 3, "Form\u0103": "Localitate", "marker-color": "#5baae5", "Tip": "giorocel", "Nume": "Giorocelul", "Varianta 2": {"Nume": "Ciorocelu", "Limb\u0103": "Limba rom\u00e2n\u0103", "Hart\u0103": "PDT"}, "Varianta 1": {"Nume": "Giorocelul", "Limb\u0103": "Limba rom\u00e2n\u0103", "Hart\u0103": "Austriac\u0103"}, "ID": 14415, "Jude\u021b": "Dolj"}}, {"geometry": {"type": "Point", "coordinates": [22.7979183138382, 47.4300521484011]}, "type": "Feature", "properties": {"Nivel": 3, "Form\u0103": "Localitate", "marker-color": "#835be5", "Tip": "giorocuta", "Nume": "Giorocuta", "Varianta 1": {"Nume": "Giorocuta", "Limb\u0103": "Limba rom\u00e2n\u0103", "Hart\u0103": "PDT"}, "ID": 15329, "Jude\u021b": "Satu Mare"}}, {"geometry": {"type": "Point", "coordinates": [21.2352594407184, 45.6980904744736]}, "type": "Feature", "properties": {"Nivel": 3, "Form\u0103": "Localitate", "marker-color": "#e55b5b", "Tip": "giroc", "Nume": "Giroc", "Varianta 2": {"Nume": "Gyirok", "Limb\u0103": "Limba rom\u00e2n\u0103", "Hart\u0103": "Transilvania (1869-1870)"}, "Varianta 3": {"Nume": "Iurock", "Limb\u0103": "Limba rom\u00e2n\u0103", "Hart\u0103": "Transilvania (1769-1773)"}, "Varianta 1": {"Nume": "Giroc", "Limb\u0103": "Limba rom\u00e2n\u0103", "Hart\u0103": "PDT"}, "ID": 15576, "Jude\u021b": "Timis"}}, {"geometry": {"type": "Point", "coordinates": [21.4768348519395, 46.0578367978614]}, "type": "Feature", "properties": {"Nivel": 3, "Form\u0103": "Vale", "marker-color": "#5be5aa", "Tip": "giuroc", "Nume": "Valea Giurocul", "Varianta 1": {"Nume": "Valea Giurocul", "Limb\u0103": "Limba rom\u00e2n\u0103", "Hart\u0103": "PDT"}, "ID": 15590, "Jude\u021b": "Timis"}}]}