{"type": "FeatureCollection", "name": "export_gioroc.geojson", "features": [{"geometry": {"type": "Point", "coordinates": [23.260674708824, 44.4735134499762]}, "type": "Feature", "properties": {"Nivel": 3, "Form\u0103": "Vale", "marker-color": "#a05be5", "Tip": "giorcotin", "Nume": "Valea Giorcotinului", "Varianta 1": {"Nume": "Valea Giorcotinului", "Limb\u0103": "Limba rom\u00e2n\u0103", "Hart\u0103": "ANCPI"}, "ID": 14538, "Jude\u021b": "Dolj"}}, {"geometry": {"type": "Point", "coordinates": [23.9532891571448, 44.1203195297416]}, "type": "Feature", "properties": {"Nivel": 2, "Form\u0103": "Localitate", "marker-color": "#e55b5b", "Tip": "gioroc", "Nume": "Giorocul Mare", "Varianta 2": {"Nume": "Zorok mare", "Limb\u0103": "Limba rom\u00e2n\u0103", "Hart\u0103": "Austriac\u0103"}, "Varianta 3": {"Nume": "Csorog", "Limb\u0103": "Limba rom\u00e2n\u0103", "Hart\u0103": "Oltenia-Muntenia (1790)"}, "Varianta 1": {"Nume": "Giorocul Mare", "Limb\u0103": "Limba rom\u00e2n\u0103", "Hart\u0103": "PDT"}, "ID": 14412, "Jude\u021b": "Dolj"}}, {"geometry": {"type": "Point", "coordinates": [23.7214814039337, 44.4557278017009]}, "type": "Feature", "properties": {"Nivel": 3, "Form\u0103": "Vale", "marker-color": "#a0e55b", "Tip": "gioroceanu", "Nume": "Valea Gioroceanu", "Varianta 1": {"Nume": "Valea Gioroceanu", "Limb\u0103": "Limba rom\u00e2n\u0103", "Hart\u0103": "ANCPI"}, "ID": 14763, "Jude\u021b": "Dolj"}}, {"geometry": {"type": "Point", "coordinates": [23.9664035827934, 43.9801766346627]}, "type": "Feature", "properties": {"Nivel": 3, "Form\u0103": "Localitate", "marker-color": "#5be5e5", "Tip": "giorocel", "Nume": "Giorocelul", "Varianta 2": {"Nume": "Ciorocelu", "Limb\u0103": "Limba rom\u00e2n\u0103", "Hart\u0103": "PDT"}, "Varianta 1": {"Nume": "Giorocelul", "Limb\u0103": "Limba rom\u00e2n\u0103", "Hart\u0103": "Austriac\u0103"}, "ID": 14415, "Jude\u021b": "Dolj"}}]}