{"type": "FeatureCollection", "name": "export_h\u00e2rseni.geojson", "features": [{"geometry": {"type": "Point", "coordinates": [25.0106776071593, 45.7524440004633]}, "type": "Feature", "properties": {"Nivel": 3, "Form\u0103": "Localitate", "marker-color": "#e55b5b", "Tip": "h\u00e2rseni", "Nume": "H\u00e2rseni", "Varianta 2": {"Nume": "Herseni", "Limb\u0103": "Limba rom\u00e2n\u0103", "Hart\u0103": "Transilvania (1869-1870)"}, "Varianta 3": {"Nume": "Herseny", "Limb\u0103": "Limba rom\u00e2n\u0103", "Hart\u0103": "Transilvania (1769-1773)"}, "Varianta 1": {"Nume": "H\u00e2rseni", "Limb\u0103": "Limba rom\u00e2n\u0103", "Hart\u0103": "ANCPI"}, "ID": 14690, "Jude\u021b": "Brasov"}}]}