{"type": "FeatureCollection", "name": "export_g\u0103mani.geojson", "features": [{"geometry": {"type": "Point", "coordinates": [23.425282665759, 45.1367820780666]}, "type": "Feature", "properties": {"Nivel": 3, "Form\u0103": "Localitate", "marker-color": "#e55b5b", "Tip": "g\u0103mani", "Nume": "G\u00e2m\u00e2ni", "Varianta 2": {"Nume": "G\u0103mani", "Limb\u0103": "Limba rom\u00e2n\u0103", "Hart\u0103": "ANCPI"}, "Varianta 1": {"Nume": "G\u00e2m\u00e2ni", "Limb\u0103": "Limba rom\u00e2n\u0103", "Hart\u0103": "Austriac\u0103"}, "ID": 14765, "Jude\u021b": "Gorj"}}]}