{"type": "FeatureCollection", "name": "export_t\u0103t\u0103r\u0103i.geojson", "features": [{"geometry": {"type": "Point", "coordinates": [25.9280408593726, 44.7352393690534]}, "type": "Feature", "properties": {"Nivel": 3, "Form\u0103": "Localitate", "marker-color": "#e55b5b", "Tip": "t\u0103t\u0103r\u0103i", "Nume": "T\u0103t\u0103r\u0103i", "Varianta 2": {"Nume": "T\u00e2t\u00e2r\u00e2i", "Limb\u0103": "Limba rom\u00e2n\u0103", "Hart\u0103": "Austriac\u0103"}, "Varianta 1": {"Nume": "T\u0103t\u0103r\u0103i", "Limb\u0103": "Limba rom\u00e2n\u0103", "Hart\u0103": "Geomil 25000"}, "ID": 4246, "Jude\u021b": "Prahova"}}]}