{"type": "FeatureCollection", "name": "export_argint\u0103rie.geojson", "features": [{"geometry": {"type": "Point", "coordinates": [26.7611542705969, 46.1317481953957]}, "type": "Feature", "properties": {"Nivel": 4, "Form\u0103": "Vale", "marker-color": "#e55b5b", "Tip": "argint\u0103rie", "Nume": "Argint\u0103ria", "Varianta 1": {"Nume": "Argint\u0103ria", "Limb\u0103": "Limba rom\u00e2n\u0103", "Hart\u0103": "Geomil 25000"}, "ID": 12942, "Jude\u021b": "Bacau"}}, {"geometry": {"type": "Point", "coordinates": [26.3427621848868, 46.2683430727001]}, "type": "Feature", "properties": {"Nivel": 4, "Form\u0103": "Vale", "marker-color": "#e55b5b", "Tip": "argint\u0103rie", "Nume": "Argint\u0103ria", "Varianta 1": {"Nume": "Argint\u0103ria", "Limb\u0103": "Limba rom\u00e2n\u0103", "Hart\u0103": "Geomil 25000"}, "ID": 14079, "Jude\u021b": "Bacau"}}, {"geometry": {"type": "Point", "coordinates": [26.308254858194, 46.5647855482536]}, "type": "Feature", "properties": {"Nivel": 4, "Form\u0103": "P\u0103dure", "marker-color": "#e55b5b", "Tip": "argint\u0103rie", "Nume": "P\u0103durea Argint\u0103riei", "Varianta 1": {"Nume": "P\u0103durea Argint\u0103riei", "Limb\u0103": "Limba rom\u00e2n\u0103", "Hart\u0103": "Geomil 25000"}, "ID": 10941, "Jude\u021b": "Bacau"}}, {"geometry": {"type": "Point", "coordinates": [26.5638305889224, 46.3844078355393]}, "type": "Feature", "properties": {"Nivel": 4, "Form\u0103": "Vale", "marker-color": "#e55b5b", "Tip": "argint\u0103rie", "Nume": "Valea Argint\u0103riei", "Varianta 1": {"Nume": "Valea Argint\u0103riei", "Limb\u0103": "Limba rom\u00e2n\u0103", "Hart\u0103": "PDT"}, "ID": 7929, "Jude\u021b": "Bacau"}}, {"geometry": {"type": "Point", "coordinates": [26.2062012792191, 45.5256302520941]}, "type": "Feature", "properties": {"Nivel": 4, "Form\u0103": "Altele", "marker-color": "#e55b5b", "Tip": "argint\u0103rie", "Nume": "Argint\u0103ria", "Varianta 1": {"Nume": "Argint\u0103ria", "Limb\u0103": "Limba rom\u00e2n\u0103", "Hart\u0103": "Geomil 25000"}, "ID": 6041, "Jude\u021b": "Buzau"}}, {"geometry": {"type": "Point", "coordinates": [25.6941513223848, 47.0076404580216]}, "type": "Feature", "properties": {"Nivel": 4, "Form\u0103": "Vale", "marker-color": "#e55b5b", "Tip": "argint\u0103rie", "Nume": "Argint\u0103ria", "Varianta 1": {"Nume": "Argint\u0103ria", "Limb\u0103": "Limba rom\u00e2n\u0103", "Hart\u0103": "Geomil 25000"}, "ID": 12869, "Jude\u021b": "Harghita"}}, {"geometry": {"type": "Point", "coordinates": [25.7063654842128, 47.0184924903913]}, "type": "Feature", "properties": {"Nivel": 4, "Form\u0103": "\u00cen\u0103l\u021bime", "marker-color": "#e55b5b", "Tip": "argint\u0103rie", "Nume": "Peatra Argint\u0103riei", "Varianta 1": {"Nume": "Peatra Argint\u0103riei", "Limb\u0103": "Limba rom\u00e2n\u0103", "Hart\u0103": "Imperiul Habsburgic (1887)"}, "ID": 10610, "Jude\u021b": "Harghita"}}, {"geometry": {"type": "Point", "coordinates": [25.7927739897904, 47.0206737200739]}, "type": "Feature", "properties": {"Nivel": 4, "Form\u0103": "Vale", "marker-color": "#e55b5b", "Tip": "argint\u0103rie", "Nume": "Argint\u0103ria", "Varianta 1": {"Nume": "Argint\u0103ria", "Limb\u0103": "Limba rom\u00e2n\u0103", "Hart\u0103": "Geomil 25000"}, "ID": 11717, "Jude\u021b": "Neamt"}}, {"geometry": {"type": "Point", "coordinates": [26.1780887185152, 47.0354040871906]}, "type": "Feature", "properties": {"Nivel": 4, "Form\u0103": "Vale", "marker-color": "#e55b5b", "Tip": "argint\u0103rie", "Nume": "Argint\u0103riei", "Varianta 1": {"Nume": "Argint\u0103riei", "Limb\u0103": "Limba rom\u00e2n\u0103", "Hart\u0103": "Geomil 25000"}, "ID": 11651, "Jude\u021b": "Neamt"}}, {"geometry": {"type": "Point", "coordinates": [25.7229331592367, 47.0813235050884]}, "type": "Feature", "properties": {"Nivel": 4, "Form\u0103": "Vale", "marker-color": "#e55b5b", "Tip": "argint\u0103rie", "Nume": "P\u00e2r\u00e2ul Argint\u0103riei", "Varianta 1": {"Nume": "P\u00e2r\u00e2ul Argint\u0103riei", "Limb\u0103": "Limba rom\u00e2n\u0103", "Hart\u0103": "Moldova (1892-1898)"}, "ID": 9946, "Jude\u021b": "Neamt"}}, {"geometry": {"type": "Point", "coordinates": [25.8136633009946, 46.9831171131545]}, "type": "Feature", "properties": {"Nivel": 4, "Form\u0103": "Vale", "marker-color": "#e55b5b", "Tip": "argint\u0103rie", "Nume": "P\u00e2r\u00e2ul Argint\u0103riei", "Varianta 1": {"Nume": "P\u00e2r\u00e2ul Argint\u0103riei", "Limb\u0103": "Limba rom\u00e2n\u0103", "Hart\u0103": "PDT"}, "ID": 11720, "Jude\u021b": "Neamt"}}]}