{"type": "FeatureCollection", "name": "export_bourie.geojson", "features": [{"geometry": {"type": "Point", "coordinates": [26.6304316236497, 47.625122261669]}, "type": "Feature", "properties": {"Nivel": 2, "Form\u0103": "Altele", "marker-color": "#e55b5b", "Tip": "bourie", "Nume": "Bou\u0103riea", "Varianta 1": {"Nume": "Bou\u0103riea", "Limb\u0103": "Limba rom\u00e2n\u0103", "Hart\u0103": "PDT"}, "ID": 7772, "Jude\u021b": "Botosani"}}, {"geometry": {"type": "Point", "coordinates": [24.9617121784532, 45.7079164011552]}, "type": "Feature", "properties": {"Nivel": 2, "Form\u0103": "Deal", "marker-color": "#e55b5b", "Tip": "bourie", "Nume": "Dealul Bouriei", "Varianta 1": {"Nume": "Dealul Bouriei", "Limb\u0103": "Limba rom\u00e2n\u0103", "Hart\u0103": "Geomil 25000"}, "ID": 9689, "Jude\u021b": "Brasov"}}, {"geometry": {"type": "Point", "coordinates": [28.0297391420399, 45.6594803906841]}, "type": "Feature", "properties": {"Nivel": 2, "Form\u0103": "Deal", "marker-color": "#e55b5b", "Tip": "bourie", "Nume": "Dealul Bouriei", "Varianta 1": {"Nume": "Dealul Bouriei", "Limb\u0103": "Limba rom\u00e2n\u0103", "Hart\u0103": "Geomil 25000"}, "ID": 702, "Jude\u021b": "Galati"}}, {"geometry": {"type": "Point", "coordinates": [25.8702663985929, 47.0984790657098]}, "type": "Feature", "properties": {"Nivel": 2, "Form\u0103": "Altele", "marker-color": "#e55b5b", "Tip": "bourie", "Nume": "Bouria", "Varianta 1": {"Nume": "Bouria", "Limb\u0103": "Limba rom\u00e2n\u0103", "Hart\u0103": "PDT"}, "ID": 9104, "Jude\u021b": "Neamt"}}, {"geometry": {"type": "Point", "coordinates": [26.2388339034603, 47.0316439342494]}, "type": "Feature", "properties": {"Nivel": 2, "Form\u0103": "Poian\u0103", "marker-color": "#e55b5b", "Tip": "bourie", "Nume": "Poiana Bouriei", "Varianta 1": {"Nume": "Poiana Bouriei", "Limb\u0103": "Limba rom\u00e2n\u0103", "Hart\u0103": "Geomil 25000"}, "ID": 11387, "Jude\u021b": "Neamt"}}]}