{"type": "FeatureCollection", "name": "export_urs\u0103rei.geojson", "features": [{"geometry": {"type": "Point", "coordinates": [23.1973732541792, 45.0636089140083]}, "type": "Feature", "properties": {"Nivel": 4, "Form\u0103": "Deal", "marker-color": "#e55b5b", "Tip": "urs\u0103rei", "Nume": "Dealul Urs\u0103reilor", "Varianta 1": {"Nume": "Dealul Urs\u0103reilor", "Limb\u0103": "Limba rom\u00e2n\u0103", "Hart\u0103": "Geomil 25000"}, "ID": 5137, "Jude\u021b": "Gorj"}}]}