{"type": "FeatureCollection", "name": "export_z\u00e2mbroaia.geojson", "features": [{"geometry": {"type": "Point", "coordinates": [26.129812221735, 45.1990617555568]}, "type": "Feature", "properties": {"Nivel": 3, "Form\u0103": "Localitate", "marker-color": "#e55b5b", "Tip": "z\u00e2mbroaia", "Nume": "Z\u00e2mbroaia", "Varianta 1": {"Nume": "Z\u00e2mbroaia", "Limb\u0103": "Limba rom\u00e2n\u0103", "Hart\u0103": "Geomil 25000"}, "ID": 7484, "Jude\u021b": "Prahova"}}, {"geometry": {"type": "Point", "coordinates": [26.6066953939164, 47.4522938161228]}, "type": "Feature", "properties": {"Nivel": 3, "Form\u0103": "C\u00e2mp", "marker-color": "#e55b5b", "Tip": "z\u00e2mbroaia", "Nume": "\u0218esul Z\u00e2mbroia", "Varianta 2": {"Nume": "\u0218esu Z\u00e2mbroia", "Limb\u0103": "Limba rom\u00e2n\u0103", "Hart\u0103": "PDT"}, "Varianta 1": {"Nume": "\u0218esul Z\u00e2mbroia", "Limb\u0103": "Limba rom\u00e2n\u0103", "Hart\u0103": "Geomil 25000"}, "ID": 7790, "Jude\u021b": "Suceava"}}, {"geometry": {"type": "Point", "coordinates": [25.0628971310853, 47.4372307880628]}, "type": "Feature", "properties": {"Nivel": 3, "Form\u0103": "\u00cen\u0103l\u021bime", "marker-color": "#e55b5b", "Tip": "z\u00e2mbroaia", "Nume": "Z\u00eembroaia", "Varianta 1": {"Nume": "Z\u00eembroaia", "Limb\u0103": "Limba rom\u00e2n\u0103", "Hart\u0103": "Geomil 25000"}, "ID": 6380, "Jude\u021b": "Suceava"}}]}