{"type": "FeatureCollection", "name": "export_veveri\u021b\u0103.geojson", "features": [{"geometry": {"type": "Point", "coordinates": [26.7593632481749, 45.5116926997122]}, "type": "Feature", "properties": {"Nivel": 2, "Form\u0103": "Deal", "marker-color": "#e55b5b", "Tip": "veveri\u021b\u0103", "Nume": "Dealul Veveri\u021bei", "Varianta 1": {"Nume": "Dealul Veveri\u021bei", "Limb\u0103": "Limba rom\u00e2n\u0103", "Hart\u0103": "PDT"}, "ID": 9247, "Jude\u021b": "Buzau"}}, {"geometry": {"type": "Point", "coordinates": [26.5059952245227, 45.1828910470467]}, "type": "Feature", "properties": {"Nivel": 2, "Form\u0103": "Vale", "marker-color": "#e55b5b", "Tip": "veveri\u021b\u0103", "Nume": "Isvoru Veveri\u021bei", "Varianta 1": {"Nume": "Isvoru Veveri\u021bei", "Limb\u0103": "Limba rom\u00e2n\u0103", "Hart\u0103": "PDT"}, "ID": 13617, "Jude\u021b": "Buzau"}}, {"geometry": {"type": "Point", "coordinates": [25.6052391323164, 44.9769597095243]}, "type": "Feature", "properties": {"Nivel": 2, "Form\u0103": "\u00cen\u0103l\u021bime", "marker-color": "#e55b5b", "Tip": "veveri\u021b\u0103", "Nume": "Plaiul Veveri\u021bei", "Varianta 1": {"Nume": "Plaiul Veveri\u021bei", "Limb\u0103": "Limba rom\u00e2n\u0103", "Hart\u0103": "PDT"}, "ID": 12402, "Jude\u021b": "Dambovita"}}, {"geometry": {"type": "Point", "coordinates": [27.8203917322526, 45.8026319941419]}, "type": "Feature", "properties": {"Nivel": 2, "Form\u0103": "Deal", "marker-color": "#e55b5b", "Tip": "veveri\u021b\u0103", "Nume": "Dealul Veveri\u021ba", "Varianta 2": {"Nume": "Dealul Veveri\u021ba", "Limb\u0103": "Limba rom\u00e2n\u0103", "Hart\u0103": "PDT"}, "Varianta 1": {"Nume": "Dealul Veveri\u021ba", "Limb\u0103": "Limba rom\u00e2n\u0103", "Hart\u0103": "Geomil 25000"}, "ID": 2189, "Jude\u021b": "Galati"}}, {"geometry": {"type": "Point", "coordinates": [23.4516646531069, 45.2853742742897]}, "type": "Feature", "properties": {"Nivel": 2, "Form\u0103": "\u00cen\u0103l\u021bime", "marker-color": "#e55b5b", "Tip": "veveri\u021b\u0103", "Nume": "Culmea Veveri\u021bei", "Varianta 1": {"Nume": "Culmea Veveri\u021bei", "Limb\u0103": "Limba rom\u00e2n\u0103", "Hart\u0103": "Geomil 25000"}, "ID": 2918, "Jude\u021b": "Gorj"}}, {"geometry": {"type": "Point", "coordinates": [24.1640342671145, 47.774078106846]}, "type": "Feature", "properties": {"Nivel": 2, "Form\u0103": "\u00cen\u0103l\u021bime", "marker-color": "#e55b5b", "Tip": "veveri\u021b\u0103", "Nume": "V\u00e2rful Veveri\u021bei", "Varianta 1": {"Nume": "V\u00e2rful Veveri\u021bei", "Limb\u0103": "Limba rom\u00e2n\u0103", "Hart\u0103": "Geomil 25000"}, "ID": 917, "Jude\u021b": "Maramures"}}, {"geometry": {"type": "Point", "coordinates": [26.1411280884838, 46.7545689764802]}, "type": "Feature", "properties": {"Nivel": 2, "Form\u0103": "\u00cen\u0103l\u021bime", "marker-color": "#e55b5b", "Tip": "veveri\u021b\u0103", "Nume": "B\u00e2tca Veveri\u021bei", "Varianta 1": {"Nume": "B\u00e2tca Veveri\u021bei", "Limb\u0103": "Limba rom\u00e2n\u0103", "Hart\u0103": "PDT"}, "ID": 6526, "Jude\u021b": "Neamt"}}, {"geometry": {"type": "Point", "coordinates": [24.5900115227802, 44.6176800343621]}, "type": "Feature", "properties": {"Nivel": 2, "Form\u0103": "Vale", "marker-color": "#e55b5b", "Tip": "veveri\u021b\u0103", "Nume": "Valea Veveri\u021ba", "Varianta 1": {"Nume": "Valea Veveri\u021ba", "Limb\u0103": "Limba rom\u00e2n\u0103", "Hart\u0103": "Geomil 25000"}, "ID": 3047, "Jude\u021b": "Olt"}}, {"geometry": {"type": "Point", "coordinates": [24.1890417644861, 45.430746764789]}, "type": "Feature", "properties": {"Nivel": 2, "Form\u0103": "\u00cen\u0103l\u021bime", "marker-color": "#e55b5b", "Tip": "veveri\u021b\u0103", "Nume": "V\u00e2rful Veveri\u021bei", "Varianta 1": {"Nume": "V\u00e2rful Veveri\u021bei", "Limb\u0103": "Limba rom\u00e2n\u0103", "Hart\u0103": "Geomil 25000"}, "ID": 1170, "Jude\u021b": "Valcea"}}]}