{"type": "FeatureCollection", "name": "export_jidov.geojson", "features": [{"geometry": {"type": "Point", "coordinates": [26.9701884641678, 46.1241936924025]}, "type": "Feature", "properties": {"Nivel": 3, "Form\u0103": "Vale", "marker-color": "#e55b5b", "Tip": "jidov", "Nume": "Valea Jidovului", "Varianta 2": {"Nume": "Valea Jidovului", "Limb\u0103": "Limba rom\u00e2n\u0103", "Hart\u0103": "Geomil 25000"}, "Varianta 1": {"Nume": "Valea Jidovului", "Limb\u0103": "Limba rom\u00e2n\u0103", "Hart\u0103": "PDT"}, "ID": 5305, "Jude\u021b": "Bacau"}}, {"geometry": {"type": "Point", "coordinates": [25.2561463491165, 45.1278001500078]}, "type": "Feature", "properties": {"Nivel": 3, "Form\u0103": "\u00cen\u0103l\u021bime", "marker-color": "#e55b5b", "Tip": "jidov", "Nume": "Plaiul Jidovu", "Varianta 1": {"Nume": "Plaiul Jidovu", "Limb\u0103": "Limba rom\u00e2n\u0103", "Hart\u0103": "PDT"}, "ID": 8825, "Jude\u021b": "Dambovita"}}, {"geometry": {"type": "Point", "coordinates": [25.0180667703827, 47.4568134647668]}, "type": "Feature", "properties": {"Nivel": 3, "Form\u0103": "Vale", "marker-color": "#e55b5b", "Tip": "jidov", "Nume": "Jidovul", "Varianta 1": {"Nume": "Jidovul", "Limb\u0103": "Limba rom\u00e2n\u0103", "Hart\u0103": "Geomil 25000"}, "ID": 12893, "Jude\u021b": "Bistrita Nasaud"}}, {"geometry": {"type": "Point", "coordinates": [23.6523640429366, 47.7010333282902]}, "type": "Feature", "properties": {"Nivel": 4, "Form\u0103": "Vale", "marker-color": "#5be5e5", "Tip": "jidovoaie", "Nume": "Valea Jidovoaie", "Varianta 1": {"Nume": "Valea Jidovoaie", "Limb\u0103": "Limba rom\u00e2n\u0103", "Hart\u0103": "PDT"}, "ID": 7216, "Jude\u021b": "Maramures"}}, {"geometry": {"type": "Point", "coordinates": [23.9165501721112, 45.5221296164043]}, "type": "Feature", "properties": {"Nivel": 4, "Form\u0103": "\u00cen\u0103l\u021bime", "marker-color": "#a05be5", "Tip": "jid", "Nume": "V\u00e2rful Jidului", "Varianta 1": {"Nume": "V\u00e2rful Jidului", "Limb\u0103": "Limba rom\u00e2n\u0103", "Hart\u0103": "Geomil 25000"}, "ID": 7414, "Jude\u021b": "Valcea"}}, {"geometry": {"type": "Point", "coordinates": [26.5780831396091, 46.9031352863592]}, "type": "Feature", "properties": {"Nivel": 5, "Form\u0103": "Localitate", "marker-color": "#a0e55b", "Tip": "jide\u0219ti", "Nume": "Jide\u0219ti", "Varianta 1": {"Nume": "Jide\u0219ti", "Limb\u0103": "Limba rom\u00e2n\u0103", "Hart\u0103": "Moldova (1892-1898)"}, "ID": 9624, "Jude\u021b": "Neamt"}}]}