{"type": "FeatureCollection", "name": "export_iez\u0103rie.geojson", "features": [{"geometry": {"type": "Point", "coordinates": [25.85175478248, 47.2340374201871]}, "type": "Feature", "properties": {"Nivel": 3, "Form\u0103": "\u00cen\u0103l\u021bime", "marker-color": "#e55b5b", "Tip": "iez\u0103rie", "Nume": "Piciorul Iez\u0103riei", "Varianta 1": {"Nume": "Piciorul Iez\u0103riei", "Limb\u0103": "Limba rom\u00e2n\u0103", "Hart\u0103": "PDT"}, "ID": 6453, "Jude\u021b": "Neamt"}}]}