{"type": "FeatureCollection", "name": "export_t\u0103buce\u0219ti.geojson", "features": [{"geometry": {"type": "Point", "coordinates": [27.4397003550933, 46.1688741665855]}, "type": "Feature", "properties": {"Nivel": 3, "Form\u0103": "Localitate", "marker-color": "#e55b5b", "Tip": "t\u0103buce\u0219ti", "Nume": "T\u0103buce\u0219ti", "Varianta 2": {"Nume": "T\u0103b\u0103ce\u0219ti", "Limb\u0103": "Limba rom\u00e2n\u0103", "Hart\u0103": "PDT"}, "Varianta 1": {"Nume": "T\u0103buce\u0219ti", "Limb\u0103": "Limba rom\u00e2n\u0103", "Hart\u0103": "ANCPI"}, "ID": 14645, "Jude\u021b": "Vaslui"}}]}