{"type": "FeatureCollection", "name": "export_mistre\u021b.geojson", "features": [{"geometry": {"type": "Point", "coordinates": [23.7265137575226, 47.7765354016814]}, "type": "Feature", "properties": {"Nivel": 3, "Form\u0103": "Vale", "Tip": "mistre\u021b", "Nume": "Valea Mistre\u021bu", "Varianta 1": {"Nume": "Valea Mistre\u021bu", "Limb\u0103": "Limba rom\u00e2n\u0103", "Hart\u0103": "Geomil 25000"}, "ID": 4470, "Jude\u021b": "Maramures"}}, {"geometry": {"type": "Point", "coordinates": [24.900999206608, 45.3821038887499]}, "type": "Feature", "properties": {"Nivel": 3, "Form\u0103": "Vale", "Tip": "mistre\u021b", "Nume": "Valea Mistre\u021bului", "Varianta 1": {"Nume": "Valea Mistre\u021bului", "Limb\u0103": "Limba rom\u00e2n\u0103", "Hart\u0103": "Geomil 25000"}, "ID": 4996, "Jude\u021b": "Arges"}}, {"geometry": {"type": "Point", "coordinates": [26.3400572311642, 46.2905783390767]}, "type": "Feature", "properties": {"Nivel": 3, "Form\u0103": "Vale", "Tip": "mistre\u021b", "Nume": "Mistre\u021bul", "Varianta 1": {"Nume": "Mistre\u021bul", "Limb\u0103": "Limba rom\u00e2n\u0103", "Hart\u0103": "Geomil 25000"}, "ID": 9963, "Jude\u021b": "Bacau"}}, {"geometry": {"type": "Point", "coordinates": [27.9772293112051, 44.4037074331778]}, "type": "Feature", "properties": {"Nivel": 3, "Form\u0103": "Ap\u0103-deal-c\u00e2mpie", "Tip": "mistre\u021b", "Nume": "Jap\u0219a Mistrea\u021ba", "Varianta 1": {"Nume": "Jap\u0219a Mistrea\u021ba", "Limb\u0103": "Limba rom\u00e2n\u0103", "Hart\u0103": "PDT"}, "ID": 9976, "Jude\u021b": "Ialomita"}}, {"geometry": {"type": "Point", "coordinates": [25.1312769508808, 46.6751545196039]}, "type": "Feature", "properties": {"Nivel": 3, "Form\u0103": "Deal", "Tip": "mistre\u021b", "Nume": "Dealul Mistre\u021bului", "Varianta 1": {"Nume": "Dealul Mistre\u021bului", "Limb\u0103": "Limba rom\u00e2n\u0103", "Hart\u0103": "Geomil 25000"}, "ID": 10846, "Jude\u021b": "Mures"}}]}