{"type": "FeatureCollection", "name": "export_ursoi\u021b\u0103.geojson", "features": [{"geometry": {"type": "Point", "coordinates": [22.5594985528242, 46.1856663757001]}, "type": "Feature", "properties": {"Nivel": 3, "Form\u0103": "Vale", "Tip": "ursoi\u021b\u0103", "Nume": "Valea Ursoi\u021bei", "Varianta 1": {"Nume": "Valea Ursoi\u021bei", "Limb\u0103": "Limba rom\u00e2n\u0103", "Hart\u0103": "PDT"}, "ID": 9003, "Jude\u021b": "Hunedoara"}}]}