{"type": "FeatureCollection", "name": "export_berbec\u0103rie.geojson", "features": [{"geometry": {"type": "Point", "coordinates": [27.4800488304182, 47.4461694228102]}, "type": "Feature", "properties": {"Nivel": 3, "Form\u0103": "Altele", "Tip": "berbec\u0103rie", "Nume": "La Berbec\u0103rie", "Varianta 1": {"Nume": "La Berbec\u0103rie", "Limb\u0103": "Limba rom\u00e2n\u0103", "Hart\u0103": "PDT"}, "ID": 4867, "Jude\u021b": "Iasi"}}]}