{"type": "FeatureCollection", "name": "export_cobuz.geojson", "features": [{"geometry": {"type": "Point", "coordinates": [25.759262364341, 47.1893394543944]}, "type": "Feature", "properties": {"Nivel": 3, "Form\u0103": "Altele", "marker-color": "#e55b5b", "Tip": "cobuz", "Nume": "Piciorul lui Cobuz", "Varianta 1": {"Nume": "Piciorul lui Cobuz", "Limb\u0103": "Limba rom\u00e2n\u0103", "Hart\u0103": "PDT"}, "ID": 15476, "Jude\u021b": "Neamt"}}]}