{"type": "FeatureCollection", "name": "export_beschen.geojson", "features": [{"geometry": {"type": "Point", "coordinates": [24.7638239472749, 45.8022232258937]}, "type": "Feature", "properties": {"Nivel": 3, "Form\u0103": "Localitate", "marker-color": "#e55b5b", "Tip": "beschen", "Nume": "Beschenbach (Valea Pecinegilor)", "Varianta 1": {"Nume": "Beschenbach (Valea Pecinegilor)", "Limb\u0103": "Limba german\u0103", "Hart\u0103": "Transilvania (1869-1870)"}, "ID": 11776, "Jude\u021b": "Brasov"}}]}