{"type": "FeatureCollection", "name": "export_ursuleas\u0103.geojson", "features": [{"geometry": {"type": "Point", "coordinates": [25.4365954030595, 47.7195505850868]}, "type": "Feature", "properties": {"Nivel": 4, "Form\u0103": "Vale", "marker-color": "#e55b5b", "Tip": "ursuleas\u0103", "Nume": "Ursuleasa", "Varianta 1": {"Nume": "Ursuleasa", "Limb\u0103": "Limba rom\u00e2n\u0103", "Hart\u0103": "Geomil 25000"}, "ID": 7235, "Jude\u021b": "Suceava"}}]}