{"type": "FeatureCollection", "name": "export_sirinca.geojson", "features": [{"geometry": {"type": "Point", "coordinates": [22.1200752179417, 44.6477092842272]}, "type": "Feature", "properties": {"Nivel": 3, "Form\u0103": "Vale", "marker-color": "#e55b5b", "Tip": "sirinca", "Nume": "Sirinka B.", "Varianta 2": {"Nume": "Valea Sirinca", "Limb\u0103": "Limba rom\u00e2n\u0103", "Hart\u0103": "ANCPI"}, "Varianta 1": {"Nume": "Sirinka B.", "Limb\u0103": "Limba rom\u00e2n\u0103", "Hart\u0103": "Ungar\u0103 1869"}, "ID": 15851, "Jude\u021b": "Caras Severin"}}]}