{"type": "FeatureCollection", "name": "export_nedei.geojson", "features": [{"geometry": {"type": "Point", "coordinates": [23.6496088885585, 45.803160788103]}, "type": "Feature", "properties": {"Nivel": 3, "Form\u0103": "Deal", "marker-color": "#e55b5b", "Tip": "nedei", "Nume": "Dealu Nedeiu", "Varianta 1": {"Nume": "Dealu Nedeiu", "Limb\u0103": "Limba rom\u00e2n\u0103", "Hart\u0103": "Geomil 25000"}, "ID": 2520, "Jude\u021b": "Sibiu"}}, {"geometry": {"type": "Point", "coordinates": [23.8418705988198, 45.3221584822645]}, "type": "Feature", "properties": {"Nivel": 3, "Form\u0103": "\u00cen\u0103l\u021bime", "marker-color": "#e55b5b", "Tip": "nedei", "Nume": "La Nedei", "Varianta 1": {"Nume": "La Nedei", "Limb\u0103": "Limba rom\u00e2n\u0103", "Hart\u0103": "Geomil 25000"}, "ID": 2929, "Jude\u021b": "Gorj"}}, {"geometry": {"type": "Point", "coordinates": [22.9550852129026, 45.2354862000767]}, "type": "Feature", "properties": {"Nivel": 3, "Form\u0103": "\u00cen\u0103l\u021bime", "marker-color": "#e55b5b", "Tip": "nedei", "Nume": "V\u00e2rfu Nedeilor", "Varianta 1": {"Nume": "V\u00e2rfu Nedeilor", "Limb\u0103": "Limba rom\u00e2n\u0103", "Hart\u0103": "Geomil 25000"}, "ID": 11579, "Jude\u021b": "Gorj"}}, {"geometry": {"type": "Point", "coordinates": [23.0217884887153, 45.5263272726475]}, "type": "Feature", "properties": {"Nivel": 3, "Form\u0103": "Deal", "marker-color": "#e55b5b", "Tip": "nedei", "Nume": "Dial Nedej", "Varianta 1": {"Nume": "Dial Nedej", "Limb\u0103": "Limba rom\u00e2n\u0103", "Hart\u0103": "Transilvania (1769-1773)"}, "ID": 12733, "Jude\u021b": "Hunedoara"}}]}