{"type": "FeatureCollection", "name": "export_barancea.geojson", "features": [{"geometry": {"type": "Point", "coordinates": [26.8515602628314, 47.8131814759544]}, "type": "Feature", "properties": {"Nivel": 3, "Form\u0103": "Lac", "marker-color": "#e55b5b", "Tip": "barancea", "Nume": "Lacul Barancea", "Varianta 1": {"Nume": "Lacul Barancea", "Limb\u0103": "Limba rom\u00e2n\u0103", "Hart\u0103": "ANCPI"}, "ID": 15947, "Jude\u021b": "Botosani"}}]}