{"type": "FeatureCollection", "name": "export_cucoaie.geojson", "features": [{"geometry": {"type": "Point", "coordinates": [22.5113803357369, 47.3949294587916]}, "type": "Feature", "properties": {"Nivel": 3, "Form\u0103": "\u00cen\u0103l\u021bime", "marker-color": "#e55b5b", "Tip": "cucoaie", "Nume": "Cucoaia", "Varianta 1": {"Nume": "Cucoaia", "Limb\u0103": "Limba rom\u00e2n\u0103", "Hart\u0103": "Geomil 25000"}, "ID": 6951, "Jude\u021b": "Bihor"}}]}