{"type": "FeatureCollection", "name": "export_fr\u00e2nceni.geojson", "features": [{"geometry": {"type": "Point", "coordinates": [23.6178389146998, 47.4005964296989]}, "type": "Feature", "properties": {"Nivel": 3, "Form\u0103": "Localitate", "marker-color": "#e55b5b", "Tip": "fr\u00e2nceni", "Nume": "Fr\u00e2ncenii Boiului", "Varianta 1": {"Nume": "Fr\u00e2ncenii Boiului", "Limb\u0103": "Limba rom\u00e2n\u0103", "Hart\u0103": "Geomil 25000"}, "ID": 9927, "Jude\u021b": "Maramures"}}, {"geometry": {"type": "Point", "coordinates": [23.6750909885977, 47.3217742683972]}, "type": "Feature", "properties": {"Nivel": 3, "Form\u0103": "Localitate", "marker-color": "#e55b5b", "Tip": "fr\u00e2nceni", "Nume": "Fr\u00e2ncenii de Piatra", "Varianta 1": {"Nume": "Fr\u00e2ncenii de Piatra", "Limb\u0103": "Limba rom\u00e2n\u0103", "Hart\u0103": "Geomil 25000"}, "ID": 6942, "Jude\u021b": "Salaj"}}]}