{"type": "FeatureCollection", "name": "export_com\u0103ni\u021ba.geojson", "features": [{"geometry": {"type": "Point", "coordinates": [23.841393997076, 44.5042494300191]}, "type": "Feature", "properties": {"Nivel": 3, "Form\u0103": "Vale", "marker-color": "#e55b5b", "Tip": "com\u0103ni\u021ba", "Nume": "Valea Com\u0103ni\u021ba", "Varianta 1": {"Nume": "Valea Com\u0103ni\u021ba", "Limb\u0103": "Limba rom\u00e2n\u0103", "Hart\u0103": "PDT"}, "ID": 4824, "Jude\u021b": "Dolj"}}, {"geometry": {"type": "Point", "coordinates": [24.3429686544402, 44.5647898197045]}, "type": "Feature", "properties": {"Nivel": 3, "Form\u0103": "Localitate", "marker-color": "#e55b5b", "Tip": "com\u0103ni\u021ba", "Nume": "Com\u0103ni\u021ba", "Varianta 2": {"Nume": "Comani\u021ba", "Limb\u0103": "Limba rom\u00e2n\u0103", "Hart\u0103": "PDT"}, "Varianta 1": {"Nume": "Com\u0103ni\u021ba", "Limb\u0103": "Limba rom\u00e2n\u0103", "Hart\u0103": "Geomil 25000"}, "ID": 9346, "Jude\u021b": "Olt"}}, {"geometry": {"type": "Point", "coordinates": [26.1979346797573, 45.0492810971757]}, "type": "Feature", "properties": {"Nivel": 3, "Form\u0103": "Vale", "marker-color": "#e55b5b", "Tip": "com\u0103ni\u021ba", "Nume": "Valea Com\u0103ni\u021ba", "Varianta 1": {"Nume": "Valea Com\u0103ni\u021ba", "Limb\u0103": "Limba rom\u00e2n\u0103", "Hart\u0103": "PDT"}, "ID": 10088, "Jude\u021b": "Prahova"}}]}