{"type": "FeatureCollection", "name": "export_onuca.geojson", "features": [{"geometry": {"type": "Point", "coordinates": [23.4387702558448, 46.9688027517713]}, "type": "Feature", "properties": {"Nivel": 3, "Form\u0103": "\u00cen\u0103l\u021bime", "marker-color": "#e55b5b", "Tip": "onuca", "Nume": "D\u00e2mbul Onuca", "Varianta 1": {"Nume": "D\u00e2mbul Onuca", "Limb\u0103": "Limba rom\u00e2n\u0103", "Hart\u0103": "ANCPI"}, "ID": 15872, "Jude\u021b": "Cluj"}}]}