{"type": "FeatureCollection", "name": "export_h\u00e2r\u0219u.geojson", "features": [{"geometry": {"type": "Point", "coordinates": [26.6638823001718, 45.1849422794158]}, "type": "Feature", "properties": {"Nivel": 3, "Form\u0103": "Vale", "marker-color": "#e55b5b", "Tip": "h\u00e2r\u0219u", "Nume": "Valea H\u00e2r\u0219u", "Varianta 1": {"Nume": "Valea H\u00e2r\u0219u", "Limb\u0103": "Limba rom\u00e2n\u0103", "Hart\u0103": "ANCPI"}, "ID": 15733, "Jude\u021b": "Buzau"}}, {"geometry": {"type": "Point", "coordinates": [22.8040144891048, 46.963192031797]}, "type": "Feature", "properties": {"Nivel": 3, "Form\u0103": "\u00cen\u0103l\u021bime", "marker-color": "#e55b5b", "Tip": "h\u00e2r\u0219u", "Nume": "V\u00e2rful H\u00e2r\u0219u", "Varianta 1": {"Nume": "V\u00e2rful H\u00e2r\u0219u", "Limb\u0103": "Limba rom\u00e2n\u0103", "Hart\u0103": "ANCPI"}, "ID": 15189, "Jude\u021b": "Cluj"}}, {"geometry": {"type": "Point", "coordinates": [24.505626135814, 44.7983215898141]}, "type": "Feature", "properties": {"Nivel": 3, "Form\u0103": "P\u0103dure", "marker-color": "#e55b5b", "Tip": "h\u00e2r\u0219u", "Nume": "P\u0103durea H\u00e2r\u0219u", "Varianta 1": {"Nume": "P\u0103durea H\u00e2r\u0219u", "Limb\u0103": "Limba rom\u00e2n\u0103", "Hart\u0103": "ANCPI"}, "ID": 15742, "Jude\u021b": "Olt"}}]}