{"type": "FeatureCollection", "name": "export_urluiasca.geojson", "features": [{"geometry": {"type": "Point", "coordinates": [24.3800298492866, 44.665575554422]}, "type": "Feature", "properties": {"Nivel": 3, "Form\u0103": "Localitate", "marker-color": "#e55b5b", "Tip": "urluiasca", "Nume": "Urluiasca", "Varianta 1": {"Nume": "Urluiasca", "Limb\u0103": "Limba rom\u00e2n\u0103", "Hart\u0103": "PDT"}, "ID": 14406, "Jude\u021b": "Olt"}}]}