{"type": "FeatureCollection", "name": "export_hurez.geojson", "features": [{"geometry": {"type": "Point", "coordinates": [24.951752340065, 45.8010466748323]}, "type": "Feature", "properties": {"Nivel": 2, "Form\u0103": "Localitate", "marker-color": "#e55b5b", "Tip": "hurez", "Nume": "Hurez", "Varianta 1": {"Nume": "Hurez", "Limb\u0103": "Limba rom\u00e2n\u0103", "Hart\u0103": "Geomil 25000"}, "ID": 11935, "Jude\u021b": "Brasov"}}, {"geometry": {"type": "Point", "coordinates": [23.2923528686887, 45.1526199169708]}, "type": "Feature", "properties": {"Nivel": 2, "Form\u0103": "Localitate", "marker-color": "#e55b5b", "Tip": "hurez", "Nume": "Hurez", "Varianta 1": {"Nume": "Hurez", "Limb\u0103": "Limba rom\u00e2n\u0103", "Hart\u0103": "Valahia-Moldova (1773-1774)"}, "ID": 12107, "Jude\u021b": "Gorj"}}, {"geometry": {"type": "Point", "coordinates": [22.837073327236, 47.4650255065195]}, "type": "Feature", "properties": {"Nivel": 2, "Form\u0103": "Localitate", "marker-color": "#e55b5b", "Tip": "hurez", "Nume": "Hurezu Mare", "Varianta 1": {"Nume": "Hurezu Mare", "Limb\u0103": "Limba rom\u00e2n\u0103", "Hart\u0103": "Geomil 25000"}, "ID": 12143, "Jude\u021b": "Satu Mare"}}, {"geometry": {"type": "Point", "coordinates": [22.1212927513049, 46.2284767700552]}, "type": "Feature", "properties": {"Nivel": 2, "Form\u0103": "\u00cen\u0103l\u021bime", "marker-color": "#e55b5b", "Tip": "hurez", "Nume": "V\u00e2rfu Hurezului", "Varianta 1": {"Nume": "V\u00e2rfu Hurezului", "Limb\u0103": "Limba rom\u00e2n\u0103", "Hart\u0103": "Geomil 25000"}, "ID": 12522, "Jude\u021b": "Arad"}}, {"geometry": {"type": "Point", "coordinates": [22.911885384158, 47.0707473098227]}, "type": "Feature", "properties": {"Nivel": 2, "Form\u0103": "Localitate", "marker-color": "#e55b5b", "Tip": "hurez", "Nume": "Hurez", "Varianta 2": {"Nume": "Hurez", "Limb\u0103": "Limba rom\u00e2n\u0103", "Hart\u0103": "Geomil 25000"}, "Varianta 1": {"Nume": "Hurez", "Limb\u0103": "Limba rom\u00e2n\u0103", "Hart\u0103": "PDT"}, "ID": 12786, "Jude\u021b": "Salaj"}}, {"geometry": {"type": "Point", "coordinates": [22.6181944414907, 47.1192805238461]}, "type": "Feature", "properties": {"Nivel": 3, "Form\u0103": "Altele", "marker-color": "#5b92e5", "Tip": "hurezi", "Nume": "La Hurezi", "Varianta 1": {"Nume": "La Hurezi", "Limb\u0103": "Limba rom\u00e2n\u0103", "Hart\u0103": "Geomil 25000"}, "ID": 11914, "Jude\u021b": "Salaj"}}, {"geometry": {"type": "Point", "coordinates": [23.9555449518022, 44.4704819626867]}, "type": "Feature", "properties": {"Nivel": 3, "Form\u0103": "Localitate", "marker-color": "#c9e55b", "Tip": "horezu", "Nume": "Horezu", "Varianta 1": {"Nume": "Horezu", "Limb\u0103": "Limba rom\u00e2n\u0103", "Hart\u0103": "Geomil 25000"}, "ID": 12234, "Jude\u021b": "Olt"}}, {"geometry": {"type": "Point", "coordinates": [25.4143993181247, 45.8667755942688]}, "type": "Feature", "properties": {"Nivel": 3, "Form\u0103": "\u00cen\u0103l\u021bime", "marker-color": "#c9e55b", "Tip": "horezu", "Nume": "V\u00e2rful Horezu", "Varianta 1": {"Nume": "V\u00e2rful Horezu", "Limb\u0103": "Limba rom\u00e2n\u0103", "Hart\u0103": "Geomil 25000"}, "ID": 12668, "Jude\u021b": "Brasov"}}, {"geometry": {"type": "Point", "coordinates": [23.9903312898037, 45.145759071621]}, "type": "Feature", "properties": {"Nivel": 3, "Form\u0103": "Localitate", "marker-color": "#c9e55b", "Tip": "horezu", "Nume": "Horezu", "Varianta 1": {"Nume": "Horezu", "Limb\u0103": "Limba rom\u00e2n\u0103", "Hart\u0103": "Geomil 25000"}, "ID": 12848, "Jude\u021b": "Valcea"}}, {"geometry": {"type": "Point", "coordinates": [26.9927471191391, 44.5872626860322]}, "type": "Feature", "properties": {"Nivel": 3, "Form\u0103": "Localitate", "marker-color": "#5be592", "Tip": "orezu", "Nume": "Orezu", "Varianta 2": {"Nume": "Orezu", "Limb\u0103": "Limba rom\u00e2n\u0103", "Hart\u0103": "Austriac\u0103"}, "Varianta 1": {"Nume": "Orezu", "Limb\u0103": "Limba rom\u00e2n\u0103", "Hart\u0103": "Geomil 25000"}, "ID": 12409, "Jude\u021b": "Ialomita"}}, {"geometry": {"type": "Point", "coordinates": [23.64580244078, 44.8014865680969]}, "type": "Feature", "properties": {"Nivel": 3, "Form\u0103": "Localitate", "marker-color": "#c95be5", "Tip": "hurezani", "Nume": "Hurezani", "Varianta 1": {"Nume": "Hurezani", "Limb\u0103": "Limba rom\u00e2n\u0103", "Hart\u0103": "Geomil 25000"}, "ID": 12678, "Jude\u021b": "Gorj"}}]}