{"type": "FeatureCollection", "name": "export_nedeiu.geojson", "features": [{"geometry": {"type": "Point", "coordinates": [23.3652092235162, 47.9499662687837]}, "type": "Feature", "properties": {"Nivel": 3, "Form\u0103": "\u00cen\u0103l\u021bime", "marker-color": "#e55b5b", "Tip": "nedeiu", "Nume": "V\u00e2rfu Nedeiu", "Varianta 1": {"Nume": "V\u00e2rfu Nedeiu", "Limb\u0103": "Limba rom\u00e2n\u0103", "Hart\u0103": "Geomil 25000"}, "ID": 4461, "Jude\u021b": "Satu Mare"}}]}