{"type": "FeatureCollection", "name": "export_\u0219mid\u0103.geojson", "features": [{"geometry": {"type": "Point", "coordinates": [21.9412560132422, 45.4390276699651]}, "type": "Feature", "properties": {"Nivel": 3, "Form\u0103": "Deal", "marker-color": "#e55b5b", "Tip": "\u0219mid\u0103", "Nume": "Dealul \u0218midea", "Varianta 1": {"Nume": "Dealul \u0218midea", "Limb\u0103": "Limba rom\u00e2n\u0103", "Hart\u0103": "Geomil 25000"}, "ID": 9424, "Jude\u021b": "Caras Severin"}}, {"geometry": {"type": "Point", "coordinates": [25.7493659283778, 47.1255815663555]}, "type": "Feature", "properties": {"Nivel": 3, "Form\u0103": "\u00cen\u0103l\u021bime", "marker-color": "#e55b5b", "Tip": "\u0219mid\u0103", "Nume": "\u0218mida Burcu\u021bului", "Varianta 1": {"Nume": "\u0218mida Burcu\u021bului", "Limb\u0103": "Limba rom\u00e2n\u0103", "Hart\u0103": "PDT"}, "ID": 15464, "Jude\u021b": "Neamt"}}]}