{"type": "FeatureCollection", "name": "export_vl\u0103\u0219cu\u021b\u0103.geojson", "features": [{"geometry": {"type": "Point", "coordinates": [24.8193712045687, 44.611312860195]}, "type": "Feature", "properties": {"Nivel": 2, "Form\u0103": "Vale", "marker-color": "#e55b5b", "Tip": "vl\u0103\u0219cu\u021b\u0103", "Nume": "Valea Vl\u0103\u0219cu\u021ba", "Varianta 1": {"Nume": "Valea Vl\u0103\u0219cu\u021ba", "Limb\u0103": "Limba rom\u00e2n\u0103", "Hart\u0103": "Geomil 25000"}, "ID": 11696, "Jude\u021b": "Arges"}}, {"geometry": {"type": "Point", "coordinates": [24.7756071782476, 44.5330489758899]}, "type": "Feature", "properties": {"Nivel": 2, "Form\u0103": "Localitate", "marker-color": "#e55b5b", "Tip": "vl\u0103\u0219cu\u021b\u0103", "Nume": "Vl\u0103\u0219cu\u021ba din Vale", "Varianta 1": {"Nume": "Vl\u0103\u0219cu\u021ba din Vale", "Limb\u0103": "Limba rom\u00e2n\u0103", "Hart\u0103": "PDT"}, "ID": 8335, "Jude\u021b": "Arges"}}]}