{"type": "FeatureCollection", "name": "export_h\u00e2r\u0219a.geojson", "features": [{"geometry": {"type": "Point", "coordinates": [26.1627764036147, 45.0400120283596]}, "type": "Feature", "properties": {"Nivel": 3, "Form\u0103": "Localitate", "marker-color": "#e55b5b", "Tip": "h\u00e2r\u0219a", "Nume": "H\u00e2r\u0219a", "Varianta 1": {"Nume": "H\u00e2r\u0219a", "Limb\u0103": "Limba rom\u00e2n\u0103", "Hart\u0103": "PDT"}, "ID": 14706, "Jude\u021b": "Prahova"}}]}