{"type": "FeatureCollection", "name": "export_c\u0103z\u0103ne\u0219ti.geojson", "features": [{"geometry": {"type": "Point", "coordinates": [24.5030006510949, 45.0268726509591]}, "type": "Feature", "properties": {"Nivel": 3, "Form\u0103": "Localitate", "marker-color": "#e55b5b", "Tip": "c\u0103z\u0103ne\u0219ti", "Nume": "K\u00e2zane\u0219ti", "Varianta 1": {"Nume": "K\u00e2zane\u0219ti", "Limb\u0103": "Limba rom\u00e2n\u0103", "Hart\u0103": "Austriac\u0103"}, "ID": 5827, "Jude\u021b": "Arges"}}, {"geometry": {"type": "Point", "coordinates": [22.512231688907, 46.1464493686923]}, "type": "Feature", "properties": {"Nivel": 3, "Form\u0103": "Localitate", "marker-color": "#e55b5b", "Tip": "c\u0103z\u0103ne\u0219ti", "Nume": "C\u0103z\u0103ne\u0219ti", "Varianta 1": {"Nume": "C\u0103z\u0103ne\u0219ti", "Limb\u0103": "Limba rom\u00e2n\u0103", "Hart\u0103": "Geomil 25000"}, "ID": 6229, "Jude\u021b": "Hunedoara"}}, {"geometry": {"type": "Point", "coordinates": [22.8904358725873, 44.7238000154546]}, "type": "Feature", "properties": {"Nivel": 3, "Form\u0103": "Localitate", "marker-color": "#e55b5b", "Tip": "c\u0103z\u0103ne\u0219ti", "Nume": "C\u0103z\u0103ne\u0219ti", "Varianta 2": {"Nume": "Kazane\u0219ti", "Limb\u0103": "Limba rom\u00e2n\u0103", "Hart\u0103": "Austriac\u0103"}, "Varianta 1": {"Nume": "C\u0103z\u0103ne\u0219ti", "Limb\u0103": "Limba rom\u00e2n\u0103", "Hart\u0103": "Geomil 25000"}, "ID": 8067, "Jude\u021b": "Mehedinti"}}, {"geometry": {"type": "Point", "coordinates": [24.3594417616067, 44.619533811242]}, "type": "Feature", "properties": {"Nivel": 3, "Form\u0103": "Localitate", "marker-color": "#e55b5b", "Tip": "c\u0103z\u0103ne\u0219ti", "Nume": "C\u0103z\u0103ne\u0219ti", "Varianta 1": {"Nume": "C\u0103z\u0103ne\u0219ti", "Limb\u0103": "Limba rom\u00e2n\u0103", "Hart\u0103": "Geomil 25000"}, "ID": 9350, "Jude\u021b": "Olt"}}, {"geometry": {"type": "Point", "coordinates": [24.2837044178236, 45.0546477602223]}, "type": "Feature", "properties": {"Nivel": 3, "Form\u0103": "Localitate", "marker-color": "#e55b5b", "Tip": "c\u0103z\u0103ne\u0219ti", "Nume": "C\u0103z\u0103ne\u0219ti", "Varianta 1": {"Nume": "C\u0103z\u0103ne\u0219ti", "Limb\u0103": "Limba rom\u00e2n\u0103", "Hart\u0103": "Geomil 25000"}, "ID": 9369, "Jude\u021b": "Valcea"}}, {"geometry": {"type": "Point", "coordinates": [27.5022577631304, 46.8690877695777]}, "type": "Feature", "properties": {"Nivel": 3, "Form\u0103": "Localitate", "marker-color": "#e55b5b", "Tip": "c\u0103z\u0103ne\u0219ti", "Nume": "C\u0103z\u0103ne\u0219ti", "Varianta 1": {"Nume": "C\u0103z\u0103ne\u0219ti", "Limb\u0103": "Limba rom\u00e2n\u0103", "Hart\u0103": "Geomil 25000"}, "ID": 9852, "Jude\u021b": "Vaslui"}}, {"geometry": {"type": "Point", "coordinates": [27.9355073644618, 45.8850857759392]}, "type": "Feature", "properties": {"Nivel": 3, "Form\u0103": "Vale", "marker-color": "#e55b5b", "Tip": "c\u0103z\u0103ne\u0219ti", "Nume": "Valea C\u0103z\u0103ne\u0219tilor", "Varianta 1": {"Nume": "Valea C\u0103z\u0103ne\u0219tilor", "Limb\u0103": "Limba rom\u00e2n\u0103", "Hart\u0103": "Geomil 25000"}, "ID": 11438, "Jude\u021b": "Galati"}}]}