{"type": "FeatureCollection", "name": "export_tocar.geojson", "features": [{"geometry": {"type": "Point", "coordinates": [27.9014620150219, 46.2209874679776]}, "type": "Feature", "properties": {"Nivel": 3, "Form\u0103": "Vale", "marker-color": "#e55b5b", "Tip": "tocar", "Nume": "Valea Tocarului", "Varianta 1": {"Nume": "Valea Tocarului", "Limb\u0103": "Limba rom\u00e2n\u0103", "Hart\u0103": "PDT"}, "ID": 14919, "Jude\u021b": "Vaslui"}}]}