{"type": "FeatureCollection", "name": "export_giorcotin.geojson", "features": [{"geometry": {"type": "Point", "coordinates": [23.260674708824, 44.4735134499762]}, "type": "Feature", "properties": {"Nivel": 3, "Form\u0103": "Vale", "marker-color": "#e55b5b", "Tip": "giorcotin", "Nume": "Valea Giorcotinului", "Varianta 1": {"Nume": "Valea Giorcotinului", "Limb\u0103": "Limba rom\u00e2n\u0103", "Hart\u0103": "ANCPI"}, "ID": 14538, "Jude\u021b": "Dolj"}}]}