{"type": "FeatureCollection", "name": "export_barc\u0103u.geojson", "features": [{"geometry": {"type": "Point", "coordinates": [22.7100165808812, 47.1091686025227]}, "type": "Feature", "properties": {"Nivel": 3, "Form\u0103": "Vale", "marker-color": "#e55b5b", "Tip": "barc\u0103u", "Nume": "R\u00e2u Barc\u0103u", "Varianta 1": {"Nume": "R\u00e2u Barc\u0103u", "Limb\u0103": "Limba rom\u00e2n\u0103", "Hart\u0103": "Geomil 25000"}, "ID": 11913, "Jude\u021b": "Salaj"}}, {"geometry": {"type": "Point", "coordinates": [21.8688156323801, 46.616762708685]}, "type": "Feature", "properties": {"Nivel": 3, "Form\u0103": "Vale", "marker-color": "#e55b5b", "Tip": "barc\u0103u", "Nume": "P\u00e2r\u00e2u Barc\u0103u", "Varianta 1": {"Nume": "P\u00e2r\u00e2u Barc\u0103u", "Limb\u0103": "Limba rom\u00e2n\u0103", "Hart\u0103": "Geomil 25000"}, "ID": 13931, "Jude\u021b": "Arad"}}]}