{"type": "FeatureCollection", "name": "export_varadi.geojson", "features": [{"geometry": {"type": "Point", "coordinates": [23.1631723355894, 47.3640058121898]}, "type": "Feature", "properties": {"Nivel": 4, "Form\u0103": "Deal", "marker-color": "#e55b5b", "Tip": "varadi", "Nume": "Dealul Varadi", "Varianta 1": {"Nume": "Dealul Varadi", "Limb\u0103": "Limba rom\u00e2n\u0103", "Hart\u0103": "Geomil 25000"}, "ID": 6947, "Jude\u021b": "Salaj"}}]}