{"type": "FeatureCollection", "name": "export_urdea.geojson", "features": [{"geometry": {"type": "Point", "coordinates": [24.7505301321768, 45.5046313790407]}, "type": "Feature", "properties": {"Nivel": 3, "Form\u0103": "\u00cen\u0103l\u021bime", "marker-color": "#e55b5b", "Tip": "urdea", "Nume": "Muntele Urdea", "Varianta 1": {"Nume": "Muntele Urdea", "Limb\u0103": "Limba rom\u00e2n\u0103", "Hart\u0103": "Mun\u021bii no\u0219tri"}, "ID": 15176, "Jude\u021b": "Arges"}}]}