{"type": "FeatureCollection", "name": "export_barac\u0103.geojson", "features": [{"geometry": {"type": "Point", "coordinates": [22.8168527192767, 44.8039607884997]}, "type": "Feature", "properties": {"Nivel": 3, "Form\u0103": "\u00cen\u0103l\u021bime", "marker-color": "#e55b5b", "Tip": "barac\u0103", "Nume": "Culmea Barac\u0103", "Varianta 1": {"Nume": "Culmea Barac\u0103", "Limb\u0103": "Limba rom\u00e2n\u0103", "Hart\u0103": "Geomil 25000"}, "ID": 12715, "Jude\u021b": "Mehedinti"}}]}