{"type": "FeatureCollection", "name": "export_orezu.geojson", "features": [{"geometry": {"type": "Point", "coordinates": [26.9927471191391, 44.5872626860322]}, "type": "Feature", "properties": {"Nivel": 3, "Form\u0103": "Localitate", "marker-color": "#e55b5b", "Tip": "orezu", "Nume": "Orezu", "Varianta 2": {"Nume": "Orezu", "Limb\u0103": "Limba rom\u00e2n\u0103", "Hart\u0103": "Austriac\u0103"}, "Varianta 1": {"Nume": "Orezu", "Limb\u0103": "Limba rom\u00e2n\u0103", "Hart\u0103": "Geomil 25000"}, "ID": 12409, "Jude\u021b": "Ialomita"}}]}