{"type": "FeatureCollection", "name": "export_b\u0103c\u0103nii.geojson", "features": [{"geometry": {"type": "Point", "coordinates": [24.9990646997149, 44.330365834292]}, "type": "Feature", "properties": {"Nivel": 3, "Form\u0103": "Vale", "marker-color": "#e55b5b", "Tip": "b\u0103c\u0103nii", "Nume": "Valea Scoroaica B\u0103c\u0103niile", "Varianta 1": {"Nume": "Valea Scoroaica B\u0103c\u0103niile", "Limb\u0103": "Limba rom\u00e2n\u0103", "Hart\u0103": "PDT"}, "ID": 14823, "Jude\u021b": "Teleorman"}}]}