{"type": "FeatureCollection", "name": "export_mo\u021b.geojson", "features": [{"geometry": {"type": "Point", "coordinates": [22.2714859901379, 46.4871029812987]}, "type": "Feature", "properties": {"Nivel": 3, "Form\u0103": "\u00cen\u0103l\u021bime", "marker-color": "#e55b5b", "Tip": "mo\u021b", "Nume": "D\u00e2mbu Mo\u021bului", "Varianta 1": {"Nume": "D\u00e2mbu Mo\u021bului", "Limb\u0103": "Limba rom\u00e2n\u0103", "Hart\u0103": "Geomil 25000"}, "ID": 13925, "Jude\u021b": "Arad"}}, {"geometry": {"type": "Point", "coordinates": [22.3744140238015, 46.3382688693006]}, "type": "Feature", "properties": {"Nivel": 3, "Form\u0103": "Deal", "marker-color": "#e55b5b", "Tip": "mo\u021b", "Nume": "Dealul Mo\u021bului", "Varianta 1": {"Nume": "Dealul Mo\u021bului", "Limb\u0103": "Limba rom\u00e2n\u0103", "Hart\u0103": "PDT"}, "ID": 5607, "Jude\u021b": "Arad"}}, {"geometry": {"type": "Point", "coordinates": [22.3925094195056, 46.08152300373]}, "type": "Feature", "properties": {"Nivel": 3, "Form\u0103": "Deal", "marker-color": "#e55b5b", "Tip": "mo\u021b", "Nume": "Dealul Mo\u021bului", "Varianta 1": {"Nume": "Dealul Mo\u021bului", "Limb\u0103": "Limba rom\u00e2n\u0103", "Hart\u0103": "Geomil 25000"}, "ID": 10937, "Jude\u021b": "Arad"}}, {"geometry": {"type": "Point", "coordinates": [22.2693406415937, 46.4695514999965]}, "type": "Feature", "properties": {"Nivel": 3, "Form\u0103": "Deal", "marker-color": "#e55b5b", "Tip": "mo\u021b", "Nume": "Dealul Mo\u021bului", "Varianta 1": {"Nume": "Dealul Mo\u021bului", "Limb\u0103": "Limba rom\u00e2n\u0103", "Hart\u0103": "PDT"}, "ID": 13505, "Jude\u021b": "Arad"}}, {"geometry": {"type": "Point", "coordinates": [21.9731886579362, 46.5461949457124]}, "type": "Feature", "properties": {"Nivel": 3, "Form\u0103": "Vale", "marker-color": "#e55b5b", "Tip": "mo\u021b", "Nume": "P\u00e2r\u00e2u Mo\u021bului", "Varianta 1": {"Nume": "P\u00e2r\u00e2u Mo\u021bului", "Limb\u0103": "Limba rom\u00e2n\u0103", "Hart\u0103": "Geomil 25000"}, "ID": 14255, "Jude\u021b": "Arad"}}, {"geometry": {"type": "Point", "coordinates": [22.264966109036, 46.4169030686373]}, "type": "Feature", "properties": {"Nivel": 3, "Form\u0103": "Vale", "marker-color": "#e55b5b", "Tip": "mo\u021b", "Nume": "P\u00e2r\u00e2ul Mo\u021bului", "Varianta 1": {"Nume": "P\u00e2r\u00e2ul Mo\u021bului", "Limb\u0103": "Limba rom\u00e2n\u0103", "Hart\u0103": "PDT"}, "ID": 4202, "Jude\u021b": "Arad"}}, {"geometry": {"type": "Point", "coordinates": [22.591049977801, 46.6079946511312]}, "type": "Feature", "properties": {"Nivel": 3, "Form\u0103": "Altele", "marker-color": "#e55b5b", "Tip": "mo\u021b", "Nume": "T\u00e2rni\u021ba Mo\u021bului", "Varianta 1": {"Nume": "T\u00e2rni\u021ba Mo\u021bului", "Limb\u0103": "Limba rom\u00e2n\u0103", "Hart\u0103": "PDT"}, "ID": 9404, "Jude\u021b": "Bihor"}}, {"geometry": {"type": "Point", "coordinates": [22.6601339524822, 46.5061348085497]}, "type": "Feature", "properties": {"Nivel": 3, "Form\u0103": "Vale", "marker-color": "#e55b5b", "Tip": "mo\u021b", "Nume": "Valea Hoanca Mo\u021bului", "Varianta 1": {"Nume": "Valea Hoanca Mo\u021bului", "Limb\u0103": "Limba rom\u00e2n\u0103", "Hart\u0103": "Geomil 25000"}, "ID": 7276, "Jude\u021b": "Bihor"}}, {"geometry": {"type": "Point", "coordinates": [22.7358639643752, 46.5902777133115]}, "type": "Feature", "properties": {"Nivel": 3, "Form\u0103": "\u00cen\u0103l\u021bime", "marker-color": "#e55b5b", "Tip": "mo\u021b", "Nume": "V\u00e2rfu Biserica Mo\u021bului", "Varianta 1": {"Nume": "V\u00e2rfu Biserica Mo\u021bului", "Limb\u0103": "Limba rom\u00e2n\u0103", "Hart\u0103": "Geomil 25000"}, "ID": 5618, "Jude\u021b": "Bihor"}}]}