{"type": "FeatureCollection", "name": "export_belcina.geojson", "features": [{"geometry": {"type": "Point", "coordinates": [25.6190397820543, 43.6860051509197]}, "type": "Feature", "properties": {"Nivel": 3, "Form\u0103": "Vale", "marker-color": "#e55b5b", "Tip": "belcina", "Nume": "Valea Belcina", "Varianta 1": {"Nume": "Valea Belcina", "Limb\u0103": "Limba rom\u00e2n\u0103", "Hart\u0103": "PDT"}, "ID": 15453, "Jude\u021b": "Teleorman"}}]}