{"type": "FeatureCollection", "name": "export_jeg\u0103lia.geojson", "features": [{"geometry": {"type": "Point", "coordinates": [27.619115691996, 44.3143625530615]}, "type": "Feature", "properties": {"Nivel": 3, "Form\u0103": "Vale", "marker-color": "#e55b5b", "Tip": "jeg\u0103lia", "Nume": "Valea Jeg\u0103lia", "Varianta 1": {"Nume": "Valea Jeg\u0103lia", "Limb\u0103": "Limba rom\u00e2n\u0103", "Hart\u0103": "Geomil 25000"}, "ID": 12487, "Jude\u021b": "Calarasi"}}]}