{"type": "FeatureCollection", "name": "export_ciocanele.geojson", "features": [{"geometry": {"type": "Point", "coordinates": [23.4477181020425, 44.5137226880649]}, "type": "Feature", "properties": {"Nivel": 3, "Form\u0103": "Localitate", "marker-color": "#e55b5b", "Tip": "ciocanele", "Nume": "Ciocanele", "Varianta 1": {"Nume": "Ciocanele", "Limb\u0103": "Limba rom\u00e2n\u0103", "Hart\u0103": "ANCPI"}, "ID": 16004, "Jude\u021b": "Dolj"}}]}