{"type": "FeatureCollection", "name": "export_spoitori.geojson", "features": [{"geometry": {"type": "Point", "coordinates": [26.4932676731631, 44.270586058597]}, "type": "Feature", "properties": {"Nivel": 3, "Form\u0103": "\u00cen\u0103l\u021bime", "marker-color": "#e55b5b", "Tip": "spoitori", "Nume": "Movila Spoitorilor", "Varianta 1": {"Nume": "Movila Spoitorilor", "Limb\u0103": "Limba rom\u00e2n\u0103", "Hart\u0103": "PDT"}, "ID": 3763, "Jude\u021b": "Calarasi"}}]}