{"type": "FeatureCollection", "name": "export_voevod.geojson", "features": [{"geometry": {"type": "Point", "coordinates": [23.7194491480806, 44.6635280190513]}, "type": "Feature", "properties": {"Nivel": 3, "Form\u0103": "Deal", "marker-color": "#e55b5b", "Tip": "voevod", "Nume": "Dealul Voievodului", "Varianta 1": {"Nume": "Dealul Voievodului", "Limb\u0103": "Limba rom\u00e2n\u0103", "Hart\u0103": "Geomil 25000"}, "ID": 11030, "Jude\u021b": "Dolj"}}]}