{"type": "FeatureCollection", "name": "export_curcan.geojson", "features": [{"geometry": {"type": "Point", "coordinates": [27.1860995656761, 47.5794070916475]}, "type": "Feature", "properties": {"Nivel": 2, "Form\u0103": "Deal", "marker-color": "#e55b5b", "Tip": "curcan", "Nume": "Dealul Podi\u0219ul Curcanului", "Varianta 1": {"Nume": "Dealul Podi\u0219ul Curcanului", "Limb\u0103": "Limba rom\u00e2n\u0103", "Hart\u0103": "Geomil 25000"}, "ID": 2369, "Jude\u021b": "Botosani"}}, {"geometry": {"type": "Point", "coordinates": [27.5340175584742, 44.2205268562361]}, "type": "Feature", "properties": {"Nivel": 2, "Form\u0103": "Ap\u0103-deal-c\u00e2mpie", "marker-color": "#e55b5b", "Tip": "curcan", "Nume": "Privalul Curcanu", "Varianta 1": {"Nume": "Privalul Curcanu", "Limb\u0103": "Limba rom\u00e2n\u0103", "Hart\u0103": "PDT"}, "ID": 3294, "Jude\u021b": "Calarasi"}}, {"geometry": {"type": "Point", "coordinates": [25.7095962007175, 44.1314755160182]}, "type": "Feature", "properties": {"Nivel": 3, "Form\u0103": "Vale", "marker-color": "#5be5e5", "Tip": "curc\u0103", "Nume": "Valea Curcii", "Varianta 1": {"Nume": "Valea Curcii", "Limb\u0103": "Limba rom\u00e2n\u0103", "Hart\u0103": "PDT"}, "ID": 4220, "Jude\u021b": "Teleorman"}}]}