{"type": "FeatureCollection", "name": "export_ursoaic\u0103.geojson", "features": [{"geometry": {"type": "Point", "coordinates": [22.4927399682628, 46.0481779940436]}, "type": "Feature", "properties": {"Nivel": 3, "Form\u0103": "Deal", "Tip": "ursoaic\u0103", "Nume": "Dealu Ursoaicii", "Varianta 1": {"Nume": "Dealu Ursoaicii", "Limb\u0103": "Limba rom\u00e2n\u0103", "Hart\u0103": "Geomil 25000"}, "ID": 945, "Jude\u021b": "Hunedoara"}}, {"geometry": {"type": "Point", "coordinates": [26.0239578813116, 47.2146555154081]}, "type": "Feature", "properties": {"Nivel": 3, "Form\u0103": "\u00cen\u0103l\u021bime", "Tip": "ursoaic\u0103", "Nume": "Ursoaica", "Varianta 1": {"Nume": "Ursoaica", "Limb\u0103": "Limba rom\u00e2n\u0103", "Hart\u0103": "Geomil 25000"}, "ID": 2063, "Jude\u021b": "Neamt"}}, {"geometry": {"type": "Point", "coordinates": [25.6574811262301, 44.4467822638515]}, "type": "Feature", "properties": {"Nivel": 3, "Form\u0103": "Lac", "Tip": "ursoaic\u0103", "Nume": "Lacul Ursoaicei", "Varianta 1": {"Nume": "Lacul Ursoaicei", "Limb\u0103": "Limba rom\u00e2n\u0103", "Hart\u0103": "PDT"}, "ID": 3735, "Jude\u021b": "Giurgiu"}}, {"geometry": {"type": "Point", "coordinates": [26.1200821551595, 47.8949186988055]}, "type": "Feature", "properties": {"Nivel": 3, "Form\u0103": "Vale", "Tip": "ursoaic\u0103", "Nume": "P\u00e2r\u00e2ul Ursoaicei", "Varianta 1": {"Nume": "P\u00e2r\u00e2ul Ursoaicei", "Limb\u0103": "Limba rom\u00e2n\u0103", "Hart\u0103": "PDT"}, "ID": 7259, "Jude\u021b": "Suceava"}}, {"geometry": {"type": "Point", "coordinates": [24.4847112945654, 44.950330686144]}, "type": "Feature", "properties": {"Nivel": 3, "Form\u0103": "Vale", "Tip": "ursoaic\u0103", "Nume": "Valea Ursoaica", "Varianta 1": {"Nume": "Valea Ursoaica", "Limb\u0103": "Limba rom\u00e2n\u0103", "Hart\u0103": "PDT"}, "ID": 13526, "Jude\u021b": "Valcea"}}]}