{"type": "FeatureCollection", "name": "export_bivola\u0219.geojson", "features": [{"geometry": {"type": "Point", "coordinates": [26.2363641200338, 48.0460227576479]}, "type": "Feature", "properties": {"Nivel": 4, "Form\u0103": "Deal", "marker-color": "#e55b5b", "Tip": "bivola\u0219", "Nume": "Dealul Bivola\u0219ului", "Varianta 1": {"Nume": "Dealul Bivola\u0219ului", "Limb\u0103": "Limba rom\u00e2n\u0103", "Hart\u0103": "Geomil 25000"}, "ID": 4897, "Jude\u021b": "Botosani"}}]}