{"type": "FeatureCollection", "name": "export_lingurar.geojson", "features": [{"geometry": {"type": "Point", "coordinates": [26.5881880207811, 47.4164654220801]}, "type": "Feature", "properties": {"Nivel": 4, "Form\u0103": "Deal", "marker-color": "#e55b5b", "Tip": "lingurar", "Nume": "Dealul Lingurarului", "Varianta 1": {"Nume": "Dealul Lingurarului", "Limb\u0103": "Limba rom\u00e2n\u0103", "Hart\u0103": "Moldova (1892-1898)"}, "ID": 14047, "Jude\u021b": "Suceava"}}]}