{"type": "FeatureCollection", "name": "export_chicioara.geojson", "features": [{"geometry": {"type": "Point", "coordinates": [24.5410808554077, 45.1513247056835]}, "type": "Feature", "properties": {"Nivel": 3, "Form\u0103": "Deal", "marker-color": "#e55b5b", "Tip": "chicioara", "Nume": "Dealul Chicioara", "Varianta 1": {"Nume": "Dealul Chicioara", "Limb\u0103": "Limba rom\u00e2n\u0103", "Hart\u0103": "Geomil 25000"}, "ID": 13208, "Jude\u021b": "Arges"}}, {"geometry": {"type": "Point", "coordinates": [24.2356846255526, 45.1347688076803]}, "type": "Feature", "properties": {"Nivel": 3, "Form\u0103": "Localitate", "marker-color": "#e55b5b", "Tip": "chicioara", "Nume": "Chicioara", "Varianta 1": {"Nume": "Chicioara", "Limb\u0103": "Limba rom\u00e2n\u0103", "Hart\u0103": "PDT"}, "ID": 13663, "Jude\u021b": "Valcea"}}, {"geometry": {"type": "Point", "coordinates": [21.8635702624402, 46.2796125267305]}, "type": "Feature", "properties": {"Nivel": 3, "Form\u0103": "Deal", "marker-color": "#e55b5b", "Tip": "chicioara", "Nume": "Dealu Chicioara", "Varianta 1": {"Nume": "Dealu Chiciora", "Limb\u0103": "Limba rom\u00e2n\u0103", "Hart\u0103": "Geomil 25000"}, "ID": 13985, "Jude\u021b": "Arad"}}]}