{"type": "FeatureCollection", "name": "export_zamca_(cet\u0103\u021buie).geojson", "features": [{"geometry": {"type": "Point", "coordinates": [26.1501658560559, 47.7667745907648]}, "type": "Feature", "properties": {"Nivel": 2, "Form\u0103": "\u00cen\u0103l\u021bime", "marker-color": "#e55b5b", "Tip": "zamca (cet\u0103\u021buie)", "Nume": "Zamci\u0219", "Varianta 2": {"Nume": "Dealul Zomca", "Limb\u0103": "Limba rom\u00e2n\u0103", "Hart\u0103": "Geomil 25000"}, "Varianta 1": {"Nume": "Zamci\u0219", "Limb\u0103": "Limba rom\u00e2n\u0103", "Hart\u0103": "PDT"}, "ID": 12063, "Jude\u021b": "Suceava"}}, {"geometry": {"type": "Point", "coordinates": [25.9352480125447, 47.6211710798088]}, "type": "Feature", "properties": {"Nivel": 2, "Form\u0103": "Deal", "marker-color": "#e55b5b", "Tip": "zamca (cet\u0103\u021buie)", "Nume": "Dealul Zamca", "Varianta 1": {"Nume": "Dealul Zamca", "Limb\u0103": "Limba rom\u00e2n\u0103", "Hart\u0103": "Geomil 25000"}, "ID": 12066, "Jude\u021b": "Suceava"}}, {"geometry": {"type": "Point", "coordinates": [26.488094244134, 48.1642780797539]}, "type": "Feature", "properties": {"Nivel": 2, "Form\u0103": "Altele", "marker-color": "#e55b5b", "Tip": "zamca (cet\u0103\u021buie)", "Nume": "La Zamca", "Varianta 1": {"Nume": "La Zamca", "Limb\u0103": "Limba rom\u00e2n\u0103", "Hart\u0103": "Geomil 25000"}, "ID": 13586, "Jude\u021b": "Botosani"}}, {"geometry": {"type": "Point", "coordinates": [26.6015067514164, 47.8477656475172]}, "type": "Feature", "properties": {"Nivel": 2, "Form\u0103": "Deal", "marker-color": "#e55b5b", "Tip": "zamca (cet\u0103\u021buie)", "Nume": "Dealul Zamca", "Varianta 1": {"Nume": "Dealul Zamca", "Limb\u0103": "Limba rom\u00e2n\u0103", "Hart\u0103": "Geomil 25000"}, "ID": 14096, "Jude\u021b": "Botosani"}}]}