{"type": "FeatureCollection", "name": "export_g\u00e2nsac.geojson", "features": [{"geometry": {"type": "Point", "coordinates": [24.08157008296, 43.9269297434023]}, "type": "Feature", "properties": {"Nivel": 3, "Form\u0103": "Vale", "marker-color": "#e55b5b", "Tip": "g\u00e2nsac", "Nume": "Valea G\u00e2nsacului", "Varianta 1": {"Nume": "Valea G\u00e2nsacului", "Limb\u0103": "Limba rom\u00e2n\u0103", "Hart\u0103": "Geomil 25000"}, "ID": 1276, "Jude\u021b": "Dolj"}}, {"geometry": {"type": "Point", "coordinates": [24.3271181735416, 44.2153211689768]}, "type": "Feature", "properties": {"Nivel": 3, "Form\u0103": "Vale", "marker-color": "#e55b5b", "Tip": "g\u00e2nsac", "Nume": "Valea G\u00e2nsacului", "Varianta 1": {"Nume": "Valea G\u00e2nsacului", "Limb\u0103": "Limba rom\u00e2n\u0103", "Hart\u0103": "Geomil 25000"}, "ID": 3008, "Jude\u021b": "Olt"}}, {"geometry": {"type": "Point", "coordinates": [23.9420229192748, 43.9450306383115]}, "type": "Feature", "properties": {"Nivel": 3, "Form\u0103": "Deal", "marker-color": "#e55b5b", "Tip": "g\u00e2nsac", "Nume": "Dealul G\u00e2nsacului", "Varianta 1": {"Nume": "Dealul G\u00e2nsacului", "Limb\u0103": "Limba rom\u00e2n\u0103", "Hart\u0103": "Geomil 25000"}, "ID": 11605, "Jude\u021b": "Dolj"}}]}