{"type": "FeatureCollection", "name": "export_t\u0103l\u0103beasca.geojson", "features": [{"geometry": {"type": "Point", "coordinates": [27.609320302532, 45.5566731793136]}, "type": "Feature", "properties": {"Nivel": 3, "Form\u0103": "Altele", "marker-color": "#e55b5b", "Tip": "t\u0103l\u0103beasca", "Nume": "T\u0103l\u0103basca", "Varianta 1": {"Nume": "T\u0103l\u0103basca", "Limb\u0103": "Limba rom\u00e2n\u0103", "Hart\u0103": "PDT"}, "ID": 3528, "Jude\u021b": "Galati"}}]}