{"type": "FeatureCollection", "name": "export_malko\u00e7.geojson", "features": [{"geometry": {"type": "Point", "coordinates": [27.7728300472296, 47.0739250822783]}, "type": "Feature", "properties": {"Nivel": 3, "Form\u0103": "Vale", "marker-color": "#e55b5b", "Tip": "malcoci", "Nume": "Valea Malcoci", "Varianta 1": {"Nume": "Valea Malcoci", "Limb\u0103": "Limba rom\u00e2n\u0103", "Hart\u0103": "PDT"}, "ID": 14925, "Jude\u021b": "Iasi"}}]}