{"type": "FeatureCollection", "name": "export_cobuza.geojson", "features": [{"geometry": {"type": "Point", "coordinates": [27.7614436486017, 46.9460750019445]}, "type": "Feature", "properties": {"Nivel": 3, "Form\u0103": "P\u0103dure", "marker-color": "#e55b5b", "Tip": "cobuza", "Nume": "P\u0103durea Cobuza", "Varianta 1": {"Nume": "P\u0103durea Cobuza", "Limb\u0103": "Limba rom\u00e2n\u0103", "Hart\u0103": "ANCPI"}, "ID": 14914, "Jude\u021b": "Iasi"}}]}