{"type": "FeatureCollection", "name": "export_stupinea.geojson", "features": [{"geometry": {"type": "Point", "coordinates": [24.3376813840599, 44.6857918801591]}, "type": "Feature", "properties": {"Nivel": 4, "Form\u0103": "Deal", "marker-color": "#e55b5b", "Tip": "stupinea", "Nume": "Dealu Stupineaua", "Varianta 1": {"Nume": "Dealu Stupineaua", "Limb\u0103": "Limba rom\u00e2n\u0103", "Hart\u0103": "Geomil 25000"}, "ID": 3060, "Jude\u021b": "Olt"}}]}