{"type": "FeatureCollection", "name": "export_jidoafc\u0103.geojson", "features": [{"geometry": {"type": "Point", "coordinates": [25.6894179341872, 47.2343394458284]}, "type": "Feature", "properties": {"Nivel": 4, "Form\u0103": "Poian\u0103", "marker-color": "#e55b5b", "Tip": "jidoafc\u0103", "Nume": "Poiana Jidoafcei", "Varianta 1": {"Nume": "Poiana Jidoafcei", "Limb\u0103": "Limba rom\u00e2n\u0103", "Hart\u0103": "PDT"}, "ID": 6401, "Jude\u021b": "Suceava"}}]}