{"type": "FeatureCollection", "name": "export_tocman.geojson", "features": [{"geometry": {"type": "Point", "coordinates": [27.5737887212185, 46.7270911210162]}, "type": "Feature", "properties": {"Nivel": 3, "Form\u0103": "Localitate", "marker-color": "#e55b5b", "Tip": "t\u0103gm\u0103ne\u0219ti", "Nume": "T\u0103gm\u0103ne\u0219ti", "Varianta 1": {"Nume": "T\u0103gm\u0103ne\u0219ti", "Limb\u0103": "Limba rom\u00e2n\u0103", "Hart\u0103": "PDT"}, "ID": 14643, "Jude\u021b": "Vaslui"}}]}