{"type": "FeatureCollection", "name": "export_jderi.geojson", "features": [{"geometry": {"type": "Point", "coordinates": [23.2145499867932, 45.4200825857512]}, "type": "Feature", "properties": {"Nivel": 2, "Form\u0103": "Vale", "marker-color": "#e55b5b", "Tip": "jderi", "Nume": "Valea Jderi", "Varianta 1": {"Nume": "Valea Jderi", "Limb\u0103": "Limba rom\u00e2n\u0103", "Hart\u0103": "Geomil 25000"}, "ID": 1197, "Jude\u021b": "Hunedoara"}}]}