{"type": "FeatureCollection", "name": "export_jderi.geojson", "features": [{"geometry": {"type": "Point", "coordinates": [23.2145499867932, 45.4200825857512]}, "type": "Feature", "properties": {"Nivel": 2, "Form\u0103": "Vale", "marker-color": "#5be5e5", "Tip": "jderi", "Nume": "Valea Jderi", "Varianta 1": {"Nume": "Valea Jderi", "Limb\u0103": "Limba rom\u00e2n\u0103", "Hart\u0103": "Geomil 25000"}, "ID": 1197, "Jude\u021b": "Hunedoara"}}, {"geometry": {"type": "Point", "coordinates": [24.6221090214942, 47.8068302947342]}, "type": "Feature", "properties": {"Nivel": 3, "Form\u0103": "Vale", "marker-color": "#e55b5b", "Tip": "jder", "Nume": "P\u00e2r\u00e2ul Jderului", "Varianta 1": {"Nume": "P\u00e2r\u00e2ul Jderului", "Limb\u0103": "Limba rom\u00e2n\u0103", "Hart\u0103": "Mun\u021bii no\u0219tri"}, "ID": 15142, "Jude\u021b": "Maramures"}}, {"geometry": {"type": "Point", "coordinates": [26.3924598159574, 45.6887617782899]}, "type": "Feature", "properties": {"Nivel": 3, "Form\u0103": "Vale", "marker-color": "#e55b5b", "Tip": "jder", "Nume": "Jderul", "Varianta 1": {"Nume": "Jderul", "Limb\u0103": "Limba rom\u00e2n\u0103", "Hart\u0103": "Mun\u021bii no\u0219tri"}, "ID": 15203, "Jude\u021b": "Vrancea"}}]}