{"type": "FeatureCollection", "name": "export_bulg\u0103reni.geojson", "features": [{"geometry": {"type": "Point", "coordinates": [25.1965269298111, 44.3381539964326]}, "type": "Feature", "properties": {"Nivel": 3, "Form\u0103": "Localitate", "marker-color": "#e55b5b", "Tip": "bulg\u0103reni", "Nume": "Bulg\u0103reni", "Varianta 1": {"Nume": "Bulg\u0103reni", "Limb\u0103": "Limba rom\u00e2n\u0103", "Hart\u0103": "PDT"}, "ID": 9033, "Jude\u021b": "Teleorman"}}]}