{"type": "FeatureCollection", "name": "export_c\u0103z\u0103noaia.geojson", "features": [{"geometry": {"type": "Point", "coordinates": [25.0735679042783, 45.240942250912]}, "type": "Feature", "properties": {"Nivel": 3, "Form\u0103": "Altele", "marker-color": "#e55b5b", "Tip": "c\u0103z\u0103noaia", "Nume": "R\u00e2pa C\u0103z\u0103naia", "Varianta 1": {"Nume": "R\u00e2pa C\u0103z\u0103naia", "Limb\u0103": "Limba rom\u00e2n\u0103", "Hart\u0103": "PDT"}, "ID": 5057, "Jude\u021b": "Arges"}}]}